Internship_IITH/general_linear_regressor_V1.0/fixed_64_mult.v
module fixed_64_mult(
    input signed [31:0] a_in,    // Input operand A (Q24.8 format)
    input signed [31:0] b_in,    // Input operand B (Q24.8 format)
    output signed [63:0] p_out,  // Product P (Q55.8 format)
    output logic overflow        // Flag for overflow detection
);

    localparam integer FRACT_BITS = 8;
    wire signed [63:0] product_full;

    assign product_full = a_in * b_in;
    assign p_out = product_full >>> FRACT_BITS;

    assign overflow = 1'b0;

endmodule

Internship_IITH/Default_func/Top.v
module Top(
    input clk,
    input rst_n,
    input start_func,
    input signed [31:0] x_in,
    output reg signed [63:0] y_out,
    output logic func_done,
    output logic overflow
);

// The default Function is assumed to be X^2 + 4x - 1

localparam STATE_IDLE       = 2'b00;
localparam STATE_INIT       = 2'b01;
localparam STATE_COMPUTE    = 2'b10;
localparam STATE_DONE       = 2'b11;
localparam MINUS_ONE        = 64'hFFFFFFFFFFFFFF00;

reg [1:0] curr_state;
reg [1:0] next_state;
reg compute_done ;
reg signed [31:0] x_val;
reg signed [63:0] four_x;
reg signed [63:0] compute_result;

wire signed [63:0] x_square;
wire overflow_x_square;

always @(*) begin
    next_state = curr_state;
    case (curr_state)
        STATE_IDLE      : begin if (start_func)  next_state = STATE_INIT; end
        STATE_INIT      : begin next_state = STATE_COMPUTE; end
        STATE_COMPUTE   : begin if (compute_done) next_state = STATE_DONE; end
        STATE_DONE      : begin if (!start_func) next_state = STATE_IDLE; end
        default         : begin next_state = STATE_IDLE; end
    endcase
    four_x = x_val << 2; // SIGN EXTENED
    compute_result = x_square + four_x + MINUS_ONE;  // Q56.8 format
end

always_ff @(posedge clk, negedge rst_n) begin 
    if (!rst_n) begin
        curr_state  <= STATE_IDLE;
        func_done   <= 1'b0;
        x_val       <= 32'd0;   
        y_out       <= 64'd0;
        compute_done <= 1'b0;
        overflow    <= 1'b0;
    end else begin 
        curr_state <= next_state;
        case (curr_state)
            STATE_IDLE : begin
                // DO NOTHING
                func_done <= 1'b0;
                compute_done <= 1'b0;   
            end  
            STATE_INIT : begin
                x_val <= x_in;
                y_out <= 64'd0;
                func_done <= 1'b0;
                compute_done <= 1'b0;   
            end
            STATE_COMPUTE: begin 
                y_out <= compute_result;
                compute_done <= 1'b1;
                overflow <= overflow_x_square;
            end
            STATE_DONE : begin 
                func_done <= 1'b1;
            end
        endcase
    end 
end

fixed_64_mult inst (   // calculate x^2
    .a_in(x_val),
    .b_in(x_val),
    .p_out(x_square),
    .overflow(overflow_x_square)
);

endmodule

Internship_IITH/Default_func/tb_Top.v
`timescale 1ns / 1ps

module tb_Top;

    reg clk;
    reg rst_n;
    reg start_func;
    reg signed [31:0] x_input;          // 32 bit Q24.8 foramt
    reg signed [31:0] x_input_buffer;   // 32 bit Q24.8 foramt
    

// WIRE DECLARATION
    wire func_done;
    wire [63:0] y_output;               // 64 bit Q56.8 foramt
    wire overflow;
    Top uut (
        .clk(clk),
        .rst_n(rst_n),
        .start_func(start_func),
        .x_in(x_input_buffer), // 32 bit Q24.8 foramt
        .y_out(y_output),      // 64 bit Q56.8 foramt
        .func_done(func_done), 
        .overflow(overflow)
    );

// clk generation
    initial begin
        clk = 0;
        forever #5 clk = ~clk; // 10 ns period (100 MHz) 
    end

// Test sequence 
    initial begin
        integer i;

        // Storing values for waveform simulation
        $dumpfile("tb_top.vcd");
        $dumpvars(0, tb_Top);

        rst_n = 1'b0;      // Assert Reset
        start_func = 1'b0; // Disasset Start of func
        x_input = 32'h00000100; // Initial Input

        $display("---------------------------------------------------------");
        $display("----Starting Testbench for Default Polynomial Function---");
        $display("---------------------------------------------------------");

        #20 rst_n = 1'b1;  // Disassert reset

        for (i = 1; i < 11; i = i+1 )begin 
            start_func = 1'b1;
            x_input_buffer = x_input;
            #20; // wait for ouput to settle

            wait(func_done == 1'b1);
            $display("\n--- Test Case %0d: Initial x = %f (Q24.8) ---", i, $itor(x_input) / 256.0);
            $display("X input : %f (0x%H)", $itor(x_input) / 256.0, x_input);
            $display("Y output: %f (0x%H)", $itor(y_output) / 256.0, y_output);

            start_func = 1'b0;
            x_input = x_input + 32'h00000100;  // decimal 1 in Q24.8 fromat
            #20;
        end
        $finish; // end simulation
    end
endmodule

Internship_IITH/Default_func/tb_top.vcd
$date
	Wed Jun 04 10:23:10 2025
$end
$version
	Icarus Verilog
$end
$timescale
	1ps
$end
$scope module tb_Top $end
$var wire 64 ! y_output [63:0] $end
$var wire 1 " overflow $end
$var wire 1 # func_done $end
$var reg 1 $ clk $end
$var reg 1 % rst_n $end
$var reg 1 & start_func $end
$var reg 32 ' x_input [31:0] $end
$var reg 32 ( x_input_buffer [31:0] $end
$scope module uut $end
$var wire 1 $ clk $end
$var wire 1 ) overflow_x_square $end
$var wire 1 % rst_n $end
$var wire 1 & start_func $end
$var wire 32 * x_in [31:0] $end
$var wire 64 + x_square [63:0] $end
$var parameter 64 , MINUS_ONE $end
$var parameter 2 - STATE_COMPUTE $end
$var parameter 2 . STATE_DONE $end
$var parameter 2 / STATE_IDLE $end
$var parameter 2 0 STATE_INIT $end
$var reg 1 1 compute_done $end
$var reg 64 2 compute_result [63:0] $end
$var reg 2 3 curr_state [1:0] $end
$var reg 64 4 four_x [63:0] $end
$var reg 1 # func_done $end
$var reg 2 5 next_state [1:0] $end
$var reg 1 " overflow $end
$var reg 32 6 x_val [31:0] $end
$var reg 64 7 y_out [63:0] $end
$scope module inst $end
$var wire 32 8 a_in [31:0] $end
$var wire 32 9 b_in [31:0] $end
$var wire 1 ) overflow $end
$var wire 64 : product_full [63:0] $end
$var wire 64 ; p_out [63:0] $end
$var parameter 32 < FRACT_BITS $end
$upscope $end
$upscope $end
$scope begin $unm_blk_15 $end
$var integer 32 = i [31:0] $end
$upscope $end
$upscope $end
$enddefinitions $end
$comment Show the parameter values. $end
$dumpall
b1000 <
b1 0
b0 /
b11 .
b10 -
b1111111111111111111111111111111111111111111111111111111100000000 ,
$end
#0
$dumpvars
bx =
b0 ;
b0 :
b0 9
b0 8
b0 7
b0 6
b0 5
b0 4
b0 3
b1111111111111111111111111111111111111111111111111111111100000000 2
01
b0 +
bx *
0)
bx (
b100000000 '
0&
0%
0$
0#
0"
b0 !
$end
#5000
1$
#10000
0$
#15000
1$
#20000
b1 5
0$
b100000000 (
b100000000 *
1&
b1 =
1%
#25000
b10 5
b1 3
1$
#30000
0$
#35000
b100000000 +
b100000000 ;
b10000000000 2
b10000000000 4
b10000000000000000 :
b100000000 6
b100000000 8
b100000000 9
b10 3
1$
#40000
0$
#45000
b11 5
11
b10000000000 !
b10000000000 7
1$
#50000
0$
#55000
b11 3
1$
#60000
0$
#65000
b0 5
b1000000000 '
0&
1#
1$
#70000
0$
#75000
b0 3
1$
#80000
0$
#85000
01
0#
b1 3
b10 5
1$
b1000000000 (
b1000000000 *
1&
b10 =
#90000
0$
#95000
b10000000000 +
b10000000000 ;
b101100000000 2
b100000000000 4
b0 !
b0 7
b1000000000000000000 :
b1000000000 6
b1000000000 8
b1000000000 9
b10 3
1$
#100000
0$
#105000
b11 5
11
b101100000000 !
b101100000000 7
1$
#110000
0$
#115000
b11 3
1$
#120000
0$
#125000
b0 5
b1100000000 '
0&
1#
1$
#130000
0$
#135000
b0 3
1$
#140000
0$
#145000
01
0#
b1 3
b10 5
1$
b1100000000 (
b1100000000 *
1&
b11 =
#150000
0$
#155000
b100100000000 +
b100100000000 ;
b1010000000000 2
b110000000000 4
b0 !
b0 7
b10010000000000000000 :
b1100000000 6
b1100000000 8
b1100000000 9
b10 3
1$
#160000
0$
#165000
b11 5
11
b1010000000000 !
b1010000000000 7
1$
#170000
0$
#175000
b11 3
1$
#180000
0$
#185000
b0 5
b10000000000 '
0&
1#
1$
#190000
0$
#195000
b0 3
1$
#200000
0$
#205000
01
0#
b1 3
b10 5
1$
b10000000000 (
b10000000000 *
1&
b100 =
#210000
0$
#215000
b1000000000000 +
b1000000000000 ;
b1111100000000 2
b1000000000000 4
b0 !
b0 7
b100000000000000000000 :
b10000000000 6
b10000000000 8
b10000000000 9
b10 3
1$
#220000
0$
#225000
b11 5
11
b1111100000000 !
b1111100000000 7
1$
#230000
0$
#235000
b11 3
1$
#240000
0$
#245000
b0 5
b10100000000 '
0&
1#
1$
#250000
0$
#255000
b0 3
1$
#260000
0$
#265000
01
0#
b1 3
b10 5
1$
b10100000000 (
b10100000000 *
1&
b101 =
#270000
0$
#275000
b1100100000000 +
b1100100000000 ;
b10110000000000 2
b1010000000000 4
b0 !
b0 7
b110010000000000000000 :
b10100000000 6
b10100000000 8
b10100000000 9
b10 3
1$
#280000
0$
#285000
b11 5
11
b10110000000000 !
b10110000000000 7
1$
#290000
0$
#295000
b11 3
1$
#300000
0$
#305000
b0 5
b11000000000 '
0&
1#
1$
#310000
0$
#315000
b0 3
1$
#320000
0$
#325000
01
0#
b1 3
b10 5
1$
b11000000000 (
b11000000000 *
1&
b110 =
#330000
0$
#335000
b10010000000000 +
b10010000000000 ;
b11101100000000 2
b1100000000000 4
b0 !
b0 7
b1001000000000000000000 :
b11000000000 6
b11000000000 8
b11000000000 9
b10 3
1$
#340000
0$
#345000
b11 5
11
b11101100000000 !
b11101100000000 7
1$
#350000
0$
#355000
b11 3
1$
#360000
0$
#365000
b0 5
b11100000000 '
0&
1#
1$
#370000
0$
#375000
b0 3
1$
#380000
0$
#385000
01
0#
b1 3
b10 5
1$
b11100000000 (
b11100000000 *
1&
b111 =
#390000
0$
#395000
b11000100000000 +
b11000100000000 ;
b100110000000000 2
b1110000000000 4
b0 !
b0 7
b1100010000000000000000 :
b11100000000 6
b11100000000 8
b11100000000 9
b10 3
1$
#400000
0$
#405000
b11 5
11
b100110000000000 !
b100110000000000 7
1$
#410000
0$
#415000
b11 3
1$
#420000
0$
#425000
b0 5
b100000000000 '
0&
1#
1$
#430000
0$
#435000
b0 3
1$
#440000
0$
#445000
01
0#
b1 3
b10 5
1$
b100000000000 (
b100000000000 *
1&
b1000 =
#450000
0$
#455000
b100000000000000 +
b100000000000000 ;
b101111100000000 2
b10000000000000 4
b0 !
b0 7
b10000000000000000000000 :
b100000000000 6
b100000000000 8
b100000000000 9
b10 3
1$
#460000
0$
#465000
b11 5
11
b101111100000000 !
b101111100000000 7
1$
#470000
0$
#475000
b11 3
1$
#480000
0$
#485000
b0 5
b100100000000 '
0&
1#
1$
#490000
0$
#495000
b0 3
1$
#500000
0$
#505000
01
0#
b1 3
b10 5
1$
b100100000000 (
b100100000000 *
1&
b1001 =
#510000
0$
#515000
b101000100000000 +
b101000100000000 ;
b111010000000000 2
b10010000000000 4
b0 !
b0 7
b10100010000000000000000 :
b100100000000 6
b100100000000 8
b100100000000 9
b10 3
1$
#520000
0$
#525000
b11 5
11
b111010000000000 !
b111010000000000 7
1$
#530000
0$
#535000
b11 3
1$
#540000
0$
#545000
b0 5
b101000000000 '
0&
1#
1$
#550000
0$
#555000
b0 3
1$
#560000
0$
#565000
01
0#
b1 3
b10 5
1$
b101000000000 (
b101000000000 *
1&
b1010 =
#570000
0$
#575000
b110010000000000 +
b110010000000000 ;
b1000101100000000 2
b10100000000000 4
b0 !
b0 7
b11001000000000000000000 :
b101000000000 6
b101000000000 8
b101000000000 9
b10 3
1$
#580000
0$
#585000
b11 5
11
b1000101100000000 !
b1000101100000000 7
1$
#590000
0$
#595000
b11 3
1$
#600000
0$
#605000
b0 5
b101100000000 '
0&
1#
1$
#610000
0$
#615000
b0 3
1$
#620000
0$
#625000
01
0#
1$
b1011 =
