Internship_IITH/4D_gradient_descent_V1.0/fixed_32_mult.v
module fixed_32_mult(
    input signed [31:0] a_in,    // Input operand A (Q24.8 format)
    input signed [31:0] b_in,    // Input operand B (Q24.8 format)
    output signed [31:0] p_out,  // Product P (Q24.8 format)
    output logic overflow,        // Flag for overflow detection
    output logic underflow_q       // Flag for underflow detection (going below minimum negative)
);

    localparam integer FRACT_BITS = 8;
    wire signed [63:0] product_full;

    assign product_full = a_in * b_in;
    assign p_out = product_full >>> FRACT_BITS;

    wire expected_sign = p_out[31]; // The sign bit of the result
    wire [23:0] msb_of_product_full = product_full[63:40]; // 63 - 40 + 1 = 24 bits
    assign overflow = (expected_sign == 1'b0) && (|msb_of_product_full); // Positive overflow if any MSB is 1
    assign underflow_q = (expected_sign == 1'b1) && (~(&msb_of_product_full)); // Negative overflow/underflow if any MSB is 0


endmodule

Internship_IITH/general_linear_regressor_V1.0/fixed_64_mult.v
module fixed_64_mult(
    input signed [31:0] a_in,    // Input operand A (Q24.8 format)
    input signed [31:0] b_in,    // Input operand B (Q24.8 format)
    output signed [63:0] p_out,  // Product P (Q55.8 format)
    output logic overflow        // Flag for overflow detection
);

    localparam integer FRACT_BITS = 8;
    wire signed [63:0] product_full;

    assign product_full = a_in * b_in;
    assign p_out = product_full >>> FRACT_BITS;

    assign overflow = 1'b0;

endmodule

Internship_IITH/func_grad_val_diff_test/func.v
module func(
    input clk,
    input rst_n,
    input start_func,
    input signed [31:0] x_in,
    output reg signed [63:0] y_out,
    output reg func_done,
    output reg overflow
);

// The default Function is assumed to be X^2 + 4x - 1

localparam STATE_IDLE       = 2'b00;
localparam STATE_INIT       = 2'b01;
localparam STATE_COMPUTE    = 2'b10;
localparam STATE_DONE       = 2'b11;
localparam MINUS_ONE        = 64'hFFFFFFFFFFFFFF00;

reg [1:0] curr_state;
reg [1:0] next_state;
reg compute_done ;
reg signed [31:0] x_val;
reg signed [63:0] four_x;
reg signed [63:0] compute_result;

wire signed [63:0] x_square;
wire overflow_x_square;

always @(*) begin
    next_state = curr_state;
    case (curr_state)
        STATE_IDLE      : begin if (start_func)  next_state = STATE_INIT; end
        STATE_INIT      : begin next_state = STATE_COMPUTE; end
        STATE_COMPUTE   : begin if (compute_done) next_state = STATE_DONE; end
        STATE_DONE      : begin if (!start_func) next_state = STATE_IDLE; end
        default         : begin next_state = STATE_IDLE; end
    endcase
    four_x = x_val << 2; // SIGN EXTENED
    compute_result = x_square + four_x + MINUS_ONE;  // Q56.8 format
end

always_ff @(posedge clk, negedge rst_n) begin 
    if (!rst_n) begin
        curr_state  <= STATE_IDLE;
        func_done   <= 1'b0;
        x_val       <= 32'd0;   
        y_out       <= 64'd0;
        compute_done <= 1'b0;
        overflow    <= 1'b0;
    end else begin 
        curr_state <= next_state;
        case (curr_state)
            STATE_IDLE : begin
                // DO NOTHING
                func_done <= 1'b0;
                compute_done <= 1'b0;   
            end  
            STATE_INIT : begin
                x_val <= x_in;
                y_out <= 64'd0;
                func_done <= 1'b0;
                compute_done <= 1'b0;   
            end
            STATE_COMPUTE: begin 
                y_out <= compute_result;
                compute_done <= 1'b1;
                overflow <= overflow_x_square;
            end
            STATE_DONE : begin 
                func_done <= 1'b1;
            end
        endcase
    end 
end

fixed_64_mult inst (   // calculate x^2
    .a_in(x_val),
    .b_in(x_val),
    .p_out(x_square),
    .overflow(overflow_x_square)
);

endmodule

Internship_IITH/func_grad_val_diff_test/Top.v
module Top(
    input clk,
    input rst_n,
    input start_func,
    input signed [31:0] x_in,
    output reg signed [63:0] gradient,
    output reg signed [63:0] value,
    output reg signed [31:0] x_diff_out,
    output reg func_done,
    output reg overflow
);
    localparam TWO_H = 32'h00000002;            // Q24.8 2H = 7.8125e-3 in decimal 
    localparam LEARNING_RATE = 32'h00000080;    // Q24.8 0.5 in decimal
    wire signed [63:0]val1;                     // Q56.8
    wire signed [63:0]val2;                     // Q56.8
    wire signed [31:0] x_in_minus_2H;           // Q24.8
    wire signed [63:0] gradient_intermediate;   // Q56.8 
    wire signed [31:0] x_diff;                  // Q24.8
    wire func1_done;
    wire func2_done;
    wire mult_done;
    wire overflow1;
    wire overflow2;
    wire overflow_mult;
    wire underflow_mult;

    assign x_in_minus_2H = x_in - TWO_H;
    assign gradient_intermediate = (val1 - val2) << 7;

    func func_val(
        .clk(clk),
        .rst_n(rst_n),
        .start_func(start_func),
        .x_in(x_in ),               // Q24.8
        .y_out(val1),               // Q56.8
        .func_done(func1_done),
        .overflow(overflow1)
    );

    func inst2(
        .clk(clk),
        .rst_n(rst_n),
        .start_func(start_func),
        .x_in(x_in_minus_2H),       // Q24.8
        .y_out(val2),               // Q56.8 
        .func_done(func2_done),
        .overflow(overflow2)
    );

    fixed_32_mult inst_diff(
        .a_in(LEARNING_RATE),               // Q24.8
        .b_in(gradient_intermediate[31:0]), // Q24.8
        .p_out(x_diff),                     // Q56.8
        .overflow(overflow_mult),
        .underflow_q(underflow_mult)
    );

    wire all_funcs_done;
    assign all_funcs_done = func1_done & func2_done ;
    always @(posedge clk, negedge rst_n) begin
        if (!rst_n) begin
            gradient    <= 64'd0;
            value       <= 64'd0;
            func_done   <= 1'b0;
            overflow    <= 1'b0;
        end else begin
            if (all_funcs_done) begin
                gradient <= gradient_intermediate;
                value <= val1;
                func_done <= 1'b1;
                overflow <= overflow1 | overflow2 | overflow_mult;
                if (overflow_mult) begin 
                    x_diff_out <= 32'h7FFFFFFF; // capped at Highest positive 32 bit signed value
                end else if (underflow_mult) begin
                    x_diff_out <= 32'h80000000; // capped at minimum negetive 32 bit signed value 
                end else begin
                    x_diff_out <= x_diff;
                end
            end else begin
                func_done <= 1'b0;
            end
        end
    end
endmodule

Internship_IITH/func_grad_val_diff_test/tb_Top.v
`timescale 1ns / 1ps

module tb_Top;

    reg clk;
    reg rst_n;
    reg start_func;
    reg signed [31:0] x_input;          // 32 bit Q24.8 foramt
    reg signed [31:0] x_input_buffer;   // 32 bit Q24.8 foramt
    

// WIRE DECLARATION
    wire func_done;
    wire [63:0] gradient;               // 64 bit Q56.8 foramt
    wire [63:0] value;                  // 64 bit Q56.8 foramt
    wire [31:0] x_diff;                 // Distance of new X in Q24.8 format
    wire overflow;

    Top uut(
        .clk(clk),
        .rst_n(rst_n),
        .start_func(start_func),
        .x_in(x_input_buffer),          // 32 bit Q24.8 foramt
        .gradient(gradient),            // 64 bit Q56.8 foramt
        .value(value),
        .x_diff_out(x_diff),
        .func_done(func_done), 
        .overflow(overflow)
    );

// clk generation
    initial begin
        clk = 0;
        forever #5 clk = ~clk; // 10 ns period (100 MHz) 
    end

// Test sequence 
    initial begin
        integer i;

        // Storing values for waveform simulation
        $dumpfile("tb_top.vcd");
        $dumpvars(0, tb_Top);

        rst_n = 1'b0;      // Assert Reset
        start_func = 1'b0; // Disasset Start of func
        x_input = 32'h00000100; // Initial Input  decimal 1.0

        $display("---------------------------------------------------------");
        $display("---Starting Testbench for Polynomial Gradient Function---");
        $display("---------------------------------------------------------");

        #20 rst_n = 1'b1;  // Disassert reset

        for (i = 1; i < 11; i = i+1 )begin 
            start_func = 1'b1;
            x_input_buffer = x_input;
            #20; // wait for ouput to settle

            wait(func_done == 1'b1);
            $display("\n--- Test Case %0d: Initial x = %f (Q24.8) ---", i, $itor(x_input) / 256.0);
            $display("X input : %f (0x%H)", $itor(x_input) / 256.0, x_input);
            $display("Gradient: %f (0x%H)", $itor(gradient) / 256.0, gradient);
            $display("value : %f (0x%H)", $itor(value) / 256.0, value);
            $display("X-Diff: %f (0x%H)", $itor(x_diff) / 256.0, x_diff);

            start_func = 1'b0;
            x_input = x_input - 32'h00000F00;  // decimal 16 in Q24.8 fromat
            #20;
        end
        $finish; // end simulation
    end
endmodule

Internship_IITH/func_grad_val_diff_test/tb_top.vcd
$date
	Fri Jun 06 12:32:08 2025
$end
$version
	Icarus Verilog
$end
$timescale
	1ps
$end
$scope module tb_Top $end
$var wire 32 ! x_diff [31:0] $end
$var wire 64 " value [63:0] $end
$var wire 1 # overflow $end
$var wire 64 $ gradient [63:0] $end
$var wire 1 % func_done $end
$var reg 1 & clk $end
$var reg 1 ' rst_n $end
$var reg 1 ( start_func $end
$var reg 32 ) x_input [31:0] $end
$var reg 32 * x_input_buffer [31:0] $end
$scope module uut $end
$var wire 1 + all_funcs_done $end
$var wire 1 & clk $end
$var wire 1 ' rst_n $end
$var wire 1 ( start_func $end
$var wire 32 , x_in [31:0] $end
$var wire 32 - x_in_minus_2H [31:0] $end
$var wire 32 . x_diff [31:0] $end
$var wire 64 / val2 [63:0] $end
$var wire 64 0 val1 [63:0] $end
$var wire 1 1 underflow_mult $end
$var wire 1 2 overflow_mult $end
$var wire 1 3 overflow2 $end
$var wire 1 4 overflow1 $end
$var wire 64 5 gradient_intermediate [63:0] $end
$var wire 1 6 func2_done $end
$var wire 1 7 func1_done $end
$var parameter 32 8 LEARNING_RATE $end
$var parameter 32 9 TWO_H $end
$var reg 1 % func_done $end
$var reg 64 : gradient [63:0] $end
$var reg 1 # overflow $end
$var reg 64 ; value [63:0] $end
$var reg 32 < x_diff_out [31:0] $end
$scope module func_val $end
$var wire 1 & clk $end
$var wire 1 = overflow_x_square $end
$var wire 1 ' rst_n $end
$var wire 1 ( start_func $end
$var wire 32 > x_in [31:0] $end
$var wire 64 ? x_square [63:0] $end
$var parameter 64 @ MINUS_ONE $end
$var parameter 2 A STATE_COMPUTE $end
$var parameter 2 B STATE_DONE $end
$var parameter 2 C STATE_IDLE $end
$var parameter 2 D STATE_INIT $end
$var reg 1 E compute_done $end
$var reg 64 F compute_result [63:0] $end
$var reg 2 G curr_state [1:0] $end
$var reg 64 H four_x [63:0] $end
$var reg 1 7 func_done $end
$var reg 2 I next_state [1:0] $end
$var reg 1 4 overflow $end
$var reg 32 J x_val [31:0] $end
$var reg 64 K y_out [63:0] $end
$scope module inst $end
$var wire 32 L a_in [31:0] $end
$var wire 32 M b_in [31:0] $end
$var wire 1 = overflow $end
$var wire 64 N product_full [63:0] $end
$var wire 64 O p_out [63:0] $end
$var parameter 32 P FRACT_BITS $end
$upscope $end
$upscope $end
$scope module inst2 $end
$var wire 1 & clk $end
$var wire 1 Q overflow_x_square $end
$var wire 1 ' rst_n $end
$var wire 1 ( start_func $end
$var wire 32 R x_in [31:0] $end
$var wire 64 S x_square [63:0] $end
$var parameter 64 T MINUS_ONE $end
$var parameter 2 U STATE_COMPUTE $end
$var parameter 2 V STATE_DONE $end
$var parameter 2 W STATE_IDLE $end
$var parameter 2 X STATE_INIT $end
$var reg 1 Y compute_done $end
$var reg 64 Z compute_result [63:0] $end
$var reg 2 [ curr_state [1:0] $end
$var reg 64 \ four_x [63:0] $end
$var reg 1 6 func_done $end
$var reg 2 ] next_state [1:0] $end
$var reg 1 3 overflow $end
$var reg 32 ^ x_val [31:0] $end
$var reg 64 _ y_out [63:0] $end
$scope module inst $end
$var wire 32 ` a_in [31:0] $end
$var wire 32 a b_in [31:0] $end
$var wire 1 Q overflow $end
$var wire 64 b product_full [63:0] $end
$var wire 64 c p_out [63:0] $end
$var parameter 32 d FRACT_BITS $end
$upscope $end
$upscope $end
$scope module inst_diff $end
$var wire 32 e a_in [31:0] $end
$var wire 32 f b_in [31:0] $end
$var wire 1 2 overflow $end
$var wire 1 1 underflow_q $end
$var wire 64 g product_full [63:0] $end
$var wire 32 h p_out [31:0] $end
$var wire 24 i msb_of_product_full [23:0] $end
$var wire 1 j expected_sign $end
$var parameter 32 k FRACT_BITS $end
$upscope $end
$upscope $end
$scope begin $unm_blk_23 $end
$var integer 32 l i [31:0] $end
$upscope $end
$upscope $end
$enddefinitions $end
$comment Show the parameter values. $end
$dumpall
b1000 k
b1000 d
b1 X
b0 W
b11 V
b10 U
b1111111111111111111111111111111111111111111111111111111100000000 T
b1000 P
b1 D
b0 C
b11 B
b10 A
b1111111111111111111111111111111111111111111111111111111100000000 @
b10 9
b10000000 8
$end
#0
$dumpvars
bx l
0j
b0 i
b0 h
b0 g
b0 f
b10000000 e
b0 c
b0 b
b0 a
b0 `
b0 _
b0 ^
b0 ]
b0 \
b0 [
b1111111111111111111111111111111111111111111111111111111100000000 Z
0Y
b0 S
bx R
0Q
b0 O
b0 N
b0 M
b0 L
b0 K
b0 J
b0 I
b0 H
b0 G
b1111111111111111111111111111111111111111111111111111111100000000 F
0E
b0 ?
bx >
0=
bx <
b0 ;
b0 :
07
06
b0 5
04
03
02
01
b0 0
b0 /
b0 .
bx -
bx ,
0+
bx *
b100000000 )
0(
0'
0&
0%
b0 $
0#
b0 "
bx !
$end
#5000
1&
#10000
0&
#15000
1&
#20000
b1 I
b1 ]
0&
b11111110 -
b11111110 R
b100000000 *
b100000000 ,
b100000000 >
1(
b1 l
1'
#25000
b10 ]
b10 I
b1 [
b1 G
1&
#30000
0&
#35000
b100000000 ?
b100000000 O
b10000000000 F
b10000000000 H
b11111100 S
b11111100 c
b1111110100 Z
b1111111000 \
b10000000000000000 N
b100000000 J
b100000000 L
b100000000 M
b10 G
b1111110000000100 b
b11111110 ^
b11111110 `
b11111110 a
b10 [
1&
#40000
0&
#45000
b1100000000 .
b1100000000 h
b110000000000000000 g
b11000000000 f
b11 ]
b11 I
b11000000000 5
1Y
b1111110100 /
b1111110100 _
1E
b10000000000 0
b10000000000 K
1&
#50000
0&
#55000
b11 G
b11 [
1&
#60000
0&
#65000
1+
16
17
1&
#70000
0&
#75000
b0 I
b0 ]
b11111111111111111111001000000000 )
0(
b1100000000 !
b1100000000 <
1%
b10000000000 "
b10000000000 ;
b11000000000 $
b11000000000 :
1&
#80000
0&
#85000
b0 [
b0 G
1&
#90000
0&
#95000
0+
0E
07
b1 G
0Y
06
b1 [
b10 I
b10 ]
1&
b11111111111111111111000111111110 -
b11111111111111111111000111111110 R
b11111111111111111111001000000000 *
b11111111111111111111001000000000 ,
b11111111111111111111001000000000 >
1(
b10 l
#100000
0&
#105000
b0 .
b0 h
b0 g
b0 f
b1100010000111000 S
b1100010000111000 c
b1000101100110000 Z
b1111111111111111111111111111111111111111111111111100011111111000 \
b0 5
b1100010000000000 ?
b1100010000000000 O
b1000101100000000 F
b1111111111111111111111111111111111111111111111111100100000000000 H
0%
b0 /
b0 _
b110001000011100000000100 b
b11111111111111111111000111111110 ^
b11111111111111111111000111111110 `
b11111111111111111111000111111110 a
b10 [
b0 0
b0 K
b110001000000000000000000 N
b11111111111111111111001000000000 J
b11111111111111111111001000000000 L
b11111111111111111111001000000000 M
b10 G
1&
#110000
0&
#115000
1j
b11111111111111111111010000000000 .
b11111111111111111111010000000000 h
02
b111111111111111111111111 i
b1111111111111111111111111111111111111111111101000000000000000000 g
b11111111111111111110100000000000 f
b11 I
b11 ]
b1111111111111111111111111111111111111111111111111110100000000000 5
1E
b1000101100000000 0
b1000101100000000 K
1Y
b1000101100110000 /
b1000101100110000 _
1&
#120000
0&
#125000
b11 [
b11 G
1&
#130000
0&
#135000
1+
17
16
1&
#140000
0&
#145000
b0 I
b0 ]
b11111111111111111110001100000000 )
0(
b11111111111111111111010000000000 !
b11111111111111111111010000000000 <
1%
b1000101100000000 "
b1000101100000000 ;
b1111111111111111111111111111111111111111111111111110100000000000 $
b1111111111111111111111111111111111111111111111111110100000000000 :
1&
#150000
0&
#155000
b0 G
b0 [
1&
#160000
0&
#165000
0+
0Y
06
b1 [
0E
07
b1 G
b10 I
b10 ]
1&
b11111111111111111110001011111110 -
b11111111111111111110001011111110 R
b11111111111111111110001100000000 *
b11111111111111111110001100000000 ,
b11111111111111111110001100000000 >
1(
b11 l
#170000
0&
#175000
0j
01
b0 .
b0 h
b0 i
b0 g
b0 f
b110100100100000000 ?
b110100100100000000 O
b101101010000000000 F
b1111111111111111111111111111111111111111111111111000110000000000 H
b0 5
b110100100101110100 S
b110100100101110100 c
b101101010001101100 Z
b1111111111111111111111111111111111111111111111111000101111111000 \
b0 0
b0 K
b11010010010000000000000000 N
b11111111111111111110001100000000 J
b11111111111111111110001100000000 L
b11111111111111111110001100000000 M
b10 G
b0 /
b0 _
b11010010010111010000000100 b
b11111111111111111110001011111110 ^
b11111111111111111110001011111110 `
b11111111111111111110001011111110 a
b10 [
0%
1&
#180000
0&
#185000
1j
b11111111111111111110010100000000 .
b11111111111111111110010100000000 h
02
b111111111111111111111111 i
b1111111111111111111111111111111111111111111001010000000000000000 g
b11111111111111111100101000000000 f
b11 ]
b11 I
b1111111111111111111111111111111111111111111111111100101000000000 5
1Y
b101101010001101100 /
b101101010001101100 _
1E
b101101010000000000 0
b101101010000000000 K
1&
#190000
0&
#195000
b11 G
b11 [
1&
#200000
0&
#205000
1+
16
17
1&
#210000
0&
#215000
b0 I
b0 ]
b11111111111111111101010000000000 )
0(
b11111111111111111110010100000000 !
b11111111111111111110010100000000 <
1%
b101101010000000000 "
b101101010000000000 ;
b1111111111111111111111111111111111111111111111111100101000000000 $
b1111111111111111111111111111111111111111111111111100101000000000 :
1&
#220000
0&
#225000
b0 [
b0 G
1&
#230000
0&
#235000
0+
0E
07
b1 G
0Y
06
b1 [
b10 I
b10 ]
1&
b11111111111111111101001111111110 -
b11111111111111111101001111111110 R
b11111111111111111101010000000000 *
b11111111111111111101010000000000 ,
b11111111111111111101010000000000 >
1(
b100 l
#240000
0&
#245000
0j
01
b0 .
b0 h
b0 i
b0 g
b0 f
b1111001000010110000 S
b1111001000010110000 c
b1101101111110101000 Z
b1111111111111111111111111111111111111111111111110100111111111000 \
b0 5
b1111001000000000000 ?
b1111001000000000000 O
b1101101111100000000 F
b1111111111111111111111111111111111111111111111110101000000000000 H
0%
b0 /
b0 _
b111100100001011000000000100 b
b11111111111111111101001111111110 ^
b11111111111111111101001111111110 `
b11111111111111111101001111111110 a
b10 [
b0 0
b0 K
b111100100000000000000000000 N
b11111111111111111101010000000000 J
b11111111111111111101010000000000 L
b11111111111111111101010000000000 M
b10 G
1&
#250000
0&
#255000
1j
b11111111111111111101011000000000 .
b11111111111111111101011000000000 h
02
b111111111111111111111111 i
b1111111111111111111111111111111111111111110101100000000000000000 g
b11111111111111111010110000000000 f
b11 I
b11 ]
b1111111111111111111111111111111111111111111111111010110000000000 5
1E
b1101101111100000000 0
b1101101111100000000 K
1Y
b1101101111110101000 /
b1101101111110101000 _
1&
#260000
0&
#265000
b11 [
b11 G
1&
#270000
0&
#275000
1+
17
16
1&
#280000
0&
#285000
b0 I
b0 ]
b11111111111111111100010100000000 )
0(
b11111111111111111101011000000000 !
b11111111111111111101011000000000 <
1%
b1101101111100000000 "
b1101101111100000000 ;
b1111111111111111111111111111111111111111111111111010110000000000 $
b1111111111111111111111111111111111111111111111111010110000000000 :
1&
#290000
0&
#295000
b0 G
b0 [
1&
#300000
0&
#305000
0+
0Y
06
b1 [
0E
07
b1 G
b10 I
b10 ]
1&
b11111111111111111100010011111110 -
b11111111111111111100010011111110 R
b11111111111111111100010100000000 *
b11111111111111111100010100000000 ,
b11111111111111111100010100000000 >
1(
b101 l
#310000
0&
#315000
0j
01
b0 .
b0 h
b0 i
b0 g
b0 f
b11011001100100000000 ?
b11011001100100000000 O
b11001010110000000000 F
b1111111111111111111111111111111111111111111111110001010000000000 H
b0 5
b11011001100111101100 S
b11011001100111101100 c
b11001010110011100100 Z
b1111111111111111111111111111111111111111111111110001001111111000 \
b0 0
b0 K
b1101100110010000000000000000 N
b11111111111111111100010100000000 J
b11111111111111111100010100000000 L
b11111111111111111100010100000000 M
b10 G
b0 /
b0 _
b1101100110011110110000000100 b
b11111111111111111100010011111110 ^
b11111111111111111100010011111110 `
b11111111111111111100010011111110 a
b10 [
0%
1&
#320000
0&
#325000
1j
b11111111111111111100011100000000 .
b11111111111111111100011100000000 h
02
b111111111111111111111111 i
b1111111111111111111111111111111111111111110001110000000000000000 g
b11111111111111111000111000000000 f
b11 ]
b11 I
b1111111111111111111111111111111111111111111111111000111000000000 5
1Y
b11001010110011100100 /
b11001010110011100100 _
1E
b11001010110000000000 0
b11001010110000000000 K
1&
#330000
0&
#335000
b11 G
b11 [
1&
#340000
0&
#345000
1+
16
17
1&
#350000
0&
#355000
b0 I
b0 ]
b11111111111111111011011000000000 )
0(
b11111111111111111100011100000000 !
b11111111111111111100011100000000 <
1%
b11001010110000000000 "
b11001010110000000000 ;
b1111111111111111111111111111111111111111111111111000111000000000 $
b1111111111111111111111111111111111111111111111111000111000000000 :
1&
#360000
0&
#365000
b0 [
b0 G
1&
#370000
0&
#375000
0+
0E
07
b1 G
0Y
06
b1 [
b10 I
b10 ]
1&
b11111111111111111011010111111110 -
b11111111111111111011010111111110 R
b11111111111111111011011000000000 *
b11111111111111111011011000000000 ,
b11111111111111111011011000000000 >
1(
b110 l
#380000
0&
#385000
0j
01
b0 .
b0 h
b0 i
b0 g
b0 f
b101010110010100101000 S
b101010110010100101000 c
b101000011110000100000 Z
b1111111111111111111111111111111111111111111111101101011111111000 \
b0 5
b101010110010000000000 ?
b101010110010000000000 O
b101000011101100000000 F
b1111111111111111111111111111111111111111111111101101100000000000 H
0%
b0 /
b0 _
b10101011001010010100000000100 b
b11111111111111111011010111111110 ^
b11111111111111111011010111111110 `
b11111111111111111011010111111110 a
b10 [
b0 0
b0 K
b10101011001000000000000000000 N
b11111111111111111011011000000000 J
b11111111111111111011011000000000 L
b11111111111111111011011000000000 M
b10 G
1&
#390000
0&
#395000
1j
b11111111111111111011100000000000 .
b11111111111111111011100000000000 h
02
b111111111111111111111111 i
b1111111111111111111111111111111111111111101110000000000000000000 g
b11111111111111110111000000000000 f
b11 I
b11 ]
b1111111111111111111111111111111111111111111111110111000000000000 5
1E
b101000011101100000000 0
b101000011101100000000 K
1Y
b101000011110000100000 /
b101000011110000100000 _
1&
#400000
0&
#405000
b11 [
b11 G
1&
#410000
0&
#415000
1+
17
16
1&
#420000
0&
#425000
b0 I
b0 ]
b11111111111111111010011100000000 )
0(
b11111111111111111011100000000000 !
b11111111111111111011100000000000 <
1%
b101000011101100000000 "
b101000011101100000000 ;
b1111111111111111111111111111111111111111111111110111000000000000 $
b1111111111111111111111111111111111111111111111110111000000000000 :
1&
#430000
0&
#435000
b0 G
b0 [
1&
#440000
0&
#445000
0+
0Y
06
b1 [
0E
07
b1 G
b10 I
b10 ]
1&
b11111111111111111010011011111110 -
b11111111111111111010011011111110 R
b11111111111111111010011100000000 *
b11111111111111111010011100000000 ,
b11111111111111111010011100000000 >
1(
b111 l
#450000
0&
#455000
0j
01
b0 .
b0 h
b0 i
b0 g
b0 f
b111101111000100000000 ?
b111101111000100000000 O
b111011000110000000000 F
b1111111111111111111111111111111111111111111111101001110000000000 H
b0 5
b111101111001001100100 S
b111101111001001100100 c
b111011000110101011100 Z
b1111111111111111111111111111111111111111111111101001101111111000 \
b0 0
b0 K
b11110111100010000000000000000 N
b11111111111111111010011100000000 J
b11111111111111111010011100000000 L
b11111111111111111010011100000000 M
b10 G
b0 /
b0 _
b11110111100100110010000000100 b
b11111111111111111010011011111110 ^
b11111111111111111010011011111110 `
b11111111111111111010011011111110 a
b10 [
0%
1&
#460000
0&
#465000
1j
b11111111111111111010100100000000 .
b11111111111111111010100100000000 h
02
b111111111111111111111111 i
b1111111111111111111111111111111111111111101010010000000000000000 g
b11111111111111110101001000000000 f
b11 ]
b11 I
b1111111111111111111111111111111111111111111111110101001000000000 5
1Y
b111011000110101011100 /
b111011000110101011100 _
1E
b111011000110000000000 0
b111011000110000000000 K
1&
#470000
0&
#475000
b11 G
b11 [
1&
#480000
0&
#485000
1+
16
17
1&
#490000
0&
#495000
b0 I
b0 ]
b11111111111111111001100000000000 )
0(
b11111111111111111010100100000000 !
b11111111111111111010100100000000 <
1%
b111011000110000000000 "
b111011000110000000000 ;
b1111111111111111111111111111111111111111111111110101001000000000 $
b1111111111111111111111111111111111111111111111110101001000000000 :
1&
#500000
0&
#505000
b0 [
b0 G
1&
#510000
0&
#515000
0+
0E
07
b1 G
0Y
06
b1 [
b10 I
b10 ]
1&
b11111111111111111001011111111110 -
b11111111111111111001011111111110 R
b11111111111111111001100000000000 *
b11111111111111111001100000000000 ,
b11111111111111111001100000000000 >
1(
b1000 l
#520000
0&
#525000
0j
01
b0 .
b0 h
b0 i
b0 g
b0 f
b1010100100000110100000 S
b1010100100000110100000 c
b1010001010000010011000 Z
b1111111111111111111111111111111111111111111111100101111111111000 \
b0 5
b1010100100000000000000 ?
b1010100100000000000000 O
b1010001001111100000000 F
b1111111111111111111111111111111111111111111111100110000000000000 H
0%
b0 /
b0 _
b101010010000011010000000000100 b
b11111111111111111001011111111110 ^
b11111111111111111001011111111110 `
b11111111111111111001011111111110 a
b10 [
b0 0
b0 K
b101010010000000000000000000000 N
b11111111111111111001100000000000 J
b11111111111111111001100000000000 L
b11111111111111111001100000000000 M
b10 G
1&
#530000
0&
#535000
1j
b11111111111111111001101000000000 .
b11111111111111111001101000000000 h
02
b111111111111111111111111 i
b1111111111111111111111111111111111111111100110100000000000000000 g
b11111111111111110011010000000000 f
b11 I
b11 ]
b1111111111111111111111111111111111111111111111110011010000000000 5
1E
b1010001001111100000000 0
b1010001001111100000000 K
1Y
b1010001010000010011000 /
b1010001010000010011000 _
1&
#540000
0&
#545000
b11 [
b11 G
1&
#550000
0&
#555000
1+
17
16
1&
#560000
0&
#565000
b0 I
b0 ]
b11111111111111111000100100000000 )
0(
b11111111111111111001101000000000 !
b11111111111111111001101000000000 <
1%
b1010001001111100000000 "
b1010001001111100000000 ;
b1111111111111111111111111111111111111111111111110011010000000000 $
b1111111111111111111111111111111111111111111111110011010000000000 :
1&
#570000
0&
#575000
b0 G
b0 [
1&
#580000
0&
#585000
0+
0Y
06
b1 [
0E
07
b1 G
b10 I
b10 ]
1&
b11111111111111111000100011111110 -
b11111111111111111000100011111110 R
b11111111111111111000100100000000 *
b11111111111111111000100100000000 ,
b11111111111111111000100100000000 >
1(
b1001 l
#590000
0&
#595000
0j
01
b0 .
b0 h
b0 i
b0 g
b0 f
b1101110101000100000000 ?
b1101110101000100000000 O
b1101010111010000000000 F
b1111111111111111111111111111111111111111111111100010010000000000 H
b0 5
b1101110101001011011100 S
b1101110101001011011100 c
b1101010111010111010100 Z
b1111111111111111111111111111111111111111111111100010001111111000 \
b0 0
b0 K
b110111010100010000000000000000 N
b11111111111111111000100100000000 J
b11111111111111111000100100000000 L
b11111111111111111000100100000000 M
b10 G
b0 /
b0 _
b110111010100101101110000000100 b
b11111111111111111000100011111110 ^
b11111111111111111000100011111110 `
b11111111111111111000100011111110 a
b10 [
0%
1&
#600000
0&
#605000
1j
b11111111111111111000101100000000 .
b11111111111111111000101100000000 h
02
b111111111111111111111111 i
b1111111111111111111111111111111111111111100010110000000000000000 g
b11111111111111110001011000000000 f
b11 ]
b11 I
b1111111111111111111111111111111111111111111111110001011000000000 5
1Y
b1101010111010111010100 /
b1101010111010111010100 _
1E
b1101010111010000000000 0
b1101010111010000000000 K
1&
#610000
0&
#615000
b11 G
b11 [
1&
#620000
0&
#625000
1+
16
17
1&
#630000
0&
#635000
b0 I
b0 ]
b11111111111111110111101000000000 )
0(
b11111111111111111000101100000000 !
b11111111111111111000101100000000 <
1%
b1101010111010000000000 "
b1101010111010000000000 ;
b1111111111111111111111111111111111111111111111110001011000000000 $
b1111111111111111111111111111111111111111111111110001011000000000 :
1&
#640000
0&
#645000
b0 [
b0 G
1&
#650000
0&
#655000
0+
0E
07
b1 G
0Y
06
b1 [
b10 I
b10 ]
1&
b11111111111111110111100111111110 -
b11111111111111110111100111111110 R
b11111111111111110111101000000000 *
b11111111111111110111101000000000 ,
b11111111111111110111101000000000 >
1(
b1010 l
#660000
0&
#665000
0j
01
b0 .
b0 h
b0 i
b0 g
b0 f
b10001100010011000011000 S
b10001100010011000011000 c
b10001000000110100010000 Z
b1111111111111111111111111111111111111111111111011110011111111000 \
b0 5
b10001100010010000000000 ?
b10001100010010000000000 O
b10001000000101100000000 F
b1111111111111111111111111111111111111111111111011110100000000000 H
0%
b0 /
b0 _
b1000110001001100001100000000100 b
b11111111111111110111100111111110 ^
b11111111111111110111100111111110 `
b11111111111111110111100111111110 a
b10 [
b0 0
b0 K
b1000110001001000000000000000000 N
b11111111111111110111101000000000 J
b11111111111111110111101000000000 L
b11111111111111110111101000000000 M
b10 G
1&
#670000
0&
#675000
1j
b11111111111111110111110000000000 .
b11111111111111110111110000000000 h
02
b111111111111111111111111 i
b1111111111111111111111111111111111111111011111000000000000000000 g
b11111111111111101111100000000000 f
b11 I
b11 ]
b1111111111111111111111111111111111111111111111101111100000000000 5
1E
b10001000000101100000000 0
b10001000000101100000000 K
1Y
b10001000000110100010000 /
b10001000000110100010000 _
1&
#680000
0&
#685000
b11 [
b11 G
1&
#690000
0&
#695000
1+
17
16
1&
#700000
0&
#705000
b0 I
b0 ]
b11111111111111110110101100000000 )
0(
b11111111111111110111110000000000 !
b11111111111111110111110000000000 <
1%
b10001000000101100000000 "
b10001000000101100000000 ;
b1111111111111111111111111111111111111111111111101111100000000000 $
b1111111111111111111111111111111111111111111111101111100000000000 :
1&
#710000
0&
#715000
b0 G
b0 [
1&
#720000
0&
#725000
0+
0Y
06
0E
07
1&
b1011 l
