Internship_IITH/4D_gradient_descent_V1.0/func_grad_val_diff_test/fixed_32_add_sub.v
module fixed_32_add_sub(
    input signed [31:0] a_in,      // Input operand A (Q24.8)
    input signed [31:0] b_in,      // Input operand B (Q24.8)
    input               sub_n_add, // Control signal: 0 for Add, 1 for Subtract
    output signed [31:0] sum_diff_out, // Result (A+B or A-B) (Q24.8)
    output logic         overflow    // Flag for overflow detection
);
    wire signed [32:0] temp_result_wide; // 1 bit extra wide to deetect overflow 

    assign temp_result_wide = (sub_n_add == 1'b1) ?
                              ({{1{a_in[31]}}, a_in} - {{1{b_in[31]}}, b_in}) :
                              ({{1{a_in[31]}}, a_in} + {{1{b_in[31]}}, b_in});

    // Assign the lower 32 bits of the wide result to the output
    assign sum_diff_out = temp_result_wide[31:0];

    // Overflow detection
    assign overflow = (temp_result_wide[32] != sum_diff_out[31]);

endmodule

Internship_IITH/4D_gradient_descent_V1.0/fixed_32_mult.v
module fixed_32_mult(
    input signed [31:0] a_in,    // Input operand A (Q24.8 format)
    input signed [31:0] b_in,    // Input operand B (Q24.8 format)
    output signed [31:0] p_out,  // Product P (Q24.8 format)
    output logic overflow,        // Flag for overflow detection
    output logic underflow_q       // Flag for underflow detection (going below minimum negative)
);

    localparam integer FRACT_BITS = 8;
    wire signed [63:0] product_full;

    assign product_full = a_in * b_in;
    assign p_out = product_full >>> FRACT_BITS;

    wire expected_sign = p_out[31]; // The sign bit of the result
    wire [23:0] msb_of_product_full = product_full[63:40]; // 63 - 40 + 1 = 24 bits
    assign overflow = (expected_sign == 1'b0) && (|msb_of_product_full); // Positive overflow if any MSB is 1
    assign underflow_q = (expected_sign == 1'b1) && (~(&msb_of_product_full)); // Negative overflow/underflow if any MSB is 0


endmodule

Internship_IITH/4D_gradient_descent_V1.0/func_test/Top.v
module Top(
    input clk,
    input rst_n,
    input start_func,
    input signed [15:0] a_in,       // Q8.8 format
    input signed [15:0] b_in,       // Q8.8 format
    input signed [15:0] c_in,       // Q8.8 format
    input signed [15:0] d_in,       // Q8.8 format
    output reg signed [31:0] z_out, // Q24.8 format
    output logic func_done,
    output logic overflow
);
    // func is assumed to be (a-2)^2 + (c+2)^2 + (5d)^2 + (b^2 - 5)
    // Terminology :
    //              term1 = (b^2 - 5)           
    //              term2 = (5d)^2
    //              term3 = (c+2)^2
    //              term4 = (a-2)^2

    // Sub Modules:
    //           fixed_32_mult:
    //               takes in two 32 bit Q24.8 inputs a_in and b_in
    //               produces a 32 bit Q24.8 product p_out.
    //               it has underflow and overflow outputs
    //           fixed_32_add_sub:
    //               takes in two 32 bit Q24.8 inputs a_in and b_in
    //               produces a 32 bit Q24.8 sum or diff sum_diff_out,
    //               depending on control signal sub_n_add, 0 for add, 1 for sub .
    //               it has overflow outputs

    // STAGE 1 - MULT: b^2, 5*d
    // STAGE 1 - SUM : a-2, c+2 

    // STAGE 2 - MULT: (a-2)^2, (c+2)^2, (5d)^2
    // STAGE 2 - SUM : b^2 - 5

    // STAGE 3 - MULT: --NIL--
    // STAGE 3 - SUM : ((a-2)^2 + (c+2)^2) , ((5d)^2 + (b^2 - 5))
    
    // STAGE 4 - MULT: --NIL--
    // STAGE 4 - SUM : ((a-2)^2 + (c+2)^2) + ((5d)^2 + (b^2 - 5))
    
    localparam IDLE         = 3'b000;
    localparam INIT         = 3'b001;
    localparam COMP_1       = 3'b010;
    localparam COMP_2       = 3'b011;
    localparam COMP_3       = 3'b100;
    localparam DONE         = 3'b101;


    localparam MINUS_FIVE   = 32'hFFFFFB00;
    localparam MINUS_TWO    = 32'hFFFFFE00;
    localparam PLUS_FIVE    = 32'h00000500;
    localparam PLUS_TWO     = 32'h00000200;

    reg signed [15:0] a_in_buffer;          // Q8.8 format, input variable
    reg signed [15:0] b_in_buffer;          // Q8.8 format, input variable
    reg signed [15:0] c_in_buffer;          // Q8.8 format, input variable
    reg signed [15:0] d_in_buffer;          // Q8.8 format, input variable

    wire signed [31:0] term1_partial;       // Q24.8 format, wire storing partial calc
    wire signed [31:0] term2_partial;       // Q24.8 format, wire storing partial calc
    wire signed [31:0] term3_partial;       // Q24.8 format, wire storing partial calc
    wire signed [31:0] term4_partial;       // Q24.8 format, wire storing partial calc
    
    reg signed [31:0] term1_partial_reg;    // Q24.8 format, registered partial at the end of calc
    reg signed [31:0] term2_partial_reg;    // Q24.8 format, registered partial at the end of calc
    reg signed [31:0] term3_partial_reg;    // Q24.8 format, registered partial at the end of calc
    reg signed [31:0] term4_partial_reg;    // Q24.8 format, registered partial at the end of calc

    wire signed [31:0] term1;               // Q24.8 format, wire storing calculated term
    wire signed [31:0] term2;               // Q24.8 format, wire storing calculated term
    wire signed [31:0] term3;               // Q24.8 format, wire storing calculated term
    wire signed [31:0] term4;               // Q24.8 format, wire storing calculated term
    
    reg signed [31:0] term1_reg;            // Q24.8 format, registered calculated term
    reg signed [31:0] term2_reg;            // Q24.8 format, registered calculated term
    reg signed [31:0] term3_reg;            // Q24.8 format, registered calculated term
    reg signed [31:0] term4_reg;            // Q24.8 format, registered calculated term

    wire signed [31:0] term1_plus_term2;    // Q24.8 format, wire summations of term1 and term2 
    wire signed [31:0] term3_plus_term4;    // Q24.8 format, wire summations of term3 and term4

    reg signed [31:0] term1_plus_term2_reg; // Q24.8 format, registered summations of term1 and term2
    reg signed [31:0] term3_plus_term4_reg; // Q24.8 format, registered summations of term3 and term4
    
    wire signed [31:0] final_value;         // Q24.8 format, wire summations of all terms


    reg [2:0] curr_state;
    reg [2:0] next_state;



always @(*) begin
    next_state = curr_state;
    case (curr_state)
        IDLE        : begin if (start_func)  next_state = INIT; end
        INIT        : begin next_state = COMP_1; end
        COMP_1      : begin next_state = COMP_2; end
        COMP_2      : begin next_state = COMP_3; end
        COMP_3      : begin next_state = DONE; end
        DONE        : begin if (!start_func) next_state = IDLE; end
        default     : begin next_state = IDLE; end
    endcase
end

    always @(posedge clk, negedge rst_n) begin 
        if (!rst_n) begin
            a_in_buffer         <=  16'd0;
            b_in_buffer         <=  16'd0;
            c_in_buffer         <=  16'd0;
            d_in_buffer         <=  16'd0;
            z_out               <=  32'd0;

            curr_state          <=  IDLE;
            func_done           <=  1'b0;
            overflow            <=  1'b0;

            term1_partial_reg   <=  32'd0;   
            term2_partial_reg   <=  32'd0;
            term3_partial_reg   <=  32'd0;
            term4_partial_reg   <=  32'd0;

            term1_reg           <=  32'd0;
            term2_reg           <=  32'd0;
            term3_reg           <=  32'd0;
            term4_reg           <=  32'd0;

            term1_plus_term2_reg<=  32'd0;
            term3_plus_term4_reg<=  32'd0;
            final_value         <=  32'd0;
        end else begin
            curr_state <= next_state;
            case (curr_state)
                IDLE: begin 
                    // DO NOTHING
                    func_done <= 1'b0; 
                end
                INIT: begin     
                    // func_done <= 1'b0; 
                    a_in_buffer <= a_in;
                    b_in_buffer <= b_in;
                    c_in_buffer <= c_in;
                    d_in_buffer <= d_in;
                    // Computation of Stage 1 Begin
                end
                COMP_1: begin
                    // Computation of Stage 1 registered   
                    term1_partial_reg <= term1_partial;
                    term2_partial_reg <= term2_partial;
                    term3_partial_reg <= term3_partial;
                    term4_partial_reg <= term4_partial;
                    // Computation of Stage 2 Begin 
                end             

                COMP_2: begin
                    // Computation of Stage 2 registered   
                    term1_reg <= term1;
                    term2_reg <= term2;
                    term3_reg <= term3;
                    term4_reg <= term4;
                    // Computation of Stage 3 Begin        
                end     

                COMP_3: begin
                    // Computation of Stage 3 registered   
                    term1_plus_term2_reg <= term1_plus_term2;
                    term3_plus_term4_reg <= term3_plus_term4;
                    // Computation of Stage 4 Begin
                end             
                DONE: begin
                    // Computation of Stage 4 registered   
                    z_out <= final_value;
                    func_done <= 1'b1;
                end             
            endcase
        end
    end



    //-----------------------STAGE 1 ----------------------------
    fixed_32_mult t1_par(       // Calculate b^2
        .a_in({{16{b_in_buffer[15]}},b_in_buffer}),  // 16 bit input sign extended to 32
        .b_in({{16{b_in_buffer[15]}},b_in_buffer}),  // 16 bit input sign extended to 32
        .p_out(term1_partial),
        .overflow(),
        .underflow_q() 
    );


    fixed_32_mult t2_par(       // Calculate 5*d
        .a_in({{16{d_in_buffer[15]}},d_in_buffer}) , // 16 bit input sign extended to 32
        .b_in(PLUS_FIVE),                            // Constant
        .p_out(term2_partial),
        .overflow(),
        .underflow_q()
    );

    fixed_32_add_sub t3_par(    // Calculate c + 2
        .a_in({{16{c_in_buffer[15]}},c_in_buffer}), // Input buffered into register
        .b_in(PLUS_TWO),                            // Constant
        .sub_n_add(1'b0),
        .sum_diff_out(term3_partial),   // Wire Output registed at next clock edge for the next stage
        .overflow()
    );
    
    fixed_32_add_sub t4_par(    // Calculate a - 2
        .a_in({{16{a_in_buffer[15]}},a_in_buffer}),// Input buffered into register
        .b_in(PLUS_TWO),                           // Constant
        .sub_n_add(1'b1),
        .sum_diff_out(term4_partial),   // Wire Output registed at next clock edge for the next stage           
        .overflow()
    );

    //-----------------------STAGE 1 ----------------------------

    //-----------------------STAGE 2 ----------------------------


    fixed_32_add_sub t1(    // Calculate b^2 - 5
        .a_in(term1_partial_reg),                   // Registered Input from prior stage
        .b_in(PLUS_FIVE),                          // Constant
        .sub_n_add(1'b1),
        .sum_diff_out(term1),   // Wire Output registed at next clock edge for the next stage
        .overflow()
    );

    fixed_32_mult t2(       // Calculate (5*d)^2
        .a_in(term2_partial_reg),                    // Registered Input from prior stage
        .b_in(term2_partial_reg),                    // Registered Input from prior stage
        .p_out(term2),       // Wire Output registed at next clock edge for the next stage
        .overflow(),
        .underflow_q()
    );

    fixed_32_mult t3(       // Calculate (c + 2)^2
        .a_in(term3_partial_reg),                    // Registered Input from prior stage
        .b_in(term3_partial_reg),                    // Registered Input from prior stage
        .p_out(term3),       // Wire Output registed at next clock edge for the next stage
        .overflow(),
        .underflow_q()
    );

    fixed_32_mult t4(       // Calculate (a - 2)^2
        .a_in(term4_partial_reg),                    // Registered Input from prior stage
        .b_in(term4_partial_reg),                    // Registered Input from prior stage
        .p_out(term4),       // Wire Output registed at next clock edge for the next stage
        .overflow(),
        .underflow_q()
    );

    //-----------------------STAGE 2 ----------------------------
    
    //-----------------------STAGE 3 ----------------------------
    fixed_32_add_sub t1_sum_t2(    //Calculate (b^2 - 5) + (5*d)^2
        .a_in(term1_reg),                           // Registered Input from prior stage
        .b_in(term2_reg),                           // Registered Input from prior stage
        .sub_n_add(1'b0),
        .sum_diff_out(term1_plus_term2),    // Wire Output registed at next clock edge for the next stage
        .overflow()
    );    
    
    fixed_32_add_sub t3_sum_t4(    // Calculate (c+2)^2 + (a-2)^2
        .a_in(term3_reg),                           // Registered Input from prior stage
        .b_in(term4_reg),                           // Registered Input from prior stage
        .sub_n_add(1'b0),
        .sum_diff_out(term3_plus_term4),    // Wire Output registed at next clock edge for the next stage
        .overflow()
    );

    //-----------------------STAGE 3 ----------------------------

    //-----------------------STAGE 4 ----------------------------
    
    fixed_32_add_sub final_val(    // Calculate ((a-2)^2 + (c+2)^2) + ((5d)^2 + (b^2 - 5))
        .a_in(term1_plus_term2_reg),                // Registered Input from prior stage
        .b_in(term3_plus_term4_reg),                // Registered Input from prior stage
        .sub_n_add(1'b0),
        .sum_diff_out(final_value),     // Wire Output registed at next clock edge for the next stage
        .overflow()
    );

    //-----------------------STAGE 4 ----------------------------


endmodule

Internship_IITH/4D_gradient_descent_V1.0/func_test/Top_tb.v
`timescale 1ns / 1ps

module Top_tb;

    reg clk;
    reg rst_n;
    reg start_func;
    reg signed [15:0] a_input;          // 16 bit Q8.8 foramt
    reg signed [15:0] b_input;          // 16 bit Q8.8 foramt
    reg signed [15:0] c_input;          // 16 bit Q8.8 foramt
    reg signed [15:0] d_input;          // 16 bit Q8.8 foramt
    reg signed [15:0] a_input_buffer;   // 16 bit Q8.8 foramt
    reg signed [15:0] b_input_buffer;   // 16 bit Q8.8 foramt
    reg signed [15:0] c_input_buffer;   // 16 bit Q8.8 foramt
    reg signed [15:0] d_input_buffer;   // 16 bit Q8.8 foramt
    

// WIRE DECLARATION
    wire func_done;
    wire overflow;
    wire [31:0] z_output;
    Top uut (
        .clk(clk),
        .rst_n(rst_n),
        .start_func(start_func),
        .a_in(a_input_buffer), // 16 bit Q8.8 foramt
        .b_in(b_input_buffer), // 16 bit Q8.8 foramt
        .c_in(c_input_buffer), // 16 bit Q8.8 foramt
        .d_in(d_input_buffer), // 16 bit Q8.8 foramt
        .z_out(z_output),      // 32 bit Q24.8 foramt
        .func_done(func_done), 
        .overflow(overflow)
    );

// clk generation
    initial begin
        clk = 0;
        forever #5 clk = ~clk; // 10 ns period (100 MHz) 
    end

// Test sequence 
    initial begin
        integer i;

        // Storing values for waveform simulation
        $dumpfile("tb_top.vcd");
        $dumpvars(0, Top_tb);

        rst_n = 1'b0;      // Assert Reset
        start_func = 1'b0; // Disasset Start of func
        a_input = 16'h0000; // Initial Input
        b_input = 16'h0000; // Initial Input
        c_input = 16'h0000; // Initial Input
        d_input = 16'h0000; // Initial Input

        $display("---------------------------------------------------------");
        $display("-----Starting Testbench for Default 4 input Function-----");
        $display("---------------------------------------------------------");

        #20 rst_n = 1'b1;  // Disassert reset

        for (i = 1; i < 11; i = i+1 )begin 
            a_input_buffer = a_input;
            b_input_buffer = b_input;
            c_input_buffer = c_input;
            d_input_buffer = d_input;

            start_func = 1'b1;
            //#20; // wait for ouput to settle

            wait(func_done == 1'b1);
            $display("\n--- Test Case %0d: Initial a = %f, b = %f, c = %f, d = %f, (Q8.8) ---", i, $itor(a_input) / 256.0, $itor(b_input) / 256.0, $itor(c_input) / 256.0, $itor(d_input) / 256.0);
            $display("a input : %f (0x%H)", $itor(a_input) / 256.0, a_input);
            $display("b input : %f (0x%H)", $itor(b_input) / 256.0, b_input);
            $display("c input : %f (0x%H)", $itor(c_input) / 256.0, c_input);
            $display("d input : %f (0x%H)", $itor(d_input) / 256.0, d_input);
            $display("z output: %f (0x%H)", $itor(z_output) / 256.0, z_output);
            start_func = 1'b0;
            wait(func_done == 1'b0);
            // @(posedge clk);
            a_input = a_input + 16'h0040;  // decimal 0.25 in Q8.8 fromat
            b_input = b_input + 16'h0040;  // decimal 0.25 in Q8.8 fromat
            c_input = c_input + 16'h0040;  // decimal 0.25 in Q8.8 fromat
            d_input = d_input + 16'h0040;  // decimal 0.25 in Q8.8 fromat
            #5;
        end
        $finish; // end simulation
    end
endmodule

Internship_IITH/4D_gradient_descent_V1.0/func_test/tb_top.vcd
$date
	Thu Jun 19 13:04:00 2025
$end
$version
	Icarus Verilog
$end
$timescale
	1ps
$end
$scope module Top_tb $end
$var wire 32 ! z_output [31:0] $end
$var wire 1 " overflow $end
$var wire 1 # func_done $end
$var reg 16 $ a_input [15:0] $end
$var reg 16 % a_input_buffer [15:0] $end
$var reg 16 & b_input [15:0] $end
$var reg 16 ' b_input_buffer [15:0] $end
$var reg 16 ( c_input [15:0] $end
$var reg 16 ) c_input_buffer [15:0] $end
$var reg 1 * clk $end
$var reg 16 + d_input [15:0] $end
$var reg 16 , d_input_buffer [15:0] $end
$var reg 1 - rst_n $end
$var reg 1 . start_func $end
$scope module uut $end
$var wire 16 / a_in [15:0] $end
$var wire 16 0 b_in [15:0] $end
$var wire 16 1 c_in [15:0] $end
$var wire 1 * clk $end
$var wire 16 2 d_in [15:0] $end
$var wire 1 - rst_n $end
$var wire 1 . start_func $end
$var wire 32 3 term4_partial [31:0] $end
$var wire 32 4 term4 [31:0] $end
$var wire 32 5 term3_plus_term4 [31:0] $end
$var wire 32 6 term3_partial [31:0] $end
$var wire 32 7 term3 [31:0] $end
$var wire 32 8 term2_partial [31:0] $end
$var wire 32 9 term2 [31:0] $end
$var wire 32 : term1_plus_term2 [31:0] $end
$var wire 32 ; term1_partial [31:0] $end
$var wire 32 < term1 [31:0] $end
$var wire 32 = final_value [31:0] $end
$var parameter 3 > COMP_1 $end
$var parameter 3 ? COMP_2 $end
$var parameter 3 @ COMP_3 $end
$var parameter 3 A DONE $end
$var parameter 3 B IDLE $end
$var parameter 3 C INIT $end
$var parameter 32 D MINUS_FIVE $end
$var parameter 32 E MINUS_TWO $end
$var parameter 32 F PLUS_FIVE $end
$var parameter 32 G PLUS_TWO $end
$var reg 16 H a_in_buffer [15:0] $end
$var reg 16 I b_in_buffer [15:0] $end
$var reg 16 J c_in_buffer [15:0] $end
$var reg 3 K curr_state [2:0] $end
$var reg 16 L d_in_buffer [15:0] $end
$var reg 1 # func_done $end
$var reg 3 M next_state [2:0] $end
$var reg 1 " overflow $end
$var reg 32 N term1_partial_reg [31:0] $end
$var reg 32 O term1_plus_term2_reg [31:0] $end
$var reg 32 P term1_reg [31:0] $end
$var reg 32 Q term2_partial_reg [31:0] $end
$var reg 32 R term2_reg [31:0] $end
$var reg 32 S term3_partial_reg [31:0] $end
$var reg 32 T term3_plus_term4_reg [31:0] $end
$var reg 32 U term3_reg [31:0] $end
$var reg 32 V term4_partial_reg [31:0] $end
$var reg 32 W term4_reg [31:0] $end
$var reg 32 X z_out [31:0] $end
$scope module final_val $end
$var wire 32 Y a_in [31:0] $end
$var wire 32 Z b_in [31:0] $end
$var wire 1 [ overflow $end
$var wire 1 \ sub_n_add $end
$var wire 33 ] temp_result_wide [32:0] $end
$var wire 32 ^ sum_diff_out [31:0] $end
$upscope $end
$scope module t1 $end
$var wire 32 _ a_in [31:0] $end
$var wire 32 ` b_in [31:0] $end
$var wire 1 a overflow $end
$var wire 1 b sub_n_add $end
$var wire 33 c temp_result_wide [32:0] $end
$var wire 32 d sum_diff_out [31:0] $end
$upscope $end
$scope module t1_par $end
$var wire 32 e a_in [31:0] $end
$var wire 32 f b_in [31:0] $end
$var wire 1 g overflow $end
$var wire 1 h underflow_q $end
$var wire 64 i product_full [63:0] $end
$var wire 32 j p_out [31:0] $end
$var wire 24 k msb_of_product_full [23:0] $end
$var wire 1 l expected_sign $end
$var parameter 32 m FRACT_BITS $end
$upscope $end
$scope module t1_sum_t2 $end
$var wire 32 n a_in [31:0] $end
$var wire 32 o b_in [31:0] $end
$var wire 1 p overflow $end
$var wire 1 q sub_n_add $end
$var wire 33 r temp_result_wide [32:0] $end
$var wire 32 s sum_diff_out [31:0] $end
$upscope $end
$scope module t2 $end
$var wire 32 t a_in [31:0] $end
$var wire 32 u b_in [31:0] $end
$var wire 1 v overflow $end
$var wire 1 w underflow_q $end
$var wire 64 x product_full [63:0] $end
$var wire 32 y p_out [31:0] $end
$var wire 24 z msb_of_product_full [23:0] $end
$var wire 1 { expected_sign $end
$var parameter 32 | FRACT_BITS $end
$upscope $end
$scope module t2_par $end
$var wire 32 } a_in [31:0] $end
$var wire 32 ~ b_in [31:0] $end
$var wire 1 !" overflow $end
$var wire 1 "" underflow_q $end
$var wire 64 #" product_full [63:0] $end
$var wire 32 $" p_out [31:0] $end
$var wire 24 %" msb_of_product_full [23:0] $end
$var wire 1 &" expected_sign $end
$var parameter 32 '" FRACT_BITS $end
$upscope $end
$scope module t3 $end
$var wire 32 (" a_in [31:0] $end
$var wire 32 )" b_in [31:0] $end
$var wire 1 *" overflow $end
$var wire 1 +" underflow_q $end
$var wire 64 ," product_full [63:0] $end
$var wire 32 -" p_out [31:0] $end
$var wire 24 ." msb_of_product_full [23:0] $end
$var wire 1 /" expected_sign $end
$var parameter 32 0" FRACT_BITS $end
$upscope $end
$scope module t3_par $end
$var wire 32 1" a_in [31:0] $end
$var wire 32 2" b_in [31:0] $end
$var wire 1 3" overflow $end
$var wire 1 4" sub_n_add $end
$var wire 33 5" temp_result_wide [32:0] $end
$var wire 32 6" sum_diff_out [31:0] $end
$upscope $end
$scope module t3_sum_t4 $end
$var wire 32 7" a_in [31:0] $end
$var wire 32 8" b_in [31:0] $end
$var wire 1 9" overflow $end
$var wire 1 :" sub_n_add $end
$var wire 33 ;" temp_result_wide [32:0] $end
$var wire 32 <" sum_diff_out [31:0] $end
$upscope $end
$scope module t4 $end
$var wire 32 =" a_in [31:0] $end
$var wire 32 >" b_in [31:0] $end
$var wire 1 ?" overflow $end
$var wire 1 @" underflow_q $end
$var wire 64 A" product_full [63:0] $end
$var wire 32 B" p_out [31:0] $end
$var wire 24 C" msb_of_product_full [23:0] $end
$var wire 1 D" expected_sign $end
$var parameter 32 E" FRACT_BITS $end
$upscope $end
$scope module t4_par $end
$var wire 32 F" a_in [31:0] $end
$var wire 32 G" b_in [31:0] $end
$var wire 1 H" overflow $end
$var wire 1 I" sub_n_add $end
$var wire 33 J" temp_result_wide [32:0] $end
$var wire 32 K" sum_diff_out [31:0] $end
$upscope $end
$upscope $end
$scope begin $unm_blk_19 $end
$var integer 32 L" i [31:0] $end
$upscope $end
$upscope $end
$enddefinitions $end
$comment Show the parameter values. $end
$dumpall
b1000 E"
b1000 0"
b1000 '"
b1000 |
b1000 m
b1000000000 G
b10100000000 F
b11111111111111111111111000000000 E
b11111111111111111111101100000000 D
b1 C
b0 B
b101 A
b100 @
b11 ?
b10 >
$end
#0
$dumpvars
bx L"
b11111111111111111111111000000000 K"
b111111111111111111111111000000000 J"
1I"
0H"
b1000000000 G"
b0 F"
0D"
b0 C"
b0 B"
b0 A"
0@"
0?"
b0 >"
b0 ="
b0 <"
b0 ;"
0:"
09"
b0 8"
b0 7"
b1000000000 6"
b1000000000 5"
04"
03"
b1000000000 2"
b0 1"
0/"
b0 ."
b0 -"
b0 ,"
0+"
0*"
b0 )"
b0 ("
0&"
b0 %"
b0 $"
b0 #"
0""
0!"
b10100000000 ~
b0 }
0{
b0 z
b0 y
b0 x
0w
0v
b0 u
b0 t
b0 s
b0 r
0q
0p
b0 o
b0 n
0l
b0 k
b0 j
b0 i
0h
0g
b0 f
b0 e
b11111111111111111111101100000000 d
b111111111111111111111101100000000 c
1b
0a
b10100000000 `
b0 _
b0 ^
b0 ]
0\
0[
b0 Z
b0 Y
b0 X
b0 W
b0 V
b0 U
b0 T
b0 S
b0 R
b0 Q
b0 P
b0 O
b0 N
b0 M
b0 L
b0 K
b0 J
b0 I
b0 H
b0 =
b11111111111111111111101100000000 <
b0 ;
b0 :
b0 9
b0 8
b0 7
b1000000000 6
b0 5
b0 4
b11111111111111111111111000000000 3
bx 2
bx 1
bx 0
bx /
0.
0-
bx ,
b0 +
0*
bx )
b0 (
bx '
b0 &
bx %
b0 $
0#
0"
b0 !
$end
#5000
1*
#10000
0*
#15000
1*
#20000
b1 M
0*
1.
b0 ,
b0 2
b0 )
b0 1
b0 '
b0 0
b0 %
b0 /
b1 L"
1-
#25000
b10 M
b1 K
1*
#30000
0*
#35000
b11 M
b10 K
1*
#40000
0*
#45000
b10000000000 4
b10000000000 B"
b10000000000 7
b10000000000 -"
b100 M
b1000000000000000000 A"
b11111111111111111111111000000000 V
b11111111111111111111111000000000 ="
b11111111111111111111111000000000 >"
b1000000000000000000 ,"
b1000000000 S
b1000000000 ("
b1000000000 )"
b11 K
1*
#50000
0*
#55000
b100000000000 5
b100000000000 <"
b11111111111111111111101100000000 :
b11111111111111111111101100000000 s
b100000000000 ;"
b111111111111111111111101100000000 r
b101 M
b10000000000 W
b10000000000 8"
b10000000000 U
b10000000000 7"
b11111111111111111111101100000000 P
b11111111111111111111101100000000 n
b100 K
1*
#60000
0*
#65000
0[
b1100000000 =
b1100000000 ^
b1100000000 ]
b100000000000 T
b100000000000 Z
b11111111111111111111101100000000 O
b11111111111111111111101100000000 Y
b101 K
1*
#70000
0*
#75000
b0 M
0.
1#
b1100000000 !
b1100000000 X
1*
#80000
0*
#85000
b0 K
1*
#90000
0*
#95000
b1 M
1.
b1000000 ,
b1000000 2
b1000000 )
b1000000 1
b1000000 '
b1000000 0
b1000000 %
b1000000 /
b10 L"
b1000000 +
b1000000 (
b1000000 &
b1000000 $
0#
1*
#100000
0*
#105000
b10 M
b1 K
1*
#110000
0*
#115000
b101000000 8
b101000000 $"
b1001000000 6
b1001000000 6"
b10000 ;
b10000 j
b11111111111111111111111001000000 3
b11111111111111111111111001000000 K"
b1001000000 5"
b111111111111111111111111001000000 J"
b11 M
b10100000000000000 #"
b1000000 }
b1000000 L
b1000000 1"
b1000000 J
b1000000000000 i
b1000000 e
b1000000 f
b1000000 I
b1000000 F"
b1000000 H
b10 K
1*
#120000
0*
#125000
b1100010000 4
b1100010000 B"
b10100010000 7
b10100010000 -"
b110010000 9
b110010000 y
b11111111111111111111101100010000 <
b11111111111111111111101100010000 d
b111111111111111111111101100010000 c
b100 M
b110001000000000000 A"
b11111111111111111111111001000000 V
b11111111111111111111111001000000 ="
b11111111111111111111111001000000 >"
b1010001000000000000 ,"
b1001000000 S
b1001000000 ("
b1001000000 )"
b11001000000000000 x
b101000000 Q
b101000000 t
b101000000 u
b10000 N
b10000 _
b11 K
1*
#130000
0*
#135000
b100000100000 5
b100000100000 <"
b11111111111111111111110010100000 :
b11111111111111111111110010100000 s
b100000100000 ;"
b111111111111111111111110010100000 r
b101 M
b1100010000 W
b1100010000 8"
b10100010000 U
b10100010000 7"
b110010000 R
b110010000 o
b11111111111111111111101100010000 P
b11111111111111111111101100010000 n
b100 K
1*
#140000
0*
#145000
b10011000000 =
b10011000000 ^
b10011000000 ]
b100000100000 T
b100000100000 Z
b11111111111111111111110010100000 O
b11111111111111111111110010100000 Y
b101 K
1*
#150000
0*
#155000
b0 M
0.
1#
b10011000000 !
b10011000000 X
1*
#160000
0*
#165000
b0 K
1*
#170000
0*
#175000
b1 M
1.
b10000000 ,
b10000000 2
b10000000 )
b10000000 1
b10000000 '
b10000000 0
b10000000 %
b10000000 /
b11 L"
b10000000 +
b10000000 (
b10000000 &
b10000000 $
0#
1*
#180000
0*
#185000
b10 M
b1 K
1*
#190000
0*
#195000
b1010000000 8
b1010000000 $"
b1010000000 6
b1010000000 6"
b1000000 ;
b1000000 j
b11111111111111111111111010000000 3
b11111111111111111111111010000000 K"
b1010000000 5"
b111111111111111111111111010000000 J"
b11 M
b101000000000000000 #"
b10000000 }
b10000000 L
b10000000 1"
b10000000 J
b10000000 e
b100000000000000 i
b10000000 f
b10000000 I
b10000000 F"
b10000000 H
b10 K
1*
#200000
0*
#205000
b1001000000 4
b1001000000 B"
b11001000000 7
b11001000000 -"
b11001000000 9
b11001000000 y
b11111111111111111111101101000000 <
b11111111111111111111101101000000 d
b111111111111111111111101101000000 c
b100 M
b100100000000000000 A"
b11111111111111111111111010000000 V
b11111111111111111111111010000000 ="
b11111111111111111111111010000000 >"
b1100100000000000000 ,"
b1010000000 S
b1010000000 ("
b1010000000 )"
b1100100000000000000 x
b1010000000 Q
b1010000000 t
b1010000000 u
b1000000 N
b1000000 _
b11 K
1*
#210000
0*
#215000
0p
b100010000000 5
b100010000000 <"
b110000000 :
b110000000 s
b100010000000 ;"
b110000000 r
b101 M
b1001000000 W
b1001000000 8"
b11001000000 U
b11001000000 7"
b11001000000 R
b11001000000 o
b11111111111111111111101101000000 P
b11111111111111111111101101000000 n
b100 K
1*
#220000
0*
#225000
0[
b101000000000 =
b101000000000 ^
b101000000000 ]
b100010000000 T
b100010000000 Z
b110000000 O
b110000000 Y
b101 K
1*
#230000
0*
#235000
b0 M
0.
1#
b101000000000 !
b101000000000 X
1*
#240000
0*
#245000
b0 K
1*
#250000
0*
#255000
b1 M
1.
b11000000 ,
b11000000 2
b11000000 )
b11000000 1
b11000000 '
b11000000 0
b11000000 %
b11000000 /
b100 L"
b11000000 +
b11000000 (
b11000000 &
b11000000 $
0#
1*
#260000
0*
#265000
b10 M
b1 K
1*
#270000
0*
#275000
b1111000000 8
b1111000000 $"
b1011000000 6
b1011000000 6"
b10010000 ;
b10010000 j
b11111111111111111111111011000000 3
b11111111111111111111111011000000 K"
b1011000000 5"
b111111111111111111111111011000000 J"
b11 M
b111100000000000000 #"
b11000000 }
b11000000 L
b11000000 1"
b11000000 J
b11000000 e
b1001000000000000 i
b11000000 f
b11000000 I
b11000000 F"
b11000000 H
b10 K
1*
#280000
0*
#285000
b110010000 4
b110010000 B"
b11110010000 7
b11110010000 -"
b111000010000 9
b111000010000 y
b11111111111111111111101110010000 <
b11111111111111111111101110010000 d
b111111111111111111111101110010000 c
b100 M
b11001000000000000 A"
b11111111111111111111111011000000 V
b11111111111111111111111011000000 ="
b11111111111111111111111011000000 >"
b1111001000000000000 ,"
b1011000000 S
b1011000000 ("
b1011000000 )"
b11100001000000000000 x
b1111000000 Q
b1111000000 t
b1111000000 u
b10010000 N
b10010000 _
b11 K
1*
#290000
0*
#295000
b100100100000 5
b100100100000 <"
b100110100000 :
b100110100000 s
b100100100000 ;"
b100110100000 r
b101 M
b110010000 W
b110010000 8"
b11110010000 U
b11110010000 7"
b111000010000 R
b111000010000 o
b11111111111111111111101110010000 P
b11111111111111111111101110010000 n
b100 K
1*
#300000
0*
#305000
b1001011000000 =
b1001011000000 ^
b1001011000000 ]
b100100100000 T
b100100100000 Z
b100110100000 O
b100110100000 Y
b101 K
1*
#310000
0*
#315000
b0 M
0.
1#
b1001011000000 !
b1001011000000 X
1*
#320000
0*
#325000
b0 K
1*
#330000
0*
#335000
b1 M
1.
b100000000 ,
b100000000 2
b100000000 )
b100000000 1
b100000000 '
b100000000 0
b100000000 %
b100000000 /
b101 L"
b100000000 +
b100000000 (
b100000000 &
b100000000 $
0#
1*
#340000
0*
#345000
b10 M
b1 K
1*
#350000
0*
#355000
b10100000000 8
b10100000000 $"
b1100000000 6
b1100000000 6"
b100000000 ;
b100000000 j
b11111111111111111111111100000000 3
b11111111111111111111111100000000 K"
b1100000000 5"
b111111111111111111111111100000000 J"
b11 M
b1010000000000000000 #"
b100000000 }
b100000000 L
b100000000 1"
b100000000 J
b100000000 e
b10000000000000000 i
b100000000 f
b100000000 I
b100000000 F"
b100000000 H
b10 K
1*
#360000
0*
