Veri/1_Bit_Full_adder_using_Half_adder/full_half_add_1bit.v
module full_half_add_1bit(
                          i_a     ,  
                          i_b     ,   
                          i_cin   ,  
                          o_sum   ,  
                          o_carry    
                          )       ;


input  i_a, i_b, i_cin            ;    
output o_sum, o_carry             ;
wire   w_sum1, w_carry1, w_carry2 ;

half_adder h1(                       
              .h_a(i_a)           ,   
              .h_b(i_b)           ,
              .h_sum(w_sum1)      ,	
              .h_carry(w_carry1)    
              )                   ;
half_adder h2(                       
              .h_a(w_sum1)        ,
              .h_b(i_cin)         ,
              .h_sum(o_sum)       ,	
              .h_carry(w_carry2)
              )                   ;

assign o_carry = w_carry1 | w_carry2;
  
endmodule 


module half_adder(
	            h_a,	
	            h_b,	
               	h_sum,	
	            h_carry    
);


input  h_a	   ;
input  h_b	   ;
output h_sum	;
output h_carry	;
  

assign h_sum   =  h_a ^ h_b;	
assign h_carry =  h_a & h_b;	
  
endmodule

Veri/1_Bit_Full_adder_using_Half_adder/full_half_add_1bit_tb.v
`include "full_half_add_1bit.v"
`timescale 1ns/1ns

module full_half_add_1bit_tb  ;
   reg a, b, cin              ;  
   wire sum, carry	         ;  
   reg new_sum, new_carry     ;  

full_half_add_1bit dut(
                       .i_a(a)           ,		
                       .i_b(b)           ,		
                       .i_cin(cin)       ,      
                       .o_sum(sum)       ,		 
                       .o_carry(carry)	         
                       );

initial begin 
   $dumpfile("full_half_add_1bit_tb.vcd");
   $dumpvars(0, full_half_add_1bit_tb);
   repeat(100)
      begin
         stimulus();                                
      end
      $finish;
end
  
task stimulus     ;    
   reg A, B, Cin  ;    

   begin 
   A   = $random;   
   B   = $random;   
   Cin = $random;   

    
   a   = A;          
   b   = B;          
   cin = Cin;          
    
   {new_carry, new_sum} = A + B + Cin;#1; 
   
   end
    
endtask     
  
endmodule

Veri/1_Bit_Full_adder_using_Half_adder/full_half_add_1bit_tb.vcd
$date
	Fri May 09 20:44:49 2025
$end
$version
	Icarus Verilog
$end
$timescale
	1ns
$end
$scope module full_half_add_1bit_tb $end
$var wire 1 ! sum $end
$var wire 1 " carry $end
$var reg 1 # a $end
$var reg 1 $ b $end
$var reg 1 % cin $end
$var reg 1 & new_carry $end
$var reg 1 ' new_sum $end
$scope module dut $end
$var wire 1 # i_a $end
$var wire 1 $ i_b $end
$var wire 1 % i_cin $end
$var wire 1 " o_carry $end
$var wire 1 ( w_sum1 $end
$var wire 1 ) w_carry2 $end
$var wire 1 * w_carry1 $end
$var wire 1 ! o_sum $end
$scope module h1 $end
$var wire 1 # h_a $end
$var wire 1 $ h_b $end
$var wire 1 * h_carry $end
$var wire 1 ( h_sum $end
$upscope $end
$scope module h2 $end
$var wire 1 ( h_a $end
$var wire 1 % h_b $end
$var wire 1 ) h_carry $end
$var wire 1 ! h_sum $end
$upscope $end
$upscope $end
$scope task stimulus $end
$var reg 1 + A $end
$var reg 1 , B $end
$var reg 1 - Cin $end
$upscope $end
$upscope $end
$enddefinitions $end
$comment Show the parameter values. $end
$dumpall
$end
#0
$dumpvars
1-
1,
0+
0*
1)
1(
0'
1&
1%
1$
0#
1"
0!
$end
#1
1!
0)
0(
1*
1'
1#
1+
#2
0!
1)
1"
1(
0*
0'
0$
0,
#5
0"
1!
0)
0&
1'
0%
1$
0#
0-
1,
0+
#6
0!
1"
0(
1*
1&
0'
1#
1+
#7
1!
0"
1(
0*
0&
1'
0$
0,
#8
1$
0#
1,
0+
#9
1"
0(
1*
1&
1%
1#
1-
1+
#10
0"
1(
0*
0&
0%
0$
0-
0,
#11
0(
1%
0#
1-
0+
#12
1"
0!
1)
1(
1&
0'
1$
1,
#13
1!
0)
0(
1*
1'
1#
1+
#14
0"
0*
0&
0$
0#
0,
0+
#15
1"
0!
1*
1&
0'
0%
1$
1#
0-
1,
1+
#16
0"
0*
0&
0$
0#
0,
0+
#17
1!
1(
1'
1$
1,
#18
1"
0!
1)
1&
0'
1%
1-
#19
0"
0)
0(
0&
0%
0$
0-
0,
#20
1!
1'
1%
1-
#21
1"
1*
1&
1$
1#
1,
1+
#22
0"
1(
0*
0&
0%
0$
0-
0,
#23
1"
0(
1*
1&
1%
1$
1-
1,
#24
0"
0*
0&
0$
0#
0,
0+
#25
1"
0!
1)
1(
1&
0'
1#
1+
#27
0)
0(
1*
0%
1$
0-
1,
#29
0"
0*
0&
0$
0#
0,
0+
#30
1"
1*
1&
1$
1#
1,
1+
#31
1)
1(
0*
1%
0#
1-
0+
#32
1!
0)
0(
1*
1'
1#
1+
#33
0!
1)
1"
1(
0*
0'
0#
0+
#34
0"
1!
0)
0&
1'
0%
0$
1#
0-
0,
1+
#35
0!
0(
0'
0#
0+
#36
1!
1'
1%
1-
#37
1"
1*
1&
1$
1#
1,
1+
#38
0!
1)
1"
1(
0*
0'
0$
0,
#39
0"
1!
0)
0&
1'
0%
0-
#40
0!
1"
0(
1*
1&
0'
1$
1,
#41
1!
1'
1%
1-
#42
0"
1(
0*
0&
0%
0$
0-
0,
#43
1$
0#
1,
0+
#44
0(
1%
0$
1-
0,
#45
1(
0%
1#
0-
1+
#47
1$
0#
1,
0+
#49
1"
0(
1*
1&
1%
1#
1-
1+
#50
0!
0'
0%
0-
#51
0"
1!
0*
0&
1'
1%
0$
0#
1-
0,
0+
#53
1(
0%
1#
0-
1+
#54
1"
0!
1)
1&
0'
1%
1$
0#
1-
1,
0+
#55
0"
0)
0(
0&
0%
0$
0-
0,
#56
1"
1*
1&
1$
1#
1,
1+
#57
0"
1!
0*
0&
1'
1%
0$
0#
1-
0,
0+
#59
0!
0'
0%
0-
#60
1"
1)
1(
1&
1%
1#
1-
1+
#61
0"
1!
0)
0&
1'
0%
0-
#62
0(
1%
0#
1-
0+
#63
0!
0'
0%
0-
#64
1"
1)
1(
1&
1%
1$
1-
1,
#65
0$
1#
0,
1+
#66
0)
0(
1*
0%
1$
0-
1,
#67
1)
1(
0*
1%
0#
1-
0+
#68
1!
0)
0(
1*
1'
1#
1+
#69
0!
1)
1"
1(
0*
0'
0#
0+
#70
0"
0)
0(
0&
0%
0$
0-
0,
#71
1"
1)
1(
1&
1%
1$
1-
1,
#72
0"
1!
0)
0(
0&
1'
0$
0,
#76
1"
0!
1*
1&
0'
0%
1$
1#
0-
1,
1+
#77
0"
1!
0*
0&
1'
1%
0$
0#
1-
0,
0+
#79
0!
0'
0%
0-
#80
1!
1(
1'
1$
1,
#81
0(
1%
0$
1-
0,
#82
1"
0!
1)
1(
1&
0'
1#
1+
#83
1!
0)
0(
1*
1'
1$
1,
#84
0!
1)
1"
1(
0*
0'
0#
0+
#85
0"
1!
0)
0&
1'
0%
0$
1#
0-
0,
1+
#87
0!
1"
0(
1*
1&
0'
1$
1,
#88
1!
0"
1(
0*
0&
1'
0#
0+
#90
0!
1"
0(
1*
1&
0'
1#
1+
#91
1)
1(
0*
1%
0$
1-
0,
#92
0"
1!
0)
0(
0&
1'
0#
0+
#93
0!
0'
0%
0-
#94
1"
1!
1*
1&
1'
1%
1$
1#
1-
1,
1+
#95
0!
0'
0%
0-
#96
1!
1'
1%
1-
#97
0"
0!
0*
0&
0'
0%
0$
0#
0-
0,
0+
#99
1"
1!
1*
1&
1'
1%
1$
1#
1-
1,
1+
