Internship_IITH/general_linear_regressor_V2.0/grad_val_diff_test/fixed_128_add.v
module fixed_128_add(
    input signed [127:0] a_in,    // Input operand A (Q56.8 format)
    input signed [127:0] b_in,    // Input operand B (Q56.8 format)
    output signed [127:0] sum,  // sum P (Q120.8 format)
    output logic overflow,        // Flag for overflow detection
    output logic underflow_q       // Flag for underflow detection (going below minimum negative)
);

    assign sum = a_in + b_in;

    // Positive overflow: (a_in > 0 and b_in > 0 and sum < 0)
    assign overflow = (a_in[127] == 1'b0) && (b_in[127] == 1'b0) && (sum[127] == 1'b1);

    // Negative underflow: (a_in < 0 and b_in < 0 and sum > 0)
    assign underflow_q = (a_in[127] == 1'b1) && (b_in[127] == 1'b1) && (sum[127] == 1'b0);

endmodule

Internship_IITH/general_linear_regressor_V2.0/grad_val_diff_test/fixed_128_mult.v
module fixed_128_mult(
    input signed [127:0] a_in,    // Input operand A (Q56.8 format)
    input signed [127:0] b_in,    // Input operand B (Q56.8 format)
    output signed [127:0] p_out,  // Product P (Q120.8 format)
    output logic overflow,        // Flag for overflow detection
    output logic underflow_q       // Flag for underflow detection (going below minimum negative)
);

    localparam integer FRACT_BITS = 8;
    wire signed [255:0] product_full;

    assign product_full = a_in * b_in;
    assign p_out = product_full [127 + FRACT_BITS : FRACT_BITS];

    wire expected_sign = product_full[127 + FRACT_BITS];; // The sign bit of the result
    wire [255 : 127 + FRACT_BITS + 1] higher_bits = product_full[255 : 127 + FRACT_BITS + 1];
    assign overflow = (!expected_sign) && (|higher_bits);
    assign underflow_q = (expected_sign) && (~(&higher_bits)); // &higher_bits checks if all bits are 1
endmodule

Internship_IITH/general_linear_regressor_V2.0/func_test/Top.v
module Top#(
    A0 = 32'h00000100,   //1.0 in decimal Q24.8 format
    A1 = 32'h00000000,  //0.0 in decimal Q24.8 format
    A2 = 32'hFFFFFF80,   //-0.5 in decimal Q24.8 format
    A3 = 32'h00000000,   //0.0 in decimal Q24.8 format
    A4 = 32'h0000000A   //0.0390625 in decimal Q24.8 format
)(
    input clk,
    input rst_n,
    input start_func,
    input signed [31:0] x_in,  
    output reg signed [127:0] y_out,
    output reg func_done,
    output reg overflow
    // a4*​x^4 + a3*​x^3 + a2*​x^2 + a1*​x + a0​
    // SET UP COS(x)
);


// wire signed [127:0] x;          
wire signed [127:0] term1;
wire signed [127:0] term2_partial;
wire signed [127:0] term2;
wire signed [127:0] term3_partial;
wire signed [127:0] term3;
wire signed [127:0] term4_partial;
wire signed [127:0] term4;
wire signed [127:0] term0_add_term1_out;
wire signed [127:0] term0_add_term1_add_term2_out;
wire signed [127:0] term3_add_term4_out;
wire signed [127:0] final_polynomial;


// STAGE 1: Calculate_product -> A1 * x, x * x
// STAGE 1: Calculate_SUM     -> --Nil--

// STAGE 2: Calculate_product -> A2 * x^2, x^2 * x, x^2 * x^2
// STAGE 2: Calculate_SUM     -> A1*x + A0

// STAGE 3: Calculate_product -> A3 * x^3, A4 * x^4
// STAGE 3: Calculate_SUM     -> (A1*x + A0) + A2*x^2

// STAGE 4: Calculate_product -> --Nil--
// STAGE 4: Calculate_SUM     -> A3*x^3 + A4*x^4

// STAGE 5: Calculate_product -> --Nil--
// STAGE 5: Calculate_SUM     -> ((A1*x + A0) + A2*x^2) + (A3*x^3 + A4*x^4)  -> Final Plynomial 



// --------------STAGE 1-------------------
fixed_128_mult term1_inst(              // caclulate a1*x
    .a_in({{96{x_val[31]}}, x_val }),   // 32 bit Q24.8 x_val sign extended to 128 bit Q56.8
    .b_in({{96{A1[31]}}, A1 }),         // 32 bit Q24.8 constant sign extended to 128 bit Q56.8
    .p_out(term1),                      // 128 bit product Q120:8 
    .overflow(),
    .underflow_q()
);

fixed_128_mult x_sq_par(                // caclulate x^2
    .a_in({{96{x_val[31]}}, x_val }),     // 32 bit Q24.8 x_val sign extended to 128 bit Q56.8
    .b_in({{96{x_val[31]}}, x_val }),     // 32 bit Q24.8 x_val sign extended to 128 bit Q56.8
    .p_out(term2_partial),              // 128 bit product Q120:8 
    .overflow(),
    .underflow_q()
);

// ------------STAGE 1-----------------------

// ------------STAGE 2-------------------------
fixed_128_mult term2_inst(              // caclulate a2*x^2
    .a_in(term2_partial),               // 64 bit x^2 
    .b_in({{96{A2[31]}}, A2}),          // 32 bit constant sign extended to 128 bit
    .p_out(term2),                      // 128 bit product Q120:8 
    .overflow(),
    .underflow_q()
);

fixed_128_mult x_cu_par(                // caclulate x^3
    .a_in({{96{x_val[31]}}, x_val }),     // 32 bit x_in sign extended to 128 bit
    .b_in(term2_partial),               // 64 bit term2 
    .p_out(term3_partial),              // 128 bit product Q120:8 
    .overflow(),
    .underflow_q()
);


fixed_128_mult x_qu_par(                // caclulate x^4
    .a_in(term2_partial),               // 64 bit x^2 partial 
    .b_in(term2_partial),               // 64 bit x^2 partial 
    .p_out(term4_partial),              // 128 bit product Q120:8 
    .overflow(),
    .underflow_q()
);

fixed_128_add term0_add_term1(          // term1 + term0
    .a_in(term1),                       // 128 bit term 1
    .b_in({{96{A0[31]}}, A0 }),         // 32 bit x_in sign extended to 128 bit
    .sum(term0_add_term1_out),        // 128 bit sum term0 + term 1 Q120:8
    .overflow(),
    .underflow_q()
);

// ------------STAGE 2-------------------------

// ------------STAGE 3-------------------------

fixed_128_mult term3_inst (             // caclulate a3*x^3
    .a_in(term3_partial),               // 64 bit x^3 partial 
    .b_in({{96{A3[31]}}, A3 }),         // 32 bit constant sign extended to 128 bit
    .p_out(term3),                      // 128 bit product Q120:8 
    .overflow(),
    .underflow_q()
);

fixed_128_mult term4_inst (             // caclulate a4*x^4
    .a_in(term4_partial),               // 64 bit x^4 partial 
    .b_in({{96{A4[31]}}, A4 }),         // 32 bit constant sign extended to 128 bit
    .p_out(term4),                      // 128 bit product Q120:8 
    .overflow(),
    .underflow_q()
);

fixed_128_add term0_add_term1_add_term2(// term0 + term1 + term2 
    .a_in(term0_add_term1_out),         // 128 bit term0 + term 1 
    .b_in(term2),                       // 128 bit term2
    .sum(term0_add_term1_add_term2_out),  // 128 bit sum term0 + term1 + term2 Q120:8
    .overflow(),
    .underflow_q()
);


// ------------STAGE 3-------------------------

// ------------STAGE 4-------------------------


fixed_128_add term3_add_term4(          // term3 + term4
    .a_in(term3),                       // 128 bit term 3
    .b_in(term4),                       // 128 bit term 4
    .sum(term3_add_term4_out),        // 128 bit sum term3 + term4 
    .overflow(),
    .underflow_q()
);


// ------------STAGE 4-------------------------

// ------------STAGE 5-------------------------

fixed_128_add final_poly(               // final term0 + term1 + term2 + term3 + term4
    .a_in(term3_add_term4_out),         // 128 bit term3 + term4
    .b_in(term0_add_term1_add_term2_out),// 128 bit term0 + term1 + term2 
    .sum(final_polynomial),           // 128 bit sum final
    .overflow(),
    .underflow_q()
);

// ------------STAGE 5-------------------------


localparam IDLE             = 3'b000;
localparam INIT             = 3'b001;
localparam COMP_1           = 3'b010;   // calculate a1*x, x^2
localparam COMP_2           = 3'b011;   // calculate a2*x^2, x^3, x^4, (a1*x + a0)
localparam COMP_3           = 3'b100;   // calculate a3*x^3, a4*x^4, ((a1*x + a0) + a2*x^2)
localparam COMP_4           = 3'b101;   // calculate (a3*x^3 + a4*x^4)
localparam COMP_5           = 3'b110;   // calculate ((a3*x^3 + a4*x^4) + ((a1*x + a0) + a2*x^2))
localparam STATE_DONE       = 3'b111;



reg [2:0] curr_state;
reg [2:0] next_state;
reg compute_done ;
reg signed [31:0] x_val;



always @(*) begin
    next_state = curr_state;
    case (curr_state)
        IDLE        : begin if (start_func)  next_state = INIT; end
        INIT        : begin next_state = COMP_1; end
        COMP_1      : begin next_state = COMP_2; end
        COMP_2      : begin next_state = COMP_3; end
        COMP_3      : begin next_state = COMP_4; end
        COMP_4      : begin next_state = COMP_5; end
        COMP_5      : begin next_state = STATE_DONE; end
        STATE_DONE  : begin if (!start_func) next_state = IDLE; end
        default     : begin next_state = IDLE; end
    endcase

end

always_ff @(posedge clk, negedge rst_n) begin 
    if (!rst_n) begin
        curr_state  <= IDLE;
        func_done   <= 1'b0;
        x_val       <= 32'd0;   
        y_out       <= 128'd0; 
        compute_done <= 1'b0;
        overflow    <= 1'b0;
    end else begin 
        curr_state <= next_state;
        case (curr_state)
            IDLE : begin
                // DO NOTHING
                func_done <= 1'b0;
                compute_done <= 1'b0;   
            end  
            INIT : begin
                x_val <= x_in;
                y_out <= 128'd0;
                func_done <= 1'b0;
                compute_done <= 1'b0;   
            end
            COMP_5: begin 
                y_out <= final_polynomial;
                compute_done <= 1'b1;
                overflow <= 1'b0;  
            end
            STATE_DONE : begin 
                func_done <= 1'b1;
            end
            default : begin
                // DO NOTHING
            end
        endcase
    end 
end


endmodule

Internship_IITH/general_linear_regressor_V2.0/func_test/Top_tb.v
`timescale 1ns / 1ps

module Top_tb;

    reg clk;
    reg rst_n;
    reg start_func;
    reg signed [31:0] x_input;          // 32 bit Q24.8 foramt
    reg signed [31:0] x_input_buffer;   // 32 bit Q24.8 foramt
    

// WIRE DECLARATION
    wire func_done;
    wire [127:0] y_output;               // 64 bit Q56.8 foramt
    wire overflow;
    Top uut (
        .clk(clk),
        .rst_n(rst_n),
        .start_func(start_func),
        .x_in(x_input_buffer), // 32 bit Q24.8 foramt
        .y_out(y_output),      // 64 bit Q56.8 foramt
        .func_done(func_done), 
        .overflow(overflow)
    );

// clk generation
    initial begin
        clk = 0;
        forever #5 clk = ~clk; // 10 ns period (100 MHz) 
    end

// Test sequence 
    initial begin
        integer i;

        // Storing values for waveform simulation
        $dumpfile("tb_top.vcd");
        $dumpvars(0, Top_tb);

        rst_n = 1'b0;      // Assert Reset
        start_func = 1'b0; // Disasset Start of func
        x_input = 32'h00000000; // Initial Input

        $display("---------------------------------------------------------");
        $display("----Starting Testbench for Default Polynomial Function---");
        $display("---------------------------------------------------------");

        #20 rst_n = 1'b1;  // Disassert reset

        for (i = 1; i < 11; i = i+1 )begin 
            start_func = 1'b1;
            x_input_buffer = x_input;
            #20; // wait for ouput to settle

            wait(func_done == 1'b1);
            $display("\n--- Test Case %0d: Initial x = %f (Q24.8) ---", i, $itor(x_input) / 256.0);
            $display("X input : %f (0x%H)", $itor(x_input) / 256.0, x_input);
            $display("Y output: %f (0x%H)", $itor(y_output) / 256.0, y_output);

            start_func = 1'b0;
            x_input = x_input + 32'h00000040;  // decimal 0.109 in Q24.8 fromat
            #20;
        end
        $finish; // end simulation
    end
endmodule

Internship_IITH/general_linear_regressor_V2.0/func_test/tb_top.vcd
$date
	Tue Jun 17 21:41:10 2025
$end
$version
	Icarus Verilog
$end
$timescale
	1ps
$end
$scope module Top_tb $end
$var wire 128 ! y_output [127:0] $end
$var wire 1 " overflow $end
$var wire 1 # func_done $end
$var reg 1 $ clk $end
$var reg 1 % rst_n $end
$var reg 1 & start_func $end
$var reg 32 ' x_input [31:0] $end
$var reg 32 ( x_input_buffer [31:0] $end
$scope module uut $end
$var wire 1 $ clk $end
$var wire 1 % rst_n $end
$var wire 1 & start_func $end
$var wire 32 ) x_in [31:0] $end
$var wire 128 * term4_partial [127:0] $end
$var wire 128 + term4 [127:0] $end
$var wire 128 , term3_partial [127:0] $end
$var wire 128 - term3_add_term4_out [127:0] $end
$var wire 128 . term3 [127:0] $end
$var wire 128 / term2_partial [127:0] $end
$var wire 128 0 term2 [127:0] $end
$var wire 128 1 term1 [127:0] $end
$var wire 128 2 term0_add_term1_out [127:0] $end
$var wire 128 3 term0_add_term1_add_term2_out [127:0] $end
$var wire 128 4 final_polynomial [127:0] $end
$var parameter 32 5 A0 $end
$var parameter 32 6 A1 $end
$var parameter 32 7 A2 $end
$var parameter 32 8 A3 $end
$var parameter 32 9 A4 $end
$var parameter 3 : COMP_1 $end
$var parameter 3 ; COMP_2 $end
$var parameter 3 < COMP_3 $end
$var parameter 3 = COMP_4 $end
$var parameter 3 > COMP_5 $end
$var parameter 3 ? IDLE $end
$var parameter 3 @ INIT $end
$var parameter 3 A STATE_DONE $end
$var reg 1 B compute_done $end
$var reg 3 C curr_state [2:0] $end
$var reg 1 # func_done $end
$var reg 3 D next_state [2:0] $end
$var reg 1 " overflow $end
$var reg 32 E x_val [31:0] $end
$var reg 128 F y_out [127:0] $end
$scope module final_poly $end
$var wire 1 G overflow $end
$var wire 1 H underflow_q $end
$var wire 128 I sum [127:0] $end
$var wire 128 J b_in [127:0] $end
$var wire 128 K a_in [127:0] $end
$upscope $end
$scope module term0_add_term1 $end
$var wire 128 L b_in [127:0] $end
$var wire 1 M overflow $end
$var wire 1 N underflow_q $end
$var wire 128 O sum [127:0] $end
$var wire 128 P a_in [127:0] $end
$upscope $end
$scope module term0_add_term1_add_term2 $end
$var wire 128 Q a_in [127:0] $end
$var wire 1 R overflow $end
$var wire 1 S underflow_q $end
$var wire 128 T sum [127:0] $end
$var wire 128 U b_in [127:0] $end
$upscope $end
$scope module term1_inst $end
$var wire 128 V a_in [127:0] $end
$var wire 128 W b_in [127:0] $end
$var wire 1 X overflow $end
$var wire 1 Y underflow_q $end
$var wire 256 Z product_full [255:0] $end
$var wire 128 [ p_out [127:0] $end
$var wire 120 \ higher_bits [255:136] $end
$var wire 1 ] expected_sign $end
$var parameter 32 ^ FRACT_BITS $end
$upscope $end
$scope module term2_inst $end
$var wire 128 _ b_in [127:0] $end
$var wire 1 ` overflow $end
$var wire 1 a underflow_q $end
$var wire 256 b product_full [255:0] $end
$var wire 128 c p_out [127:0] $end
$var wire 120 d higher_bits [255:136] $end
$var wire 1 e expected_sign $end
$var wire 128 f a_in [127:0] $end
$var parameter 32 g FRACT_BITS $end
$upscope $end
$scope module term3_add_term4 $end
$var wire 1 h overflow $end
$var wire 1 i underflow_q $end
$var wire 128 j sum [127:0] $end
$var wire 128 k b_in [127:0] $end
$var wire 128 l a_in [127:0] $end
$upscope $end
$scope module term3_inst $end
$var wire 128 m b_in [127:0] $end
$var wire 1 n overflow $end
$var wire 1 o underflow_q $end
$var wire 256 p product_full [255:0] $end
$var wire 128 q p_out [127:0] $end
$var wire 120 r higher_bits [255:136] $end
$var wire 1 s expected_sign $end
$var wire 128 t a_in [127:0] $end
$var parameter 32 u FRACT_BITS $end
$upscope $end
$scope module term4_inst $end
$var wire 128 v b_in [127:0] $end
$var wire 1 w overflow $end
$var wire 1 x underflow_q $end
$var wire 256 y product_full [255:0] $end
$var wire 128 z p_out [127:0] $end
$var wire 120 { higher_bits [255:136] $end
$var wire 1 | expected_sign $end
$var wire 128 } a_in [127:0] $end
$var parameter 32 ~ FRACT_BITS $end
$upscope $end
$scope module x_cu_par $end
$var wire 128 !" a_in [127:0] $end
$var wire 1 "" overflow $end
$var wire 1 #" underflow_q $end
$var wire 256 $" product_full [255:0] $end
$var wire 128 %" p_out [127:0] $end
$var wire 120 &" higher_bits [255:136] $end
$var wire 1 '" expected_sign $end
$var wire 128 (" b_in [127:0] $end
$var parameter 32 )" FRACT_BITS $end
$upscope $end
$scope module x_qu_par $end
$var wire 1 *" overflow $end
$var wire 1 +" underflow_q $end
$var wire 256 ," product_full [255:0] $end
$var wire 128 -" p_out [127:0] $end
$var wire 120 ." higher_bits [255:136] $end
$var wire 1 /" expected_sign $end
$var wire 128 0" b_in [127:0] $end
$var wire 128 1" a_in [127:0] $end
$var parameter 32 2" FRACT_BITS $end
$upscope $end
$scope module x_sq_par $end
$var wire 128 3" a_in [127:0] $end
$var wire 128 4" b_in [127:0] $end
$var wire 1 5" overflow $end
$var wire 1 6" underflow_q $end
$var wire 256 7" product_full [255:0] $end
$var wire 128 8" p_out [127:0] $end
$var wire 120 9" higher_bits [255:136] $end
$var wire 1 :" expected_sign $end
$var parameter 32 ;" FRACT_BITS $end
$upscope $end
$upscope $end
$scope begin $unm_blk_20 $end
$var integer 32 <" i [31:0] $end
$upscope $end
$upscope $end
$enddefinitions $end
$comment Show the parameter values. $end
$dumpall
b1000 ;"
b1000 2"
b1000 )"
b1000 ~
b1000 u
b1000 g
b1000 ^
b111 A
b1 @
b0 ?
b110 >
b101 =
b100 <
b11 ;
b10 :
b1010 9
b0 8
b11111111111111111111111110000000 7
b0 6
b100000000 5
$end
#0
$dumpvars
bx <"
0:"
b0 9"
b0 8"
b0 7"
06"
05"
b0 4"
b0 3"
b0 1"
b0 0"
0/"
b0 ."
b0 -"
b0 ,"
0+"
0*"
b0 ("
0'"
b0 &"
b0 %"
b0 $"
0#"
0""
b0 !"
b0 }
0|
b0 {
b0 z
b0 y
0x
0w
b1010 v
b0 t
0s
b0 r
b0 q
b0 p
0o
0n
b0 m
b0 l
b0 k
b0 j
0i
0h
b0 f
0e
b0 d
b0 c
b0 b
0a
0`
b11111111111111111111111111111111111111111111111111111111111111111111111111111111111111111111111111111111111111111111111110000000 _
0]
b0 \
b0 [
b0 Z
0Y
0X
b0 W
b0 V
b0 U
b100000000 T
0S
0R
b100000000 Q
b0 P
b100000000 O
0N
0M
b100000000 L
b0 K
b100000000 J
b100000000 I
0H
0G
b0 F
b0 E
b0 D
b0 C
0B
b100000000 4
b100000000 3
b100000000 2
b0 1
b0 0
b0 /
b0 .
b0 -
b0 ,
b0 +
b0 *
bx )
bx (
b0 '
0&
0%
0$
0#
0"
b0 !
$end
#5000
1$
#10000
0$
#15000
1$
#20000
b1 D
0$
b0 (
b0 )
1&
b1 <"
1%
#25000
b10 D
b1 C
1$
#30000
0$
#35000
b11 D
b10 C
1$
#40000
0$
#45000
b100 D
b11 C
1$
#50000
0$
#55000
b101 D
b100 C
1$
#60000
0$
#65000
b110 D
b101 C
1$
#70000
0$
#75000
b111 D
b110 C
1$
#80000
0$
#85000
1B
b100000000 !
b100000000 F
b111 C
1$
#90000
0$
#95000
b0 D
b1000000 '
0&
1#
1$
#100000
0$
#105000
b0 C
1$
#110000
0$
#115000
0B
0#
b1 C
b10 D
1$
b1000000 (
b1000000 )
1&
b10 <"
#120000
0$
#125000
b1010 y
b1 *
b1 }
b1 -"
b100 ,
b100 t
b100 %"
b11111000 4
b11111000 I
b11111000 3
b11111000 J
b11111000 T
b11111111111111111111111111111111111111111111111111111111111111111111111111111111111111111111111111111111111111111111111111111000 0
b11111111111111111111111111111111111111111111111111111111111111111111111111111111111111111111111111111111111111111111111111111000 U
b11111111111111111111111111111111111111111111111111111111111111111111111111111111111111111111111111111111111111111111111111111000 c
1e
b111111111111111111111111111111111111111111111111111111111111111111111111111111111111111111111111111111111111111111111111 d
b100000000 ,"
b10000000000 $"
b1111111111111111111111111111111111111111111111111111111111111111111111111111111111111111111111111111111111111111111111111111111111111111111111111111111111111111111111111111111111111111111111111111111111111111111111111111111111111111111111111111100000000000 b
b10000 /
b10000 f
b10000 ("
b10000 0"
b10000 1"
b10000 8"
b11 D
b0 !
b0 F
b1000000 V
b1000000000000 7"
b1000000 3"
b1000000 4"
b1000000 !"
b1000000 E
b10 C
1$
#130000
0$
#135000
b100 D
b11 C
1$
#140000
0$
#145000
b101 D
b100 C
1$
#150000
0$
#155000
b110 D
b101 C
1$
#160000
0$
#165000
b111 D
b110 C
1$
#170000
0$
#175000
1B
b11111000 !
b11111000 F
b111 C
1$
#180000
0$
#185000
b0 D
b10000000 '
0&
1#
1$
#190000
0$
#195000
b0 C
1$
#200000
0$
#205000
0B
0#
b1 C
b10 D
1$
b10000000 (
b10000000 )
1&
b11 <"
#210000
0$
#215000
b10100000 y
b10000 *
b10000 }
b10000 -"
b11100000 4
b11100000 I
b11100000 3
b11100000 J
b11100000 T
b11111111111111111111111111111111111111111111111111111111111111111111111111111111111111111111111111111111111111111111111111100000 0
b11111111111111111111111111111111111111111111111111111111111111111111111111111111111111111111111111111111111111111111111111100000 U
b11111111111111111111111111111111111111111111111111111111111111111111111111111111111111111111111111111111111111111111111111100000 c
b1000000000000 ,"
b1111111111111111111111111111111111111111111111111111111111111111111111111111111111111111111111111111111111111111111111111111111111111111111111111111111111111111111111111111111111111111111111111111111111111111111111111111111111111111111111111110000000000000 b
b1000000 /
b1000000 f
b1000000 ("
b1000000 0"
b1000000 1"
b1000000 8"
b100000 ,
b100000 t
b100000 %"
b11 D
b0 !
b0 F
b10000000 V
b10000000 3"
b100000000000000 7"
b10000000 4"
b10000000000000 $"
b10000000 !"
b10000000 E
b10 C
1$
#220000
0$
#225000
b100 D
b11 C
1$
#230000
0$
#235000
b101 D
b100 C
1$
#240000
0$
#245000
b110 D
b101 C
1$
#250000
0$
#255000
b111 D
b110 C
1$
#260000
0$
#265000
1B
b11100000 !
b11100000 F
b111 C
1$
#270000
0$
#275000
b0 D
b11000000 '
0&
1#
1$
#280000
0$
#285000
b0 C
1$
#290000
0$
#295000
0B
0#
b1 C
b10 D
1$
b11000000 (
b11000000 )
1&
b100 <"
#300000
0$
#305000
b11 -
b11 K
b11 j
b11 +
b11 k
b11 z
b1100101010 y
b1010001 *
b1010001 }
b1010001 -"
b10111011 4
b10111011 I
b10111000 3
b10111000 J
b10111000 T
b11111111111111111111111111111111111111111111111111111111111111111111111111111111111111111111111111111111111111111111111110111000 0
b11111111111111111111111111111111111111111111111111111111111111111111111111111111111111111111111111111111111111111111111110111000 U
b11111111111111111111111111111111111111111111111111111111111111111111111111111111111111111111111111111111111111111111111110111000 c
b101000100000000 ,"
b1111111111111111111111111111111111111111111111111111111111111111111111111111111111111111111111111111111111111111111111111111111111111111111111111111111111111111111111111111111111111111111111111111111111111111111111111111111111111111111111111011100000000000 b
b10010000 /
b10010000 f
b10010000 ("
b10010000 0"
b10010000 1"
b10010000 8"
b1101100 ,
b1101100 t
b1101100 %"
b11 D
b0 !
b0 F
b11000000 V
b11000000 3"
b1001000000000000 7"
b11000000 4"
b110110000000000 $"
b11000000 !"
b11000000 E
b10 C
1$
#310000
0$
#315000
b100 D
b11 C
1$
#320000
0$
#325000
b101 D
b100 C
1$
#330000
0$
#335000
b110 D
b101 C
1$
#340000
0$
#345000
b111 D
b110 C
1$
#350000
0$
#355000
1B
b10111011 !
b10111011 F
b111 C
1$
#360000
0$
#365000
b0 D
b100000000 '
0&
1#
1$
#370000
0$
#375000
b0 C
1$
#380000
0$
#385000
0B
0#
b1 C
b10 D
1$
b100000000 (
b100000000 )
1&
b101 <"
#390000
0$
#395000
b1010 -
b1010 K
b1010 j
b1010 +
b1010 k
b1010 z
b101000000000 y
b100000000 *
b100000000 }
b100000000 -"
b10001010 4
b10001010 I
b10000000 3
b10000000 J
b10000000 T
b11111111111111111111111111111111111111111111111111111111111111111111111111111111111111111111111111111111111111111111111110000000 0
b11111111111111111111111111111111111111111111111111111111111111111111111111111111111111111111111111111111111111111111111110000000 U
b11111111111111111111111111111111111111111111111111111111111111111111111111111111111111111111111111111111111111111111111110000000 c
b10000000000000000 ,"
b1111111111111111111111111111111111111111111111111111111111111111111111111111111111111111111111111111111111111111111111111111111111111111111111111111111111111111111111111111111111111111111111111111111111111111111111111111111111111111111111111000000000000000 b
b100000000 /
b100000000 f
b100000000 ("
b100000000 0"
b100000000 1"
b100000000 8"
b100000000 ,
b100000000 t
b100000000 %"
b11 D
b0 !
b0 F
b100000000 V
b100000000 3"
b10000000000000000 7"
b100000000 4"
b10000000000000000 $"
b100000000 !"
b100000000 E
b10 C
1$
#400000
0$
#405000
b100 D
b11 C
1$
#410000
0$
#415000
b101 D
b100 C
1$
#420000
0$
#425000
b110 D
b101 C
1$
#430000
0$
#435000
b111 D
b110 C
1$
#440000
0$
#445000
1B
b10001010 !
b10001010 F
b111 C
1$
#450000
0$
#455000
b0 D
b101000000 '
0&
1#
1$
#460000
0$
#465000
b0 C
1$
#470000
0$
#475000
0B
0#
b1 C
b10 D
1$
b101000000 (
b101000000 )
1&
b110 <"
#480000
0$
#485000
b11000 -
b11000 K
b11000 j
b11000 +
b11000 k
b11000 z
b1100001101010 y
b1001110001 *
b1001110001 }
b1001110001 -"
b1010000 4
b1010000 I
b111000 3
b111000 J
b111000 T
b11111111111111111111111111111111111111111111111111111111111111111111111111111111111111111111111111111111111111111111111100111000 0
b11111111111111111111111111111111111111111111111111111111111111111111111111111111111111111111111111111111111111111111111100111000 U
b11111111111111111111111111111111111111111111111111111111111111111111111111111111111111111111111111111111111111111111111100111000 c
b100111000100000000 ,"
b1111111111111111111111111111111111111111111111111111111111111111111111111111111111111111111111111111111111111111111111111111111111111111111111111111111111111111111111111111111111111111111111111111111111111111111111111111111111111111111111110011100000000000 b
b110010000 /
b110010000 f
b110010000 ("
b110010000 0"
b110010000 1"
b110010000 8"
b111110100 ,
b111110100 t
b111110100 %"
b11 D
b0 !
b0 F
b101000000 V
b101000000 3"
b11001000000000000 7"
b101000000 4"
b11111010000000000 $"
b101000000 !"
b101000000 E
b10 C
1$
#490000
0$
#495000
b100 D
b11 C
1$
#500000
0$
#505000
b101 D
b100 C
1$
#510000
0$
#515000
b110 D
b101 C
1$
#520000
0$
#525000
b111 D
b110 C
1$
#530000
0$
#535000
1B
b1010000 !
b1010000 F
b111 C
1$
#540000
0$
#545000
b0 D
b110000000 '
0&
1#
1$
#550000
0$
#555000
b0 C
1$
#560000
0$
#565000
0B
0#
b1 C
b10 D
1$
b110000000 (
b110000000 )
1&
b111 <"
#570000
0$
#575000
0G
b110010 -
b110010 K
b110010 j
b110010 +
b110010 k
b110010 z
b11001010100000 y
b10100010000 *
b10100010000 }
b10100010000 -"
b10010 4
b10010 I
b11111111111111111111111111111111111111111111111111111111111111111111111111111111111111111111111111111111111111111111111111100000 3
b11111111111111111111111111111111111111111111111111111111111111111111111111111111111111111111111111111111111111111111111111100000 J
b11111111111111111111111111111111111111111111111111111111111111111111111111111111111111111111111111111111111111111111111111100000 T
b11111111111111111111111111111111111111111111111111111111111111111111111111111111111111111111111111111111111111111111111011100000 0
b11111111111111111111111111111111111111111111111111111111111111111111111111111111111111111111111111111111111111111111111011100000 U
b11111111111111111111111111111111111111111111111111111111111111111111111111111111111111111111111111111111111111111111111011100000 c
b1010001000000000000 ,"
b1111111111111111111111111111111111111111111111111111111111111111111111111111111111111111111111111111111111111111111111111111111111111111111111111111111111111111111111111111111111111111111111111111111111111111111111111111111111111111111111101110000000000000 b
b1001000000 /
b1001000000 f
b1001000000 ("
b1001000000 0"
b1001000000 1"
b1001000000 8"
b1101100000 ,
b1101100000 t
b1101100000 %"
b11 D
b0 !
b0 F
b110000000 V
b110000000 3"
b100100000000000000 7"
b110000000 4"
b110110000000000000 $"
b110000000 !"
b110000000 E
b10 C
1$
#580000
0$
#585000
b100 D
b11 C
1$
#590000
0$
#595000
b101 D
b100 C
1$
#600000
0$
#605000
b110 D
b101 C
1$
#610000
0$
#615000
b111 D
b110 C
1$
#620000
0$
#625000
1B
b10010 !
b10010 F
b111 C
1$
#630000
0$
#635000
b0 D
b111000000 '
0&
1#
1$
#640000
0$
#645000
b0 C
1$
#650000
0$
#655000
0B
0#
b1 C
b10 D
1$
b111000000 (
b111000000 )
1&
b1000 <"
#660000
0$
#665000
b1011101 -
b1011101 K
b1011101 j
b1011101 +
b1011101 k
b1011101 z
b101110111001010 y
b100101100001 *
b100101100001 }
b100101100001 -"
b11111111111111111111111111111111111111111111111111111111111111111111111111111111111111111111111111111111111111111111111111010101 4
b11111111111111111111111111111111111111111111111111111111111111111111111111111111111111111111111111111111111111111111111111010101 I
b11111111111111111111111111111111111111111111111111111111111111111111111111111111111111111111111111111111111111111111111101111000 3
b11111111111111111111111111111111111111111111111111111111111111111111111111111111111111111111111111111111111111111111111101111000 J
b11111111111111111111111111111111111111111111111111111111111111111111111111111111111111111111111111111111111111111111111101111000 T
b11111111111111111111111111111111111111111111111111111111111111111111111111111111111111111111111111111111111111111111111001111000 0
b11111111111111111111111111111111111111111111111111111111111111111111111111111111111111111111111111111111111111111111111001111000 U
b11111111111111111111111111111111111111111111111111111111111111111111111111111111111111111111111111111111111111111111111001111000 c
b10010110000100000000 ,"
b1111111111111111111111111111111111111111111111111111111111111111111111111111111111111111111111111111111111111111111111111111111111111111111111111111111111111111111111111111111111111111111111111111111111111111111111111111111111111111111111100111100000000000 b
b1100010000 /
b1100010000 f
b1100010000 ("
b1100010000 0"
b1100010000 1"
b1100010000 8"
b10101011100 ,
b10101011100 t
b10101011100 %"
b11 D
b0 !
b0 F
b111000000 V
b111000000 3"
b110001000000000000 7"
b111000000 4"
b1010101110000000000 $"
b111000000 !"
b111000000 E
b10 C
1$
#670000
0$
#675000
b100 D
b11 C
1$
#680000
0$
#685000
b101 D
b100 C
1$
#690000
0$
#695000
b110 D
b101 C
1$
#700000
0$
#705000
b111 D
b110 C
1$
#710000
0$
#715000
1B
b11111111111111111111111111111111111111111111111111111111111111111111111111111111111111111111111111111111111111111111111111010101 !
b11111111111111111111111111111111111111111111111111111111111111111111111111111111111111111111111111111111111111111111111111010101 F
b111 C
1$
#720000
0$
#725000
b0 D
b1000000000 '
0&
1#
1$
#730000
0$
#735000
b0 C
1$
#740000
0$
#745000
0B
0#
b1 C
b10 D
1$
b1000000000 (
b1000000000 )
1&
b1001 <"
#750000
0$
