Internship_IITH/general_linear_regressor/fixed_64_comp.v
module fixed_64_comp(
    input signed [63:0] a_in,  // signed Q56.8
    input signed [63:0] b_in,  // signed Q56.8
    output logic comp_result   // 1 if a_in < b_in, else 0
);
    assign comp_result = (a_in < b_in) ;
endmodule

Internship_IITH/4D_gradient_descent_V1.0/fixed_32_mult.v
module fixed_32_mult(
    input signed [31:0] a_in,    // Input operand A (Q24.8 format)
    input signed [31:0] b_in,    // Input operand B (Q24.8 format)
    output signed [31:0] p_out,  // Product P (Q24.8 format)
    output logic overflow,        // Flag for overflow detection
    output logic underflow_q       // Flag for underflow detection (going below minimum negative)
);

    localparam integer FRACT_BITS = 8;
    wire signed [63:0] product_full;

    assign product_full = a_in * b_in;
    assign p_out = product_full >>> FRACT_BITS;

    wire expected_sign = p_out[31]; // The sign bit of the result
    wire [23:0] msb_of_product_full = product_full[63:40]; // 63 - 40 + 1 = 24 bits
    assign overflow = (expected_sign == 1'b0) && (|msb_of_product_full); // Positive overflow if any MSB is 1
    assign underflow_q = (expected_sign == 1'b1) && (~(&msb_of_product_full)); // Negative overflow/underflow if any MSB is 0


endmodule

Internship_IITH/general_linear_regressor_V1.0/fixed_64_mult.v
module fixed_64_mult(
    input signed [31:0] a_in,    // Input operand A (Q24.8 format)
    input signed [31:0] b_in,    // Input operand B (Q24.8 format)
    output signed [63:0] p_out,  // Product P (Q55.8 format)
    output logic overflow        // Flag for overflow detection
);

    localparam integer FRACT_BITS = 8;
    wire signed [63:0] product_full;

    assign product_full = a_in * b_in;
    assign p_out = product_full >>> FRACT_BITS;

    assign overflow = 1'b0;

endmodule

Internship_IITH/general_linear_regressor_V1.0/func.v
module func(
    input clk,
    input rst_n,
    input start_func,
    input signed [31:0] x_in,
    output reg signed [63:0] y_out,
    output reg func_done,
    output reg overflow
);

// The default Function is assumed to be X^2 + 4x - 1

localparam STATE_IDLE       = 2'b00;
localparam STATE_INIT       = 2'b01;
localparam STATE_COMPUTE    = 2'b10;
localparam STATE_DONE       = 2'b11;
localparam MINUS_ONE        = 64'hFFFFFFFFFFFFFF00;

reg [1:0] curr_state;
reg [1:0] next_state;
reg compute_done ;
reg signed [31:0] x_val;
reg signed [63:0] four_x;
reg signed [63:0] compute_result;

wire signed [63:0] x_square;
wire overflow_x_square;

always @(*) begin
    next_state = curr_state;
    case (curr_state)
        STATE_IDLE      : begin if (start_func)  next_state = STATE_INIT; end
        STATE_INIT      : begin next_state = STATE_COMPUTE; end
        STATE_COMPUTE   : begin if (compute_done) next_state = STATE_DONE; end
        STATE_DONE      : begin if (!start_func) next_state = STATE_IDLE; end
        default         : begin next_state = STATE_IDLE; end
    endcase
    four_x = x_val << 2; // SIGN EXTENED
    compute_result = x_square + four_x + MINUS_ONE;  // Q56.8 format
end

always_ff @(posedge clk, negedge rst_n) begin 
    if (!rst_n) begin
        curr_state  <= STATE_IDLE;
        func_done   <= 1'b0;
        x_val       <= 32'd0;   
        y_out       <= MINUS_ONE; 
        compute_done <= 1'b0;
        overflow    <= 1'b0;
    end else begin 
        curr_state <= next_state;
        case (curr_state)
            STATE_IDLE : begin
                // DO NOTHING
                func_done <= 1'b0;
                compute_done <= 1'b0;   
            end  
            STATE_INIT : begin
                x_val <= x_in;
                y_out <= 64'd0;
                func_done <= 1'b0;
                compute_done <= 1'b0;   
            end
            STATE_COMPUTE: begin 
                y_out <= compute_result;
                compute_done <= 1'b1;
                overflow <= overflow_x_square;
            end
            STATE_DONE : begin 
                func_done <= 1'b1;
            end
        endcase
    end 
end

fixed_64_mult inst (   // calculate x^2
    .a_in(x_val),
    .b_in(x_val),
    .p_out(x_square),
    .overflow(overflow_x_square)
);

endmodule

Internship_IITH/general_linear_regressor/func_grad_val_diff.v
module func_grad_val_diff #(
    parameter LEARNING_RATE = 32'h00000020 // Parameter for the learning rate
)(
    input clk,            
    input rst_n,
    input start_func,     
    input signed [31:0] x_in, //(Q24.8 fixed-point format)
    output reg signed [63:0] gradient, //(Q56.8 fixed-point format)
    output reg signed [63:0] value,    //(Q56.8 fixed-point format)
    output reg signed [31:0] x_diff_out, // Change in x (LEARNING_RATE * gradient) (Q24.8 fixed-point format)
    output reg func_done,  
    output reg overflow    
);

    localparam TWO_H = 32'h00000002; // Q24.8 fixed-point format (decimal 7.8125e-3 if Q0.31, but here Q24.8 means 2 / 2^8 = 2/256)
    localparam GRADatZERO = 32'h00000400;  // Gradeint of the function at zero (where it is after reset)
    wire signed [63:0] y_out1_func; // Output of the first function (f(x_in))
    wire signed [63:0] y_out2_func; // Output of the second function (f(x_in - 2H))

    reg signed [63:0] val1_reg; // Stores the completed f(x_in)
    reg signed [63:0] val2_reg; // Stores the completed f(x_in - 2H)

    wire signed [31:0] x_in_minus_2H;
    wire signed [63:0] gradient_calc;
    wire signed [31:0] x_diff;
    wire func1_done;
    wire func2_done;
    wire overflow1;
    wire overflow2;
    wire overflow_mult;
    wire underflow_mult;

    assign x_in_minus_2H = x_in - TWO_H;

    func func_val(
        .clk(clk),
        .rst_n(rst_n),
        .start_func(start_func),
        .x_in(x_in),                     // Input x (Q24.8)
        .y_out(y_out1_func),             // Output f(x) (Q56.8)
        .func_done(func1_done),          // Completion 
        .overflow(overflow1)             // Overflow 
    );

    func inst2(
        .clk(clk),
        .rst_n(rst_n),
        .start_func(start_func),
        .x_in(x_in_minus_2H),           // Input x - 2H (Q24.8)
        .y_out(y_out2_func),            // Output f(x - 2H) (Q56.8)
        .func_done(func2_done),         // Completion 
        .overflow(overflow2)            // Overflow 
    );

    always @(posedge clk, negedge rst_n) begin
        if (!rst_n) begin
            val1_reg <= 64'd0; // Reset registered value
            val2_reg <= 64'd0; // Reset registered value
        end else begin
            if (func1_done) begin
                val1_reg <= y_out1_func; // Capture f(x_in) when its computation is done
            end
            if (func2_done) begin
                val2_reg <= y_out2_func; // Capture f(x_in - 2H) when its computation is done
            end
        end
    end

    assign gradient_calc = (val1_reg - val2_reg) << 7; // Result is Q56.8

    fixed_32_mult inst_diff(
        .a_in(LEARNING_RATE),                   // Multiplicand A (Q24.8)
        .b_in(gradient_calc[31:0]),             // Multiplicand B (Q24.8, truncated from gradient_calc)
        .p_out(x_diff),                         // Product P (Q24.8)
        .overflow(overflow_mult),               // Overflow from multiplier
        .underflow_q(underflow_mult)            // Underflow from multiplier
    );

    wire all_funcs_done;
    assign all_funcs_done = func1_done & func2_done;
    always @(posedge clk, negedge rst_n) begin
        if (!rst_n) begin
            // Reset all output registers
            gradient    <= 64'd0;
            value       <= 64'd0;
            x_diff_out  <= 32'd0; 
            func_done   <= 1'b0;
            overflow    <= 1'b0;
        end else begin
            // If both function computations are complete
            if (all_funcs_done) begin
                gradient  <= gradient_calc; // Assign the computed gradient
                value     <= y_out1_func;   // Assign the value of f(x_in)
                func_done <= 1'b1;          // Assert done signal
                overflow  <= overflow1 | overflow2 | overflow_mult;

                if (overflow_mult) begin
                    x_diff_out <= 32'h7FFFFFFF; // Capped at highest positive 32-bit signed value
                end else if (underflow_mult) begin
                    x_diff_out <= 32'h80000000; // Capped at minimum negative 32-bit signed value
                end else begin
                    x_diff_out <= x_diff;      // Assign the valid computed x_diff
                end
            end else begin
                func_done <= 1'b0; 
            end
        end
    end

endmodule

Internship_IITH/general_linear_regressor_V1.0/Top.v
// TODO:
//      {DONE} Finish func_grad_val_diff.v using |||FSM||| (Ditched FSM)
//      {DONE} Finish Top.v implementing func_grad_val_diff
//      {DONE} Write Testbech for Top.v
// TODO AFTER:
//      Write synthesis in vivado 



module Top #(
    NUM_ITERATIONS = 15,
    LEARNING_RATE = 32'h00000080
) (
    input clk,
    input rst_n,
    input start_op,
    input signed [31:0] x_init,
    output reg signed [31:0] x_at_min,
    output reg signed [63:0] y_min,
    output reg done_op
);

    // INTERNAL VARIABLE REG
    reg signed [31:0] x_in;     // Q24.8 format
    reg [$clog2(NUM_ITERATIONS + 1)-1 : 0] iter_count;
    reg func_reset;     
    reg start_func;      
    reg signed [31:0] x_at_min_inter;
    reg signed [63:0] y_min_inter;

    // REGISTERS TO HOLD STATE
    reg [2:0] current_state;
    reg [2:0] next_state;

    // INTERNAL WIREs
    wire func_done;
    wire comp_result;
    wire [31:0] x_next_val;
    wire [63:0] y_out;
    wire [31:0] x_diff_out;

    // STATE DEFINITION
    localparam STATE_IDLE = 3'b000;
    localparam STATE_INIT = 3'b001;
    localparam STATE_CALL_FUNC = 3'b010; 
    localparam STATE_CMP_STR = 3'b011; // COMPARE AND STORE
    localparam STATE_DONE = 3'b100;

    assign x_next_val = (x_in - x_diff_out);
        
    always @(*) begin 
        next_state = current_state;
        case (current_state)
            STATE_IDLE : begin 
                if (start_op) next_state = STATE_INIT;
            end
            STATE_INIT : begin 
                next_state = STATE_CALL_FUNC;
            end
            STATE_CALL_FUNC : begin 
                if (func_done) next_state = STATE_CMP_STR;
            end
            STATE_CMP_STR : begin
                if (iter_count == NUM_ITERATIONS) begin
                    next_state = STATE_DONE;
                end else begin 
                    next_state = STATE_CALL_FUNC;
                end
            end
            STATE_DONE : begin 
                if (!start_op) next_state = STATE_IDLE;
            end
        endcase
    end

    //           STATE_IDLE---------( start_op == 1)--------->STATE_INIT
    //               ʌ                                             |    
    //               |           MOVE TO IDLE WHENEVER             |
    //               |             start_op is UNSET               |
    //       (start_op == 0 )                                STATE_CALL_FUNC<-----\
    //               ʌ                                             V              |            
    //               |                                             |              |
    //           STATE_DONE<---(iter_count == NUM_ITERATIONS)<--STATE_CMP_STR     |
    //                                                             |              ʌ
    //                                                             L > (iter_count < NUM_ITERATIONS)



    always @(posedge clk, negedge rst_n) begin
        if (!rst_n) begin 
            current_state <= STATE_IDLE;
            x_in <= 32'd0;
            x_at_min <= 32'd0;
            x_at_min_inter <= 32'd0;     // Add this
            y_min <= 64'h7FFFFFFFFFFFFFFF;
            y_min_inter <= 64'h7FFFFFFFFFFFFFFF;       // Add this
            func_reset <= 1'b0;
            iter_count <= 0;
            done_op <= 1'b0;
        end else begin
            current_state <= next_state;
            case (current_state)
                STATE_IDLE : begin 
                    // DO NOTHING
                    done_op <= 1'b0;
                    func_reset <= 1'b1; // Disassert Reset Of func
                end
                STATE_INIT : begin 
                    x_in <= x_init;
                    y_min <= 64'h7FFFFFFFFFFFFFFF; // Initial y_min set to arbitrary high val
                    x_at_min <= x_init;
                    y_min_inter <= 64'h7FFFFFFFFFFFFFFF;  // Add this
                    x_at_min_inter <= x_init;             // Add this
                    iter_count <= 0;
                    start_func <= 1'b1;
                end
                STATE_CALL_FUNC : begin 
                    if (func_done) begin
                        iter_count <= iter_count +1;
                        y_min_inter <= y_out;
                        x_at_min_inter <= x_in;
                        start_func <= 1'b0;
                    end
                end
                STATE_CMP_STR : begin
                    // if (func_done)       // Trying to Prevent Race Condition of start_func being
                                            // disasserted same cycle as reading func_done 
                    if (comp_result) begin
                        y_min <= y_min_inter;
                        x_at_min <= x_at_min_inter; // could be changed to  //x_at_min <= x_in;
                    end
                    x_in <= x_next_val;
                    start_func <= 1'b1;
                end
                STATE_DONE : begin 
                    done_op <= 1'b1;
                    func_reset <= 1'b0; // assert Reset Of func
                end
            endcase
        end
    end

    // MODULE CALLS

    // Ouputs the Gradient, value & Step size of 'function under test' at x_in 
    func_grad_val_diff  #(
        .LEARNING_RATE(LEARNING_RATE)
    ) inst (
        .clk(clk),
        .rst_n(func_reset),     // FLASH the fucntion every iterations to prevent hold over garbage values 
        .start_func(start_func),// input level Flag signaling Start of function
        .x_in(x_in),            // X input of the function
        .gradient(),            // Gradient Output of the function at X
        .value(y_out),          // value of func at X
        .x_diff_out(x_diff_out),// calculated Step size to next X 
        .func_done(func_done),  // Flag so signaling func completion
        .overflow()             // Overflow Flag
    );
    fixed_64_comp compare(
        .a_in(y_min_inter),
        .b_in(y_min),
        .comp_result(comp_result)   // out put 1 if y_min_inter < y_min
    );

    
endmodule

Internship_IITH/general_linear_regressor_V1.0/tb_Top.v
`timescale 1ns / 1ps

module tb_Top;
    // Parameters for the Top module (can be overridden here for testing)
    parameter NUM_ITERATIONS = 50;
    parameter LEARNING_RATE = 32'h0000001A; // Learning Rate of 0.125 (Q24.8)
    parameter INCREMENT = 32'h00000100;     // 1.0 Increment between test cases (Q24.8)
    parameter LOOP_COUNT = 1;

    // Inputs to the Top module
    reg clk;
    reg rst_n;
    reg start_op;
    reg signed [31:0] initial_x_in;
    reg signed [31:0] test_x_val;

    // Outputs from the Top module
    wire signed [31:0] x_at_min;
    wire signed [63:0] y_min;
    wire done_op;

    // Instantiate the Top module
    Top #(
        .NUM_ITERATIONS(NUM_ITERATIONS),
        .LEARNING_RATE(LEARNING_RATE)
    ) uut_top (
        .clk(clk),
        .rst_n(rst_n),
        .start_op(start_op),    
        .x_init(initial_x_in),
        .x_at_min(x_at_min),
        .y_min(y_min),
        .done_op(done_op)
    );

    // Clock Generation
    initial begin
        clk = 0;
        forever #5 clk = ~clk; // 10ns period (100 MHz)
    end

    // Test sequence
    initial begin
        integer i;
        // For waveform dumping (optional)
        $dumpfile("tb_Top.vcd");
        $dumpvars(0, tb_Top);

        // Initialize inputs
        rst_n = 0; // Assert reset
        start_op = 0;
        initial_x_in = 32'd0;
        test_x_val = 32'hD0000000;  // 0.0 in decimal

        $display("---------------------------------------------------------");
        $display("Starting Testbench for Fixed-Point Gradient Descent");
        $display("Parameters: NUM_ITERATIONS = %0d, LEARNING_RATE = %f",
            NUM_ITERATIONS, $itor(LEARNING_RATE) / 256.0);
        $display("---------------------------------------------------------");
        #20 ;        

        initial_x_in = test_x_val; // Q24.8 (2's complement)
        rst_n = 1; // Deassert reset 
        start_op = 1;
        // #20;
        wait(done_op == 1'b1);
        $display("\n--- Test Case %0d: Initial x = %f (Q24.8) ---", i, $itor(test_x_val) / 256.0);
        $display("Initial X: %f", $itor(test_x_val) / 256.0);
        $display("Final X at Min: %f (0x%H)", $itor(x_at_min) / 256.0, x_at_min);
        $display("Min Y Value: %f (0x%H)", $itor(y_min) / 256.0, y_min);
        // Reset for next test
        // start_op = 0;
        // rst_n = 0;
        // test_x_val = test_x_val + INCREMENT; // Increment set default to 1.0
        // wait(done_op == 1'b0);
        $finish; // End simulation
    end
endmodule






        // for(i = 0; i < LOOP_COUNT; i = i + 1 ) begin
        //     initial_x_in = test_x_val; // Q24.8 (2's complement)
        //     rst_n = 1; // Deassert reset 
        //     start_op = 1;
        //     // #20;

        //     wait(done_op == 1'b1);
        //     $display("\n--- Test Case %0d: Initial x = %f (Q24.8) ---", i, $itor(test_x_val) / 256.0);
        //     $display("Initial X: %f", $itor(test_x_val) / 256.0);
        //     $display("Final X at Min: %f (0x%H)", $itor(x_at_min) / 256.0, x_at_min);
        //     $display("Min Y Value: %f (0x%H)", $itor(y_min) / 256.0, y_min);
        //     // Reset for next test
        //     start_op = 0;
        //     rst_n = 0;
        //     test_x_val = test_x_val + INCREMENT; // Increment set default to 1.0
        //     wait(done_op == 1'b0);
        //     // #10
        // end

Internship_IITH/general_linear_regressor_V1.0/tb_Top.vcd
$date
	Sun Jun 15 00:16:00 2025
$end
$version
	Icarus Verilog
$end
$timescale
	1ps
$end
$scope module tb_Top $end
$var wire 64 ! y_min [63:0] $end
$var wire 32 " x_at_min [31:0] $end
$var wire 1 # done_op $end
$var parameter 32 $ INCREMENT $end
$var parameter 32 % LEARNING_RATE $end
$var parameter 32 & LOOP_COUNT $end
$var parameter 32 ' NUM_ITERATIONS $end
$var reg 1 ( clk $end
$var reg 32 ) initial_x_in [31:0] $end
$var reg 1 * rst_n $end
$var reg 1 + start_op $end
$var reg 32 , test_x_val [31:0] $end
$scope module uut_top $end
$var wire 1 ( clk $end
$var wire 1 * rst_n $end
$var wire 1 + start_op $end
$var wire 32 - x_init [31:0] $end
$var wire 64 . y_out [63:0] $end
$var wire 32 / x_next_val [31:0] $end
$var wire 32 0 x_diff_out [31:0] $end
$var wire 1 1 func_done $end
$var wire 1 2 comp_result $end
$var parameter 32 3 LEARNING_RATE $end
$var parameter 32 4 NUM_ITERATIONS $end
$var parameter 3 5 STATE_CALL_FUNC $end
$var parameter 3 6 STATE_CMP_STR $end
$var parameter 3 7 STATE_DONE $end
$var parameter 3 8 STATE_IDLE $end
$var parameter 3 9 STATE_INIT $end
$var reg 3 : current_state [2:0] $end
$var reg 1 # done_op $end
$var reg 1 ; func_reset $end
$var reg 6 < iter_count [5:0] $end
$var reg 3 = next_state [2:0] $end
$var reg 1 > start_func $end
$var reg 32 ? x_at_min [31:0] $end
$var reg 32 @ x_at_min_inter [31:0] $end
$var reg 32 A x_in [31:0] $end
$var reg 64 B y_min [63:0] $end
$var reg 64 C y_min_inter [63:0] $end
$scope module compare $end
$var wire 64 D a_in [63:0] $end
$var wire 64 E b_in [63:0] $end
$var wire 1 2 comp_result $end
$upscope $end
$scope module inst $end
$var wire 1 F all_funcs_done $end
$var wire 1 ( clk $end
$var wire 1 ; rst_n $end
$var wire 1 > start_func $end
$var wire 32 G x_in [31:0] $end
$var wire 64 H y_out2_func [63:0] $end
$var wire 64 I y_out1_func [63:0] $end
$var wire 32 J x_in_minus_2H [31:0] $end
$var wire 32 K x_diff [31:0] $end
$var wire 1 L underflow_mult $end
$var wire 1 M overflow_mult $end
$var wire 1 N overflow2 $end
$var wire 1 O overflow1 $end
$var wire 64 P gradient_calc [63:0] $end
$var wire 1 Q func2_done $end
$var wire 1 R func1_done $end
$var parameter 32 S GRADatZERO $end
$var parameter 32 T LEARNING_RATE $end
$var parameter 32 U TWO_H $end
$var reg 1 1 func_done $end
$var reg 64 V gradient [63:0] $end
$var reg 1 W overflow $end
$var reg 64 X val1_reg [63:0] $end
$var reg 64 Y val2_reg [63:0] $end
$var reg 64 Z value [63:0] $end
$var reg 32 [ x_diff_out [31:0] $end
$scope module func_val $end
$var wire 1 ( clk $end
$var wire 1 \ overflow_x_square $end
$var wire 1 ; rst_n $end
$var wire 1 > start_func $end
$var wire 32 ] x_in [31:0] $end
$var wire 64 ^ x_square [63:0] $end
$var parameter 64 _ MINUS_ONE $end
$var parameter 2 ` STATE_COMPUTE $end
$var parameter 2 a STATE_DONE $end
$var parameter 2 b STATE_IDLE $end
$var parameter 2 c STATE_INIT $end
$var reg 1 d compute_done $end
$var reg 64 e compute_result [63:0] $end
$var reg 2 f curr_state [1:0] $end
$var reg 64 g four_x [63:0] $end
$var reg 1 R func_done $end
$var reg 2 h next_state [1:0] $end
$var reg 1 O overflow $end
$var reg 32 i x_val [31:0] $end
$var reg 64 j y_out [63:0] $end
$scope module inst $end
$var wire 32 k a_in [31:0] $end
$var wire 32 l b_in [31:0] $end
$var wire 1 \ overflow $end
$var wire 64 m product_full [63:0] $end
$var wire 64 n p_out [63:0] $end
$var parameter 32 o FRACT_BITS $end
$upscope $end
$upscope $end
$scope module inst2 $end
$var wire 1 ( clk $end
$var wire 1 p overflow_x_square $end
$var wire 1 ; rst_n $end
$var wire 1 > start_func $end
$var wire 32 q x_in [31:0] $end
$var wire 64 r x_square [63:0] $end
$var parameter 64 s MINUS_ONE $end
$var parameter 2 t STATE_COMPUTE $end
$var parameter 2 u STATE_DONE $end
$var parameter 2 v STATE_IDLE $end
$var parameter 2 w STATE_INIT $end
$var reg 1 x compute_done $end
$var reg 64 y compute_result [63:0] $end
$var reg 2 z curr_state [1:0] $end
$var reg 64 { four_x [63:0] $end
$var reg 1 Q func_done $end
$var reg 2 | next_state [1:0] $end
$var reg 1 N overflow $end
$var reg 32 } x_val [31:0] $end
$var reg 64 ~ y_out [63:0] $end
$scope module inst $end
$var wire 32 !" a_in [31:0] $end
$var wire 32 "" b_in [31:0] $end
$var wire 1 p overflow $end
$var wire 64 #" product_full [63:0] $end
$var wire 64 $" p_out [63:0] $end
$var parameter 32 %" FRACT_BITS $end
$upscope $end
$upscope $end
$scope module inst_diff $end
$var wire 32 &" a_in [31:0] $end
$var wire 32 '" b_in [31:0] $end
$var wire 1 M overflow $end
$var wire 1 L underflow_q $end
$var wire 64 (" product_full [63:0] $end
$var wire 32 )" p_out [31:0] $end
$var wire 24 *" msb_of_product_full [23:0] $end
$var wire 1 +" expected_sign $end
$var parameter 32 ," FRACT_BITS $end
$upscope $end
$upscope $end
$upscope $end
$scope begin $unm_blk_46 $end
$var integer 32 -" i [31:0] $end
$upscope $end
$upscope $end
$enddefinitions $end
$comment Show the parameter values. $end
$dumpall
b1000 ,"
b1000 %"
b1 w
b0 v
b11 u
b10 t
b1111111111111111111111111111111111111111111111111111111100000000 s
b1000 o
b1 c
b0 b
b11 a
b10 `
b1111111111111111111111111111111111111111111111111111111100000000 _
b10 U
b11010 T
b10000000000 S
b1 9
b0 8
b100 7
b11 6
b10 5
b110010 4
b11010 3
b110010 '
b1 &
b11010 %
b100000000 $
$end
#0
$dumpvars
bx -"
0+"
b0 *"
b0 )"
b0 ("
b0 '"
b11010 &"
b0 $"
b0 #"
b0 ""
b0 !"
b1111111111111111111111111111111111111111111111111111111100000000 ~
b0 }
b0 |
b0 {
b0 z
b1111111111111111111111111111111111111111111111111111111100000000 y
0x
b0 r
b11111111111111111111111111111110 q
0p
b0 n
b0 m
b0 l
b0 k
b1111111111111111111111111111111111111111111111111111111100000000 j
b0 i
b0 h
b0 g
b0 f
b1111111111111111111111111111111111111111111111111111111100000000 e
0d
b0 ^
b0 ]
0\
b0 [
b0 Z
b0 Y
b0 X
0W
b0 V
0R
0Q
b0 P
0O
0N
0M
0L
b0 K
b11111111111111111111111111111110 J
b1111111111111111111111111111111111111111111111111111111100000000 I
b1111111111111111111111111111111111111111111111111111111100000000 H
b0 G
0F
b111111111111111111111111111111111111111111111111111111111111111 E
b111111111111111111111111111111111111111111111111111111111111111 D
b111111111111111111111111111111111111111111111111111111111111111 C
b111111111111111111111111111111111111111111111111111111111111111 B
b0 A
b0 @
b0 ?
x>
b0 =
b0 <
0;
b0 :
02
01
b0 0
b0 /
b0 .
b0 -
b11010000000000000000000000000000 ,
0+
0*
b0 )
0(
0#
b0 "
b111111111111111111111111111111111111111111111111111111111111111 !
$end
#5000
1(
#10000
0(
#15000
1(
#20000
b1 =
0(
1+
1*
b11010000000000000000000000000000 )
b11010000000000000000000000000000 -
#25000
b10 =
1;
b1 :
1(
#30000
0(
#35000
b1 h
b1 |
1>
b11010000000000000000000000000000 @
b11010000000000000000000000000000 "
b11010000000000000000000000000000 ?
b11010000000000000000000000000000 /
b11001111111111111111111111111110 J
b11001111111111111111111111111110 q
b11010000000000000000000000000000 A
b11010000000000000000000000000000 G
b11010000000000000000000000000000 ]
b10 :
1(
#40000
0(
#45000
b10 |
b10 h
b1 z
b1 f
1(
#50000
0(
#55000
b1001000000000000000000000000000000000000000000000000 ^
b1001000000000000000000000000000000000000000000000000 n
b1000111111111111111100111111111111111111111100000000 e
b1111111111111111111111111111111101000000000000000000000000000000 g
b1001000000000000000000000000110000000000000000000000 r
b1001000000000000000000000000110000000000000000000000 $"
b1000111111111111111101000000101111111111111011111000 y
b1111111111111111111111111111111100111111111111111111111111111000 {
b0 I
b0 j
b100100000000000000000000000000000000000000000000000000000000 m
b11010000000000000000000000000000 i
b11010000000000000000000000000000 k
b11010000000000000000000000000000 l
b10 f
b0 H
b0 ~
b100100000000000000000000000011000000000000000000000000000100 #"
b11001111111111111111111111111110 }
b11001111111111111111111111111110 !"
b11001111111111111111111111111110 ""
b10 z
1(
#60000
0(
#65000
b11 |
b11 h
1x
b1000111111111111111101000000101111111111111011111000 H
b1000111111111111111101000000101111111111111011111000 ~
1d
b1000111111111111111100111111111111111111111100000000 I
b1000111111111111111100111111111111111111111100000000 j
1(
#70000
0(
#75000
b11 f
b11 z
1(
#80000
0(
#85000
1F
1Q
1R
1(
#90000
0(
#95000
1+"
b11110110010000000000000001101000 K
b11110110010000000000000001101000 )"
0M
b111111111111111111111111 *"
b1111111111111111111111111111011001000000000000000110100000000000 ("
b10100000000000000000010000000000 '"
b1111111111111111111111111111111110100000000000000000010000000000 P
b11 =
b1000111111111111111101000000101111111111111011111000 Y
b1000111111111111111100111111111111111111111100000000 X
11
b1000111111111111111100111111111111111111111100000000 .
b1000111111111111111100111111111111111111111100000000 Z
1(
#100000
0(
#105000
b0 h
b0 |
b10 =
b11011001101111111111111110011000 /
b11110110010000000000000001101000 0
b11110110010000000000000001101000 [
b1111111111111111111111111111111110100000000000000000010000000000 V
0>
12
b1000111111111111111100111111111111111111111100000000 C
b1000111111111111111100111111111111111111111100000000 D
b1 <
b11 :
1(
#110000
0(
#115000
b1 h
b1 |
b11 =
b0 f
b0 z
1>
b11100011011111111111111100110000 /
b11011001101111111111111110010110 J
b11011001101111111111111110010110 q
b11011001101111111111111110011000 A
b11011001101111111111111110011000 G
b11011001101111111111111110011000 ]
02
b1000111111111111111100111111111111111111111100000000 !
b1000111111111111111100111111111111111111111100000000 B
b1000111111111111111100111111111111111111111100000000 E
b10 :
1(
#120000
0(
#125000
0F
b10 h
b10 |
b10 =
0x
0Q
b1 z
0d
0R
b1 f
0>
b11011001101111111111111110011000 @
b10 <
b11 :
1(
#130000
0(
#135000
b101101101110001000000011111000101000000000000101010 ^
b101101101110001000000011111000101000000000000101010 n
b101101101110001000000011111101011010000000000101011 r
b101101101110001000000011111101011010000000000101011 $"
b101101101110000111110000110000100111111110110001010 e
b1111111111111111111111111111111101100110111111111111111001100000 g
b101101101110000111110000110101011001111110110000011 y
b1111111111111111111111111111111101100110111111111111111001011000 {
b0 I
b0 j
b10110110111000100000001111100010100000000000010101001000000 m
b11011001101111111111111110011000 i
b11011001101111111111111110011000 k
b11011001101111111111111110011000 l
b10 f
b0 H
b0 ~
b10110110111000100000001111110101101000000000010101111100100 #"
b11011001101111111111111110010110 }
b11011001101111111111111110010110 !"
b11011001101111111111111110010110 ""
b10 z
01
1>
b11101101001111111111111011001000 /
b11100011011111111111111100101110 J
b11100011011111111111111100101110 q
b11100011011111111111111100110000 A
b11100011011111111111111100110000 G
b11100011011111111111111100110000 ]
b10 :
1(
#140000
0(
#145000
b11 |
b11 h
1x
b101101101110000111110000110101011001111110110000011 H
b101101101110000111110000110101011001111110110000011 ~
1d
b101101101110000111110000110000100111111110110001010 I
b101101101110000111110000110000100111111110110001010 j
1(
#150000
0(
#155000
b11 f
b11 z
1(
#160000
0(
#165000
1F
1Q
1R
1(
#170000
0(
#175000
b11111000001110110000000001011011 K
b11111000001110110000000001011011 )"
b1111111111111111111111111111100000111011000000000101101100000000 ("
b10110011100000000000001110000000 '"
b1111111111111111111111111111111110110011100000000000001110000000 P
b11 =
b101101101110000111110000110101011001111110110000011 Y
b101101101110000111110000110000100111111110110001010 X
11
b101101101110000111110000110000100111111110110001010 .
b101101101110000111110000110000100111111110110001010 Z
1(
#180000
0(
#185000
b0 h
b0 |
b10 =
b11101011010001001111111011010101 /
b11111000001110110000000001011011 0
b11111000001110110000000001011011 [
b1111111111111111111111111111111110110011100000000000001110000000 V
0>
b11100011011111111111111100110000 @
12
b101101101110000111110000110000100111111110110001010 C
b101101101110000111110000110000100111111110110001010 D
b11 <
b11 :
1(
#190000
0(
#195000
b1 h
b1 |
b11 =
b0 f
b0 z
1>
b11110011000010011111111001111010 /
b11101011010001001111111011010011 J
b11101011010001001111111011010011 q
b11101011010001001111111011010101 A
b11101011010001001111111011010101 G
b11101011010001001111111011010101 ]
b11100011011111111111111100110000 "
b11100011011111111111111100110000 ?
02
b101101101110000111110000110000100111111110110001010 !
b101101101110000111110000110000100111111110110001010 B
b101101101110000111110000110000100111111110110001010 E
b10 :
1(
#200000
0(
#205000
0F
b10 h
b10 |
b10 =
0x
0Q
b1 z
0d
0R
b1 f
0>
b11101011010001001111111011010101 @
b100 <
b11 :
1(
#210000
0(
#215000
b1101011011100000011001001011011001101001101011101 ^
b1101011011100000011001001011011001101001101011101 n
b1101011011100000011001001101111111011111101100001 r
b1101011011100000011001001101111111011111101100001 $"
b1101011011100000001110110100000001100110110110001 e
b1111111111111111111111111111111110101101000100111111101101010100 g
b1101011011100000001110110110100111011100110101101 y
b1111111111111111111111111111111110101101000100111111101101001100 {
b0 I
b0 j
b110101101110000001100100101101100110100110101110100111001 m
b11101011010001001111111011010101 i
b11101011010001001111111011010101 k
b11101011010001001111111011010101 l
b10 f
b0 H
b0 ~
b110101101110000001100100110111111101111110110000111101001 #"
b11101011010001001111111011010011 }
b11101011010001001111111011010011 !"
b11101011010001001111111011010011 ""
b10 z
01
1>
b11111010110011101111111000011111 /
b11110011000010011111111001111000 J
b11110011000010011111111001111000 q
b11110011000010011111111001111010 A
b11110011000010011111111001111010 G
b11110011000010011111111001111010 ]
b10 :
1(
#220000
0(
#225000
b11 |
b11 h
1x
b1101011011100000001110110110100111011100110101101 H
b1101011011100000001110110110100111011100110101101 ~
1d
b1101011011100000001110110100000001100110110110001 I
b1101011011100000001110110100000001100110110110001 j
1(
#230000
0(
#235000
b11 f
b11 z
1(
#240000
0(
#245000
1F
1Q
1R
1(
#250000
0(
#255000
b11111011110010100000010000110100 K
b11111011110010100000010000110100 )"
b1111111111111111111111111111101111001010000001000011010000000000 ("
b11010110100010100000001000000000 '"
b1111111111111111111111111111111111010110100010100000001000000000 P
b11 =
b1101011011100000001110110110100111011100110101101 Y
b1101011011100000001110110100000001100110110110001 X
11
b1101011011100000001110110100000001100110110110001 .
b1101011011100000001110110100000001100110110110001 Z
1(
#260000
0(
#265000
b0 h
b0 |
b10 =
b11110111001111111111101001000110 /
b11111011110010100000010000110100 0
b11111011110010100000010000110100 [
b1111111111111111111111111111111111010110100010100000001000000000 V
0>
b11110011000010011111111001111010 @
12
b1101011011100000001110110100000001100110110110001 C
b1101011011100000001110110100000001100110110110001 D
b101 <
b11 :
1(
#270000
0(
