Internship_IITH/general_linear_regressor/fixed_64_comp.v
module fixed_64_comp(
    input signed [63:0] a_in,  // signed Q56.8
    input signed [63:0] b_in,  // signed Q56.8
    output logic comp_result   // 1 if a_in < b_in, else 0
);
    assign comp_result = (a_in < b_in) ;
endmodule

Internship_IITH/4D_gradient_descent_V1.0/fixed_32_mult.v
module fixed_32_mult(
    input signed [31:0] a_in,    // Input operand A (Q24.8 format)
    input signed [31:0] b_in,    // Input operand B (Q24.8 format)
    output signed [31:0] p_out,  // Product P (Q24.8 format)
    output logic overflow,        // Flag for overflow detection
    output logic underflow_q       // Flag for underflow detection (going below minimum negative)
);

    localparam integer FRACT_BITS = 8;
    wire signed [63:0] product_full;

    assign product_full = a_in * b_in;
    assign p_out = product_full >>> FRACT_BITS;

    wire expected_sign = p_out[31]; // The sign bit of the result
    wire [23:0] msb_of_product_full = product_full[63:40]; // 63 - 40 + 1 = 24 bits
    assign overflow = (expected_sign == 1'b0) && (|msb_of_product_full); // Positive overflow if any MSB is 1
    assign underflow_q = (expected_sign == 1'b1) && (~(&msb_of_product_full)); // Negative overflow/underflow if any MSB is 0


endmodule

Internship_IITH/general_linear_regressor_V1.0/fixed_64_mult.v
module fixed_64_mult(
    input signed [31:0] a_in,    // Input operand A (Q24.8 format)
    input signed [31:0] b_in,    // Input operand B (Q24.8 format)
    output signed [63:0] p_out,  // Product P (Q55.8 format)
    output logic overflow        // Flag for overflow detection
);

    localparam integer FRACT_BITS = 8;
    wire signed [63:0] product_full;

    assign product_full = a_in * b_in;
    assign p_out = product_full >>> FRACT_BITS;

    assign overflow = 1'b0;

endmodule

Internship_IITH/func_grad_val_diff_test/func.v
module func(
    input clk,
    input rst_n,
    input start_func,
    input signed [31:0] x_in,
    output reg signed [63:0] y_out,
    output reg func_done,
    output reg overflow
);

// The default Function is assumed to be X^2 + 4x - 1

localparam STATE_IDLE       = 2'b00;
localparam STATE_INIT       = 2'b01;
localparam STATE_COMPUTE    = 2'b10;
localparam STATE_DONE       = 2'b11;
localparam MINUS_ONE        = 64'hFFFFFFFFFFFFFF00;

reg [1:0] curr_state;
reg [1:0] next_state;
reg compute_done ;
reg signed [31:0] x_val;
reg signed [63:0] four_x;
reg signed [63:0] compute_result;

wire signed [63:0] x_square;
wire overflow_x_square;

always @(*) begin
    next_state = curr_state;
    case (curr_state)
        STATE_IDLE      : begin if (start_func)  next_state = STATE_INIT; end
        STATE_INIT      : begin next_state = STATE_COMPUTE; end
        STATE_COMPUTE   : begin if (compute_done) next_state = STATE_DONE; end
        STATE_DONE      : begin if (!start_func) next_state = STATE_IDLE; end
        default         : begin next_state = STATE_IDLE; end
    endcase
    four_x = x_val << 2; // SIGN EXTENED
    compute_result = x_square + four_x + MINUS_ONE;  // Q56.8 format
end

always_ff @(posedge clk, negedge rst_n) begin 
    if (!rst_n) begin
        curr_state  <= STATE_IDLE;
        func_done   <= 1'b0;
        x_val       <= 32'd0;   
        y_out       <= 64'd0;
        compute_done <= 1'b0;
        overflow    <= 1'b0;
    end else begin 
        curr_state <= next_state;
        case (curr_state)
            STATE_IDLE : begin
                // DO NOTHING
                func_done <= 1'b0;
                compute_done <= 1'b0;   
            end  
            STATE_INIT : begin
                x_val <= x_in;
                y_out <= 64'd0;
                func_done <= 1'b0;
                compute_done <= 1'b0;   
            end
            STATE_COMPUTE: begin 
                y_out <= compute_result;
                compute_done <= 1'b1;
                overflow <= overflow_x_square;
            end
            STATE_DONE : begin 
                func_done <= 1'b1;
            end
        endcase
    end 
end

fixed_64_mult inst (   // calculate x^2
    .a_in(x_val),
    .b_in(x_val),
    .p_out(x_square),
    .overflow(overflow_x_square)
);

endmodule

Internship_IITH/general_linear_regressor/func_grad_val_diff.v
module func_grad_val_diff(
    input clk,
    input rst_n,
    input start_func,
    input signed [31:0] x_in,
    output reg signed [63:0] gradient,
    output reg signed [63:0] value,
    output reg signed [31:0] x_diff_out,
    output reg func_done,
    output reg overflow
);
    localparam TWO_H = 32'h00000002;            // Q24.8 2H = 7.8125e-3 in decimal 
    localparam LEARNING_RATE = 32'h00000080;    // Q24.8 0.5 in decimal
    wire signed [63:0]val1;                     // Q56.8
    wire signed [63:0]val2;                     // Q56.8
    wire signed [31:0] x_in_minus_2H;           // Q24.8
    wire signed [63:0] gradient_intermediate;   // Q56.8 
    wire signed [31:0] x_diff;                  // Q24.8
    wire func1_done;
    wire func2_done;
    wire mult_done;
    wire overflow1;
    wire overflow2;
    wire overflow_mult;
    wire underflow_mult;

    assign x_in_minus_2H = x_in - TWO_H;
    assign gradient_intermediate = (val1 - val2) << 7;

    func func_val(
        .clk(clk),
        .rst_n(rst_n),
        .start_func(start_func),
        .x_in(x_in ),               // Q24.8
        .y_out(val1),               // Q56.8
        .func_done(func1_done),
        .overflow(overflow1)
    );

    func inst2(
        .clk(clk),
        .rst_n(rst_n),
        .start_func(start_func),
        .x_in(x_in_minus_2H),       // Q24.8
        .y_out(val2),               // Q56.8 
        .func_done(func2_done),
        .overflow(overflow2)
    );

    fixed_32_mult inst_diff(
        .a_in(LEARNING_RATE),               // Q24.8
        .b_in(gradient_intermediate[31:0]), // Q24.8
        .p_out(x_diff),                     // Q56.8
        .overflow(overflow_mult),
        .underflow_q(underflow_mult)
    );

    wire all_funcs_done;
    assign all_funcs_done = func1_done & func2_done ;
    always @(posedge clk, negedge rst_n) begin
        if (!rst_n) begin
            gradient    <= 64'd0;
            value       <= 64'd0;
            func_done   <= 1'b0;
            overflow    <= 1'b0;
        end else begin
            if (all_funcs_done) begin
                gradient <= gradient_intermediate;
                value <= val1;
                func_done <= 1'b1;
                overflow <= overflow1 | overflow2 | overflow_mult;
                if (overflow_mult) begin 
                    x_diff_out <= 32'h7FFFFFFF; // capped at Highest positive 32 bit signed value
                end else if (underflow_mult) begin
                    x_diff_out <= 32'h80000000; // capped at minimum negetive 32 bit signed value 
                end else begin
                    x_diff_out <= x_diff;
                end
            end else begin
                func_done <= 1'b0;
            end
        end
    end
endmodule

Internship_IITH/general_linear_regressor/Top.v
// TODO:
//      {DONE} Finish func_grad_val_diff.v using |||FSM||| (Ditched FSM)
//      {DONE} Finish Top.v implementing func_grad_val_diff
//      Write Testbech for Top.v
// TODO AFTER:
//      Write synthesis in vivado 



module Top #(
    NUM_ITERATIONS = 10,
    LEARNING_RATE = 32'h00000080
) (
    input clk,
    input rst_n,
    input start_op,
    input signed [31:0] x_init,
    output reg signed [31:0] x_at_min,
    output reg signed [63:0] y_min,
    output reg done_op
);

    // INTERNAL VARIABLE REG
    reg signed [31:0] x_in;     // Q24.8 format
    reg [$clog2(NUM_ITERATIONS + 1)-1 : 0] iter_count;
    reg func_reset;     
    reg start_func;      
    reg signed [31:0] x_at_min_inter;
    reg signed [63:0] y_min_inter;

    // REGISTERS TO HOLD STATE
    reg [2:0] current_state;
    reg [2:0] next_state;

    // INTERNAL WIREs
    wire func_done;
    wire comp_result;
    wire [31:0] x_next_val;
    wire [63:0] y_out;
    wire [31:0] x_diff_out;

    // STATE DEFINITION
    localparam STATE_IDLE = 3'b000;
    localparam STATE_INIT = 3'b001;
    localparam STATE_CALL_FUNC = 3'b010; 
    localparam STATE_CMP_STR = 3'b011; // COMPARE AND STORE
    localparam STATE_DONE = 3'b100;

    assign x_next_val = (x_in - x_diff_out);
        
    always @(*) begin 
        next_state = current_state;
        case (current_state)
            STATE_IDLE : begin 
                if (start_op) next_state = STATE_INIT;
            end
            STATE_INIT : begin 
                next_state = STATE_CALL_FUNC;
            end
            STATE_CALL_FUNC : begin 
                if (func_done) next_state = STATE_CMP_STR;
            end
            STATE_CMP_STR : begin
                if (iter_count == NUM_ITERATIONS) begin
                    next_state = STATE_DONE;
                end else begin 
                    next_state = STATE_CALL_FUNC;
                end
            end
            STATE_DONE : begin 
                if (!start_op) next_state = STATE_IDLE;
            end
        endcase
    end

    //           STATE_IDLE---------( start_op == 1)--------->STATE_INIT
    //               ʌ                                             |    
    //               |           MOVE TO IDLE WHENEVER             |
    //               |             start_op is UNSET               |
    //       (start_op == 0 )                                STATE_CALL_FUNC<-----\
    //               ʌ                                             V              |            
    //               |                                             |              |
    //           STATE_DONE<---(iter_count == NUM_ITERATIONS)<--STATE_CMP_STR     |
    //                                                             |              ʌ
    //                                                             L > (iter_count < NUM_ITERATIONS)



    always @(posedge clk, negedge rst_n) begin
        if (!rst_n) begin 
            current_state <= STATE_IDLE;
            x_in <= 32'd0;
            x_at_min <= 32'd0;
            y_min <= 64'd0;
            y_min_inter <= 64'd0;        // Add this
            x_at_min_inter <= 32'd0;     // Add this
            iter_count <= 0;
            done_op <= 1'b0;
        end else begin
            current_state <= next_state;
            case (current_state)
                STATE_IDLE : begin 
                    // DO NOTHING
                    done_op <= 1'b0;
                end
                STATE_INIT : begin 
                    x_in <= x_init;
                    y_min <= 64'h7FFFFFFFFFFFFFFF; // Initial y_min set to arbitrary high val
                    x_at_min <= x_init;
                    y_min_inter <= 64'h7FFFFFFFFFFFFFFF;  // Add this
                    x_at_min_inter <= x_init;             // Add this
                    iter_count <= 0;
                    start_func <= 1'b1;
                end
                STATE_CALL_FUNC : begin 
                    if (func_done) begin
                        iter_count <= iter_count +1;
                        y_min_inter <= y_out;
                        x_at_min_inter <= x_in;
                        start_func <= 1'b0;
                    end
                end
                STATE_CMP_STR : begin
                    if (comp_result) begin
                        y_min <= y_min_inter;
                        x_at_min <= x_at_min_inter;
                    end
                    x_in <= x_next_val;
                    start_func <= 1'b1;
                end
                STATE_DONE : begin 
                    done_op <= 1'b1;
                end
            endcase
        end
    end

    // MODULE CALLS

    // Ouputs the Gradient, value & Step size of 'function under test' at x_in 
    func_grad_val_diff inst (
        .clk(clk),
        .rst_n(rst_n),
        .start_func(start_func),// input level Flag signaling Start of function
        .x_in(x_in),            // X input of the function
        .gradient(),            // Gradient Output of the function at X
        .value(y_out),          // value of func at X
        .x_diff_out(x_diff_out),// calculated Step size to next X 
        .func_done(func_done),  // Flag so signaling func completion
        .overflow()             // Overflow Flag
    );
    fixed_64_comp compare(
        .a_in(y_min_inter),
        .b_in(y_min),
        .comp_result(comp_result)   // out put 1 if y_min_inter < y_min
    );

    
endmodule

Internship_IITH/general_linear_regressor/tb_Top.v
`timescale 1ns / 1ps

module tb_Top;
    // Parameters for the Top module (can be overridden here for testing)
    parameter NUM_ITERATIONS = 10;
    parameter LEARNING_RATE = 32'h00000020; // Learning Rate of 0.125 (Q24.8)
    parameter INCREMENT = 32'h00000100;     // 1.0 Increment between test cases (Q24.8)
    parameter LOOP_COUNT = 10;

    // Inputs to the Top module
    reg clk;
    reg rst_n;
    reg start_op;
    reg signed [31:0] initial_x_in;
    reg signed [31:0] test_x_val;

    // Outputs from the Top module
    wire signed [31:0] x_at_min;
    wire signed [63:0] y_min;
    wire done_op;

    // Instantiate the Top module
    Top #(
        .NUM_ITERATIONS(NUM_ITERATIONS),
        .LEARNING_RATE(LEARNING_RATE)
    ) uut_top (
        .clk(clk),
        .rst_n(rst_n),
        .start_op(start_op),    
        .x_init(initial_x_in),
        .x_at_min(x_at_min),
        .y_min(y_min),
        .done_op(done_op)
    );

    // Clock Generation
    initial begin
        clk = 0;
        forever #5 clk = ~clk; // 10ns period (100 MHz)
    end

    // Test sequence
    initial begin
        integer i;
        // For waveform dumping (optional)
        $dumpfile("tb_Top.vcd");
        $dumpvars(0, tb_Top);

        // Initialize inputs
        rst_n = 0; // Assert reset
        start_op = 0;
        initial_x_in = 32'b0;
        test_x_val = 32'h00000000;  // 0.0 in decimal

        $display("---------------------------------------------------------");
        $display("Starting Testbench for Fixed-Point Gradient Descent");
        $display("Parameters: NUM_ITERATIONS = %0d, LEARNING_RATE = %f",
            NUM_ITERATIONS, $itor(LEARNING_RATE) / 256.0);
        $display("---------------------------------------------------------");
        #20 rst_n = 1; // Deassert reset        

        for(i = 0; i < LOOP_COUNT; i = i + 1 ) begin
            initial_x_in = test_x_val; // Q24.8 (2's complement)
            start_op = 1;
            // #20;

            wait(done_op == 1'b1);
            $display("\n--- Test Case %0d: Initial x = %f (Q24.8) ---", i, $itor(test_x_val) / 256.0);
            $display("Initial X: %f", $itor(test_x_val) / 256.0);
            $display("Final X at Min: %f (0x%H)", $itor(x_at_min) / 256.0, x_at_min);
            $display("Min Y Value: %f (0x%H)", $itor(y_min) / 256.0, y_min);
            // Reset for next test
            start_op = 0;
            test_x_val = test_x_val + INCREMENT; // Increment set default to 1.0
            wait(done_op == 1'b0);
            // #10
        end      
        $finish; // End simulation
    end
endmodule

Internship_IITH/general_linear_regressor/tb_Top.vcd
$date
	Fri Jun 06 14:51:43 2025
$end
$version
	Icarus Verilog
$end
$timescale
	1ps
$end
$scope module tb_Top $end
$var wire 64 ! y_min [63:0] $end
$var wire 32 " x_at_min [31:0] $end
$var wire 1 # done_op $end
$var parameter 32 $ INCREMENT $end
$var parameter 32 % LEARNING_RATE $end
$var parameter 32 & LOOP_COUNT $end
$var parameter 32 ' NUM_ITERATIONS $end
$var reg 1 ( clk $end
$var reg 32 ) initial_x_in [31:0] $end
$var reg 1 * rst_n $end
$var reg 1 + start_op $end
$var reg 32 , test_x_val [31:0] $end
$scope module uut_top $end
$var wire 1 ( clk $end
$var wire 1 * rst_n $end
$var wire 1 + start_op $end
$var wire 32 - x_init [31:0] $end
$var wire 64 . y_out [63:0] $end
$var wire 32 / x_next_val [31:0] $end
$var wire 32 0 x_diff_out [31:0] $end
$var wire 1 1 func_done $end
$var wire 1 2 comp_result $end
$var parameter 32 3 LEARNING_RATE $end
$var parameter 32 4 NUM_ITERATIONS $end
$var parameter 3 5 STATE_CALL_FUNC $end
$var parameter 3 6 STATE_CMP_STR $end
$var parameter 3 7 STATE_DONE $end
$var parameter 3 8 STATE_IDLE $end
$var parameter 3 9 STATE_INIT $end
$var reg 3 : current_state [2:0] $end
$var reg 1 # done_op $end
$var reg 5 ; iter_count [4:0] $end
$var reg 3 < next_state [2:0] $end
$var reg 1 = start_func $end
$var reg 32 > x_at_min [31:0] $end
$var reg 32 ? x_at_min_inter [31:0] $end
$var reg 32 @ x_in [31:0] $end
$var reg 64 A y_min [63:0] $end
$var reg 64 B y_min_inter [63:0] $end
$scope module compare $end
$var wire 64 C a_in [63:0] $end
$var wire 64 D b_in [63:0] $end
$var wire 1 2 comp_result $end
$upscope $end
$scope module inst $end
$var wire 1 E all_funcs_done $end
$var wire 1 ( clk $end
$var wire 1 * rst_n $end
$var wire 1 = start_func $end
$var wire 32 F x_in [31:0] $end
$var wire 32 G x_in_minus_2H [31:0] $end
$var wire 32 H x_diff [31:0] $end
$var wire 64 I val2 [63:0] $end
$var wire 64 J val1 [63:0] $end
$var wire 1 K underflow_mult $end
$var wire 1 L overflow_mult $end
$var wire 1 M overflow2 $end
$var wire 1 N overflow1 $end
$var wire 64 O gradient_intermediate [63:0] $end
$var wire 1 P func2_done $end
$var wire 1 Q func1_done $end
$var parameter 32 R LEARNING_RATE $end
$var parameter 32 S TWO_H $end
$var reg 1 1 func_done $end
$var reg 64 T gradient [63:0] $end
$var reg 1 U overflow $end
$var reg 64 V value [63:0] $end
$var reg 32 W x_diff_out [31:0] $end
$scope module func_val $end
$var wire 1 ( clk $end
$var wire 1 X overflow_x_square $end
$var wire 1 * rst_n $end
$var wire 1 = start_func $end
$var wire 32 Y x_in [31:0] $end
$var wire 64 Z x_square [63:0] $end
$var parameter 64 [ MINUS_ONE $end
$var parameter 2 \ STATE_COMPUTE $end
$var parameter 2 ] STATE_DONE $end
$var parameter 2 ^ STATE_IDLE $end
$var parameter 2 _ STATE_INIT $end
$var reg 1 ` compute_done $end
$var reg 64 a compute_result [63:0] $end
$var reg 2 b curr_state [1:0] $end
$var reg 64 c four_x [63:0] $end
$var reg 1 Q func_done $end
$var reg 2 d next_state [1:0] $end
$var reg 1 N overflow $end
$var reg 32 e x_val [31:0] $end
$var reg 64 f y_out [63:0] $end
$scope module inst $end
$var wire 32 g a_in [31:0] $end
$var wire 32 h b_in [31:0] $end
$var wire 1 X overflow $end
$var wire 64 i product_full [63:0] $end
$var wire 64 j p_out [63:0] $end
$var parameter 32 k FRACT_BITS $end
$upscope $end
$upscope $end
$scope module inst2 $end
$var wire 1 ( clk $end
$var wire 1 l overflow_x_square $end
$var wire 1 * rst_n $end
$var wire 1 = start_func $end
$var wire 32 m x_in [31:0] $end
$var wire 64 n x_square [63:0] $end
$var parameter 64 o MINUS_ONE $end
$var parameter 2 p STATE_COMPUTE $end
$var parameter 2 q STATE_DONE $end
$var parameter 2 r STATE_IDLE $end
$var parameter 2 s STATE_INIT $end
$var reg 1 t compute_done $end
$var reg 64 u compute_result [63:0] $end
$var reg 2 v curr_state [1:0] $end
$var reg 64 w four_x [63:0] $end
$var reg 1 P func_done $end
$var reg 2 x next_state [1:0] $end
$var reg 1 M overflow $end
$var reg 32 y x_val [31:0] $end
$var reg 64 z y_out [63:0] $end
$scope module inst $end
$var wire 32 { a_in [31:0] $end
$var wire 32 | b_in [31:0] $end
$var wire 1 l overflow $end
$var wire 64 } product_full [63:0] $end
$var wire 64 ~ p_out [63:0] $end
$var parameter 32 !" FRACT_BITS $end
$upscope $end
$upscope $end
$scope module inst_diff $end
$var wire 32 "" a_in [31:0] $end
$var wire 32 #" b_in [31:0] $end
$var wire 1 L overflow $end
$var wire 1 K underflow_q $end
$var wire 64 $" product_full [63:0] $end
$var wire 32 %" p_out [31:0] $end
$var wire 24 &" msb_of_product_full [23:0] $end
$var wire 1 '" expected_sign $end
$var parameter 32 (" FRACT_BITS $end
$upscope $end
$upscope $end
$upscope $end
$scope begin $unm_blk_41 $end
$var integer 32 )" i [31:0] $end
$upscope $end
$upscope $end
$enddefinitions $end
$comment Show the parameter values. $end
$dumpall
b1000 ("
b1000 !"
b1 s
b0 r
b11 q
b10 p
b1111111111111111111111111111111111111111111111111111111100000000 o
b1000 k
b1 _
b0 ^
b11 ]
b10 \
b1111111111111111111111111111111111111111111111111111111100000000 [
b10 S
b10000000 R
b1 9
b0 8
b100 7
b11 6
b10 5
b11001 4
b100000 3
b11001 '
b1010 &
b100000 %
b100000000 $
$end
#0
$dumpvars
bx )"
0'"
b0 &"
b0 %"
b0 $"
b0 #"
b10000000 ""
b0 ~
b0 }
b0 |
b0 {
b0 z
b0 y
b0 x
b0 w
b0 v
b1111111111111111111111111111111111111111111111111111111100000000 u
0t
b0 n
b11111111111111111111111111111110 m
0l
b0 j
b0 i
b0 h
b0 g
b0 f
b0 e
b0 d
b0 c
b0 b
b1111111111111111111111111111111111111111111111111111111100000000 a
0`
b0 Z
b0 Y
0X
bx W
b0 V
0U
b0 T
0Q
0P
b0 O
0N
0M
0L
0K
b0 J
b0 I
b0 H
b11111111111111111111111111111110 G
b0 F
0E
b0 D
b0 C
b0 B
b0 A
b0 @
b0 ?
b0 >
x=
b0 <
b0 ;
b0 :
02
01
bx 0
bx /
b0 .
b0 -
b0 ,
0+
0*
b0 )
0(
0#
b0 "
b0 !
$end
#5000
1(
#10000
0(
#15000
1(
#20000
b1 <
0(
1+
b0 )"
1*
#25000
b10 <
b1 :
1(
#30000
0(
#35000
b1 d
b1 x
1=
b111111111111111111111111111111111111111111111111111111111111111 B
b111111111111111111111111111111111111111111111111111111111111111 C
02
b111111111111111111111111111111111111111111111111111111111111111 !
b111111111111111111111111111111111111111111111111111111111111111 A
b111111111111111111111111111111111111111111111111111111111111111 D
b10 :
1(
#40000
0(
#45000
b10 x
b10 d
b1 v
b1 b
1(
#50000
0(
#55000
b1111111111111111111111111111111111111111111111111111111011111000 u
b1111111111111111111111111111111111111111111111111111111111111000 w
b10 b
b100 }
b11111111111111111111111111111110 y
b11111111111111111111111111111110 {
b11111111111111111111111111111110 |
b10 v
1(
#60000
0(
#65000
b1000000000 H
b1000000000 %"
b100000000000000000 $"
b10000000000 #"
b11 x
b11 d
b10000000000 O
1t
b1111111111111111111111111111111111111111111111111111111011111000 I
b1111111111111111111111111111111111111111111111111111111011111000 z
1`
b1111111111111111111111111111111111111111111111111111111100000000 J
b1111111111111111111111111111111111111111111111111111111100000000 f
1(
#70000
0(
#75000
b11 b
b11 v
1(
#80000
0(
#85000
1E
1P
1Q
1(
#90000
0(
#95000
b11 <
b11111111111111111111111000000000 /
b1000000000 0
b1000000000 W
11
b1111111111111111111111111111111111111111111111111111111100000000 .
b1111111111111111111111111111111111111111111111111111111100000000 V
b10000000000 T
1(
#100000
0(
#105000
b0 d
b0 x
b10 <
0=
12
b1111111111111111111111111111111111111111111111111111111100000000 B
b1111111111111111111111111111111111111111111111111111111100000000 C
b1 ;
b11 :
1(
#110000
0(
#115000
b1 d
b1 x
b11 <
b0 b
b0 v
1=
b11111111111111111111110000000000 /
b11111111111111111111110111111110 G
b11111111111111111111110111111110 m
b11111111111111111111111000000000 @
b11111111111111111111111000000000 F
b11111111111111111111111000000000 Y
02
b1111111111111111111111111111111111111111111111111111111100000000 !
b1111111111111111111111111111111111111111111111111111111100000000 A
b1111111111111111111111111111111111111111111111111111111100000000 D
b10 :
1(
#120000
0(
#125000
b10 <
b10 x
0E
b10 d
0=
b11111111111111111111111000000000 ?
b10 ;
b11 :
0t
0P
b1 v
0`
0Q
b1 b
1(
#130000
0(
#135000
b0 H
b0 %"
b0 $"
b0 #"
b10000000000 Z
b10000000000 j
b0 O
b10000001000 n
b10000001000 ~
b1111111111111111111111111111111111111111111111111111101100000000 a
b1111111111111111111111111111111111111111111111111111100000000000 c
b1111111111111111111111111111111111111111111111111111101100000000 u
b1111111111111111111111111111111111111111111111111111011111111000 w
b0 J
b0 f
b1000000000000000000 i
b11111111111111111111111000000000 e
b11111111111111111111111000000000 g
b11111111111111111111111000000000 h
b10 b
b0 I
b0 z
b1000000100000000100 }
b11111111111111111111110111111110 y
b11111111111111111111110111111110 {
b11111111111111111111110111111110 |
b10 v
01
1=
b11111111111111111111101000000000 /
b11111111111111111111101111111110 G
b11111111111111111111101111111110 m
b11111111111111111111110000000000 @
b11111111111111111111110000000000 F
b11111111111111111111110000000000 Y
b10 :
1(
#140000
0(
#145000
b11 x
b11 d
1t
b1111111111111111111111111111111111111111111111111111101100000000 I
b1111111111111111111111111111111111111111111111111111101100000000 z
1`
b1111111111111111111111111111111111111111111111111111101100000000 J
b1111111111111111111111111111111111111111111111111111101100000000 f
1(
#150000
0(
#155000
b11 b
b11 v
1(
#160000
0(
#165000
1E
1P
1Q
1(
#170000
0(
#175000
b11 <
b11111111111111111111110000000000 /
b0 0
b0 W
11
b1111111111111111111111111111111111111111111111111111101100000000 .
b1111111111111111111111111111111111111111111111111111101100000000 V
b0 T
1(
#180000
0(
#185000
b0 d
b0 x
b10 <
0=
b11111111111111111111110000000000 ?
12
b1111111111111111111111111111111111111111111111111111101100000000 B
b1111111111111111111111111111111111111111111111111111101100000000 C
b11 ;
b11 :
1(
#190000
0(
#195000
b1 d
b1 x
b11 <
b0 b
b0 v
1=
b11111111111111111111110000000000 "
b11111111111111111111110000000000 >
02
b1111111111111111111111111111111111111111111111111111101100000000 !
b1111111111111111111111111111111111111111111111111111101100000000 A
b1111111111111111111111111111111111111111111111111111101100000000 D
b10 :
1(
#200000
0(
#205000
b10 <
b10 x
0E
b10 d
0=
b100 ;
b11 :
0t
0P
b1 v
0`
0Q
b1 b
1(
#210000
0(
#215000
b1000000000000 Z
b1000000000000 j
b1000000010000 n
b1000000010000 ~
b1111111111111111111111111111111111111111111111111111111100000000 a
b1111111111111111111111111111111111111111111111111111000000000000 c
b1111111111111111111111111111111111111111111111111111111100001000 u
b1111111111111111111111111111111111111111111111111110111111111000 w
b0 J
b0 f
b100000000000000000000 i
b11111111111111111111110000000000 e
b11111111111111111111110000000000 g
b11111111111111111111110000000000 h
b10 b
b0 I
b0 z
b100000001000000000100 }
b11111111111111111111101111111110 y
b11111111111111111111101111111110 {
b11111111111111111111101111111110 |
b10 v
01
1=
b10 :
1(
#220000
0(
#225000
1'"
b11111111111111111111111000000000 H
b11111111111111111111111000000000 %"
0L
b111111111111111111111111 &"
b1111111111111111111111111111111111111111111111100000000000000000 $"
b11111111111111111111110000000000 #"
b11 x
b11 d
b1111111111111111111111111111111111111111111111111111110000000000 O
1t
b1111111111111111111111111111111111111111111111111111111100001000 I
b1111111111111111111111111111111111111111111111111111111100001000 z
1`
b1111111111111111111111111111111111111111111111111111111100000000 J
b1111111111111111111111111111111111111111111111111111111100000000 f
1(
#230000
0(
#235000
b11 b
b11 v
1(
#240000
0(
#245000
1E
1P
1Q
1(
#250000
0(
#255000
b11 <
b11111111111111111111111000000000 /
b11111111111111111111111000000000 0
b11111111111111111111111000000000 W
11
b1111111111111111111111111111111111111111111111111111111100000000 .
b1111111111111111111111111111111111111111111111111111111100000000 V
b1111111111111111111111111111111111111111111111111111110000000000 T
1(
#260000
0(
#265000
b0 d
b0 x
b10 <
0=
b1111111111111111111111111111111111111111111111111111111100000000 B
b1111111111111111111111111111111111111111111111111111111100000000 C
b101 ;
b11 :
1(
#270000
0(
#275000
b1 d
b1 x
b11 <
b0 b
b0 v
1=
b0 /
b11111111111111111111110111111110 G
b11111111111111111111110111111110 m
b11111111111111111111111000000000 @
b11111111111111111111111000000000 F
b11111111111111111111111000000000 Y
b10 :
1(
#280000
0(
#285000
b10 <
b10 x
0E
b10 d
0=
b11111111111111111111111000000000 ?
b110 ;
b11 :
0t
0P
b1 v
0`
0Q
b1 b
1(
#290000
0(
#295000
0'"
0K
b0 H
b0 %"
b0 &"
b0 $"
b0 #"
b10000000000 Z
b10000000000 j
b0 O
b10000001000 n
b10000001000 ~
b1111111111111111111111111111111111111111111111111111101100000000 a
b1111111111111111111111111111111111111111111111111111100000000000 c
b1111111111111111111111111111111111111111111111111111101100000000 u
b1111111111111111111111111111111111111111111111111111011111111000 w
b0 J
b0 f
b1000000000000000000 i
b11111111111111111111111000000000 e
b11111111111111111111111000000000 g
b11111111111111111111111000000000 h
b10 b
b0 I
b0 z
b1000000100000000100 }
b11111111111111111111110111111110 y
b11111111111111111111110111111110 {
b11111111111111111111110111111110 |
b10 v
01
1=
b1000000000 /
b11111111111111111111111111111110 G
b11111111111111111111111111111110 m
b0 @
b0 F
b0 Y
b10 :
1(
#300000
0(
#305000
b11 x
b11 d
1t
b1111111111111111111111111111111111111111111111111111101100000000 I
b1111111111111111111111111111111111111111111111111111101100000000 z
1`
b1111111111111111111111111111111111111111111111111111101100000000 J
b1111111111111111111111111111111111111111111111111111101100000000 f
1(
#310000
0(
#315000
b11 b
b11 v
1(
#320000
0(
#325000
1E
1P
1Q
1(
#330000
0(
#335000
b11 <
b0 /
b0 0
b0 W
11
b1111111111111111111111111111111111111111111111111111101100000000 .
b1111111111111111111111111111111111111111111111111111101100000000 V
b0 T
1(
#340000
0(
#345000
b0 d
b0 x
b10 <
0=
b0 ?
b1111111111111111111111111111111111111111111111111111101100000000 B
b1111111111111111111111111111111111111111111111111111101100000000 C
b111 ;
b11 :
1(
#350000
0(
#355000
b1 d
b1 x
b11 <
b0 b
b0 v
1=
b10 :
1(
#360000
0(
#365000
b10 <
b10 x
0E
b10 d
0=
b1000 ;
b11 :
0t
0P
b1 v
0`
0Q
b1 b
1(
#370000
0(
#375000
b0 Z
b0 j
b0 n
b0 ~
b1111111111111111111111111111111111111111111111111111111100000000 a
b0 c
b1111111111111111111111111111111111111111111111111111111011111000 u
b1111111111111111111111111111111111111111111111111111111111111000 w
b0 J
b0 f
b0 i
b0 e
b0 g
b0 h
b10 b
b0 I
b0 z
b100 }
b11111111111111111111111111111110 y
b11111111111111111111111111111110 {
b11111111111111111111111111111110 |
b10 v
01
1=
b10 :
1(
#380000
0(
#385000
b1000000000 H
b1000000000 %"
b100000000000000000 $"
b10000000000 #"
b11 x
b11 d
b10000000000 O
1t
b1111111111111111111111111111111111111111111111111111111011111000 I
b1111111111111111111111111111111111111111111111111111111011111000 z
1`
b1111111111111111111111111111111111111111111111111111111100000000 J
b1111111111111111111111111111111111111111111111111111111100000000 f
1(
#390000
0(
#395000
b11 b
b11 v
1(
#400000
0(
#405000
1E
1P
1Q
1(
#410000
0(
#415000
b11 <
b11111111111111111111111000000000 /
b1000000000 0
b1000000000 W
11
b1111111111111111111111111111111111111111111111111111111100000000 .
b1111111111111111111111111111111111111111111111111111111100000000 V
b10000000000 T
1(
#420000
0(
#425000
b0 d
b0 x
b10 <
0=
b1111111111111111111111111111111111111111111111111111111100000000 B
b1111111111111111111111111111111111111111111111111111111100000000 C
b1001 ;
b11 :
1(
#430000
0(
#435000
b1 d
b1 x
b11 <
b0 b
b0 v
1=
b11111111111111111111110000000000 /
b11111111111111111111110111111110 G
b11111111111111111111110111111110 m
b11111111111111111111111000000000 @
b11111111111111111111111000000000 F
b11111111111111111111111000000000 Y
b10 :
1(
#440000
0(
#445000
b10 <
b10 x
0E
b10 d
0=
b11111111111111111111111000000000 ?
b1010 ;
b11 :
0t
0P
b1 v
0`
0Q
b1 b
1(
#450000
0(
#455000
b0 H
b0 %"
b0 $"
b0 #"
b10000000000 Z
b10000000000 j
b0 O
b10000001000 n
b10000001000 ~
b1111111111111111111111111111111111111111111111111111101100000000 a
b1111111111111111111111111111111111111111111111111111100000000000 c
b1111111111111111111111111111111111111111111111111111101100000000 u
b1111111111111111111111111111111111111111111111111111011111111000 w
b0 J
b0 f
b1000000000000000000 i
b11111111111111111111111000000000 e
b11111111111111111111111000000000 g
b11111111111111111111111000000000 h
b10 b
b0 I
b0 z
b1000000100000000100 }
b11111111111111111111110111111110 y
b11111111111111111111110111111110 {
b11111111111111111111110111111110 |
b10 v
01
1=
b11111111111111111111101000000000 /
b11111111111111111111101111111110 G
b11111111111111111111101111111110 m
b11111111111111111111110000000000 @
b11111111111111111111110000000000 F
b11111111111111111111110000000000 Y
b10 :
1(
#460000
0(
