Internship_IITH/fixed_32_add_sub.v
module fixed_32_add_sub(
    input signed [31:0] a_in,      // Input operand A (Q16.16)
    input signed [31:0] b_in,      // Input operand B (Q16.16)
    input               sub_n_add, // Control signal: 0 for Add, 1 for Subtract
    output signed [31:0] sum_diff_out, // Result (A+B or A-B) (Q16.16)
    output logic         overflow    // Flag for overflow detection
);
    wire signed [32:0] temp_result_wide; // 1 bit extra wide to deetect overflow 

    assign temp_result_wide = (sub_n_add == 1'b1) ?
                              ($signed({1'b0, a_in}) - $signed({1'b0, b_in})) : // if 1 then Subtraction
                              ($signed({1'b0, a_in}) + $signed({1'b0, b_in})); // else Addition

    // Assign the lower 32 bits of the wide result to the output
    assign sum_diff_out = temp_result_wide[31:0];

    // Overflow detection
    assign overflow = (temp_result_wide[32] != sum_diff_out[31]);

endmodule

Internship_IITH/Linear_regressor_Q24.8/fixed_56_mult.v
module fixed_56_mult(
    input signed [31:0] a_in,    // Input operand A (Q24.8 format)
    input signed [31:0] b_in,    // Input operand B (Q24.8 format)
    output signed [55:0] p_out,  // Product P (Q47.8 format)
    output logic overflow        // Flag for overflow detection
);

    localparam integer FRACT_BITS = 8;
    wire signed [63:0] product_full;

    assign product_full = a_in * b_in;
    assign p_out = product_full >>> FRACT_BITS;

    assign overflow = (product_full[63:56] != {8{p_out[63]}});

endmodule

Internship_IITH/Linear_regressor_Q24.8/fixed_32_mult.v
module fixed_32_mult(
    input signed [31:0] a_in,    // Input operand A (Q24.8 format)
    input signed [31:0] b_in,    // Input operand B (Q24.8 format)
    output signed [31:0] p_out,  // Product P (Q24.8 format)
    output logic overflow        // Flag for overflow detection
);

    localparam integer FRACT_BITS = 8;
    wire signed [63:0] product_full;

    assign product_full = a_in * b_in;
    assign p_out = product_full >>> FRACT_BITS;

    assign overflow = (product_full[63:31] != {33{p_out[31]}});

endmodule

Internship_IITH/Linear_regressor_Q24.8/fixed_56_cmp.v
module fixed_56_cmp(
    input signed [55:0]a,
    input signed [55:0]b,
    output logic res    // Output 1 if b > a
);
    assign res = b > a;
endmodule

Internship_IITH/Linear_regressor_Q24.8/gradient_func.v
module gradient_func(
    input signed [31:0] offset,
    input signed [31:0]x,
    output signed [31:0]res,
    output logic overflow
);
    wire [31:0] diff_out;
    assign diff_out = x - offset;
    assign overflow = diff_out[31] != diff_out[30];
    assign res = diff_out << 1;  // 2*(x - OFFSET) {Slope of (x - OFFSET)^2}
endmodule

Internship_IITH/Linear_regressor_Q24.8/Top.v

module Top #(
    parameter NUM_ITERATIONS = 16,
    parameter OFFSET = 32'h00000400,        // Offset of 4 from Y axis
    parameter LEARNING_RATE = 32'h00000080  // Learning Rate of 0.5
) (
    input clk,
    input rst_n,                            // Active Low reset
    input start_op,                         // Level Dtected Operation Start 
    input signed [31:0] initial_x_in,       // Initial X
    output reg signed [31:0] x_at_min,      // X at minimum value of function
    output reg signed [55:0] y_min,         // Minimum Values of fucntion
    output reg done_op,                      // Flag to signal Completion of operation
    // FOR DEBUGGING
    output reg signed [31:0] learning_rate_out,   // Outputs the value of learning rate 
    output wire gradient_overflow,
    output wire x_sqr_overflow,
    output wire x_diff_overflow,
    output wire init_x_square_overflow
);

// Internal register Declaration
reg signed [31:0] x;
reg [$clog2(NUM_ITERATIONS + 1) -1 : 0] iter_count;

// Register to hold current and next state

reg [1:0] current_state;
reg [1:0] next_state;

// Internal Wire Declaration

wire comp_result;
wire signed [31:0] gradient_out;
wire signed [55:0] x_squared_out;
wire signed [31:0] x_diff_out;
wire signed [31:0] x_next_val;
wire signed [55:0] initial_y_min_val;
wire signed [31:0] x_minus_offset;
wire signed [31:0] initial_x_minus_offset;
// State Machine State declaration

localparam STATE_IDLE     = 2'b00;
localparam STATE_INIT     = 2'b01;
localparam STATE_RUNNING  = 2'b10;
localparam STATE_DONE     = 2'b11;

always @(*) begin
    next_state = current_state;
    case (current_state)
        STATE_IDLE: begin                   // IF start_op is Set - Start Operation.
            if (start_op)
                next_state = STATE_INIT;
        end
        STATE_INIT: begin                   // Start RUNNING after INIT
            next_state = STATE_RUNNING;
        end
        STATE_RUNNING: begin                    // KEEP RUNNING iterations unto NUM_ITERATIONS
            if ( iter_count == NUM_ITERATIONS)  // Upon reaching NUM_ITERATIONS Move to DONE
                next_state = STATE_DONE;
        end
        STATE_DONE: begin                   // IF start_op is UN-SET 
            if (!start_op)
                next_state = STATE_IDLE;
        end 
    endcase
end


//           STATE_IDLE---------( start_op == 1)--------->STATE_INIT
//               ^           MOVE TO IDLE WHENEVER            |
//          (start_op == 0 )   start_op is UNSET              |
//               |                                            v    
//           STATE_DONE<---(iter_count == NUM_ITERATIONS)---STATE_RUNNING <----
//                                                            |               |
//                                                            L > (iter_count < NUM_ITERATIONS)

 always @(posedge clk, negedge rst_n) begin
    if (!rst_n) begin
        // When RESET is LOW defauly Values are loaded into the register
        current_state <= STATE_IDLE;    
        x <= 32'b0;
        y_min <= 32'd0;
        x_at_min <= 32'd0;
        learning_rate_out <= LEARNING_RATE;
        iter_count <= 0;
        done_op <= 1'b0;
    end else begin
        current_state <= next_state;
        case (current_state)
            STATE_IDLE : begin
                // DO NOTHING
                done_op <= 1'b0;
            end
            STATE_INIT : begin
                x <= initial_x_in;           // Initialize x
                y_min <= initial_y_min_val;  // Initialize y_min
                x_at_min <= initial_x_in;    // Initialize x_at_min
                iter_count <= 0;
                
            end
            STATE_RUNNING : begin
                iter_count <= iter_count + 1;

                if (comp_result) begin
                    y_min <= x_squared_out;
                    x_at_min <= x;
                end

                x <= x_next_val;
            end
            STATE_DONE : begin
                done_op <= 1'b1;
            end
        endcase
    end
 end

// ALL CALCULATIONS ARE DONE IN FIXED POINT Q24.8 FORMAT

// Calculate gradient
    gradient_func inst_grad (
        .x(x), // Use the current value of x
        .offset(OFFSET),
        .res(gradient_out), // Output of the gradient calculation
        .overflow(gradient_overflow)
    );

    fixed_32_add_sub inst_x_minus_offset(
        .a_in(x),
        .b_in(OFFSET),
        .sub_n_add(1'b1),
        .sum_diff_out(x_minus_offset),
        .overflow()
    );

    // Calculate y = (x-OFFSET)^2
    fixed_56_mult inst_mult_y ( // Q47.8 format
        .a_in(x_minus_offset),
        .b_in(x_minus_offset),
        .p_out(x_squared_out),
        .overflow(x_sqr_overflow)
    );

    fixed_56_cmp cmp_fixed(
        .a(x_squared_out),
        .b(y_min),
        .res(comp_result)    // Output 1 if y_min > x_squared_out 
    );

    // Calculate x_diff = learning_rate * gradient
    fixed_32_mult inst_mult_x_diff ( // Q24.8 format
        .a_in(learning_rate_out), //Learning rate is always less than 1
        .b_in(gradient_out), //gradient out from gradient_func
        .p_out(x_diff_out), // Output = learning_rate * gradient
        .overflow(x_diff_overflow)
    );

    fixed_32_add_sub inst_initial_x_minus_offset(
        .a_in(initial_x_in),
        .b_in(OFFSET),
        .sub_n_add(1'b1),
        .sum_diff_out(initial_x_minus_offset),
        .overflow()
    );
    
    // Fix the initial square calculation:
    fixed_56_mult inst_initial_x_square ( // Q47.8 format
        .a_in(initial_x_minus_offset),    // Use (initial_x_in - OFFSET)
        .b_in(initial_x_minus_offset),    // instead of just initial_x_in
        .p_out(initial_y_min_val),
        .overflow(init_x_square_overflow)
    );

    // Calculate x = x - x_diff
    fixed_32_add_sub inst_sub_x ( 
        .a_in(x), 
        .b_in(x_diff_out),  // Use the combinational x_diff output
        .sub_n_add(1'b1), // Set to subtract
        .sum_diff_out(x_next_val), // Output of x - x_diff
        .overflow()
    );
endmodule

Internship_IITH/Linear_regressor_Q24.8/tb_Top.v
`timescale 1ns / 1ps

module tb_Top;

    // Parameters for the Top module (can be overridden here for testing)
    parameter NUM_ITERATIONS = 5;
    parameter OFFSET = 32'h00000400;        // Offset of 4 (Q24.8)
    parameter LEARNING_RATE = 32'h00000080; // Learning Rate of 0.5 (Q24.8)
    parameter INCREMENT = 32'h00000001;     // 1.0 Increment between test cases (Q24.8)
    parameter LOOP_COUNT = 10;

    // Inputs to the Top module
    reg clk;
    reg rst_n;
    reg start_op;
    reg signed [31:0] initial_x_in;
    reg signed [31:0] test_x_val;

    // Outputs from the Top module
    wire signed [31:0] x_at_min;
    wire signed [55:0] y_min;
    wire done_op;
    wire signed [31:0] learning_rate_out; // Renamed to avoid conflict with parameter
    wire x_sqr_overflow;
    wire x_diff_overflow;
    wire init_x_square_overflow;
    wire gradient_overflow;
    // Instantiate the Top module
    Top #(
        .NUM_ITERATIONS(NUM_ITERATIONS),
        .OFFSET(OFFSET),
        .LEARNING_RATE(LEARNING_RATE)
    ) uut_top (
        .clk(clk),
        .rst_n(rst_n),
        .start_op(start_op),
        .initial_x_in(initial_x_in),
        .x_at_min(x_at_min),
        .y_min(y_min),
        .done_op(done_op),
        .learning_rate_out(learning_rate_out),
        .gradient_overflow(gradient_overflow),
        .x_sqr_overflow(x_sqr_overflow),
        .x_diff_overflow(x_diff_overflow),
        .init_x_square_overflow(init_x_square_overflow)
    );


    // Clock Generation
    initial begin
        clk = 0;
        forever #5 clk = ~clk; // 10ns period (100 MHz)
    end

    // Test sequence
    initial begin
        integer i;
        // For waveform dumping (optional)
        $dumpfile("tb_Top.vcd");
        $dumpvars(0, tb_Top);

        // Initialize inputs
        rst_n = 0; // Assert reset
        start_op = 0;
        initial_x_in = 32'b0;
        test_x_val = 32'h400003F8;

        $display("---------------------------------------------------------");
        $display("Starting Testbench for Fixed-Point Gradient Descent");
        $display("Parameters: NUM_ITERATIONS = %0d, OFFSET = %f, LEARNING_RATE = %f",
            NUM_ITERATIONS, $itor(OFFSET) / 256.0, $itor(LEARNING_RATE) / 256.0);
        $display("---------------------------------------------------------");
        #20 rst_n = 1; // Deassert reset        

        for(i = 0; i < LOOP_COUNT; i = i + 1 ) begin
            initial_x_in = test_x_val; // Q24.8 (2's complement)
            start_op = 1;
            #20;

            wait(done_op == 1'b1);

            if ($abs($itor(x_at_min) / 256.0 - $itor(OFFSET) / 256.0) > 0.1) begin
                $display("___TEST BENCH FAILED___");
                $display("\n--- Test Case %0d: Initial x = %f (Q24.8) ---", i, $itor(test_x_val) / 256.0);
                $display("Initial X: %f", $itor(test_x_val) / 256.0);
                $display("Final X at Min: %f (0x%H)", $itor(x_at_min) / 256.0, x_at_min);
                $display("Min Y Value: %f (0x%H)", $itor(y_min) / 256.0, y_min);
                $finish;
            end

            // Reset for next test
            start_op = 0;
            test_x_val = test_x_val + INCREMENT; // Increment set default to 1.0
            #20;
        end      
        $finish; // End simulation
    end
endmodule

Internship_IITH/Linear_regressor_Q24.8/tb_Top.vcd
$date
	Thu Jun 05 14:36:33 2025
$end
$version
	Icarus Verilog
$end
$timescale
	1ps
$end
$scope module tb_Top $end
$var wire 56 ! y_min [55:0] $end
$var wire 1 " x_sqr_overflow $end
$var wire 1 # x_diff_overflow $end
$var wire 32 $ x_at_min [31:0] $end
$var wire 32 % learning_rate_out [31:0] $end
$var wire 1 & init_x_square_overflow $end
$var wire 1 ' gradient_overflow $end
$var wire 1 ( done_op $end
$var parameter 32 ) INCREMENT $end
$var parameter 32 * LEARNING_RATE $end
$var parameter 32 + LOOP_COUNT $end
$var parameter 32 , NUM_ITERATIONS $end
$var parameter 32 - OFFSET $end
$var reg 1 . clk $end
$var reg 32 / initial_x_in [31:0] $end
$var reg 1 0 rst_n $end
$var reg 1 1 start_op $end
$var reg 32 2 test_x_val [31:0] $end
$scope module uut_top $end
$var wire 1 . clk $end
$var wire 32 3 initial_x_in [31:0] $end
$var wire 1 0 rst_n $end
$var wire 1 1 start_op $end
$var wire 56 4 x_squared_out [55:0] $end
$var wire 1 " x_sqr_overflow $end
$var wire 32 5 x_next_val [31:0] $end
$var wire 32 6 x_minus_offset [31:0] $end
$var wire 1 # x_diff_overflow $end
$var wire 32 7 x_diff_out [31:0] $end
$var wire 56 8 initial_y_min_val [55:0] $end
$var wire 32 9 initial_x_minus_offset [31:0] $end
$var wire 1 & init_x_square_overflow $end
$var wire 1 ' gradient_overflow $end
$var wire 32 : gradient_out [31:0] $end
$var wire 1 ; comp_result $end
$var parameter 32 < LEARNING_RATE $end
$var parameter 32 = NUM_ITERATIONS $end
$var parameter 32 > OFFSET $end
$var parameter 2 ? STATE_DONE $end
$var parameter 2 @ STATE_IDLE $end
$var parameter 2 A STATE_INIT $end
$var parameter 2 B STATE_RUNNING $end
$var reg 2 C current_state [1:0] $end
$var reg 1 ( done_op $end
$var reg 3 D iter_count [2:0] $end
$var reg 32 E learning_rate_out [31:0] $end
$var reg 2 F next_state [1:0] $end
$var reg 32 G x [31:0] $end
$var reg 32 H x_at_min [31:0] $end
$var reg 56 I y_min [55:0] $end
$scope module cmp_fixed $end
$var wire 56 J b [55:0] $end
$var wire 1 ; res $end
$var wire 56 K a [55:0] $end
$upscope $end
$scope module inst_grad $end
$var wire 32 L offset [31:0] $end
$var wire 1 ' overflow $end
$var wire 32 M x [31:0] $end
$var wire 32 N res [31:0] $end
$var wire 32 O diff_out [31:0] $end
$upscope $end
$scope module inst_initial_x_minus_offset $end
$var wire 32 P a_in [31:0] $end
$var wire 32 Q b_in [31:0] $end
$var wire 1 R overflow $end
$var wire 1 S sub_n_add $end
$var wire 33 T temp_result_wide [32:0] $end
$var wire 32 U sum_diff_out [31:0] $end
$upscope $end
$scope module inst_initial_x_square $end
$var wire 32 V a_in [31:0] $end
$var wire 32 W b_in [31:0] $end
$var wire 64 X product_full [63:0] $end
$var wire 56 Y p_out [55:0] $end
$var wire 1 & overflow $end
$var parameter 32 Z FRACT_BITS $end
$upscope $end
$scope module inst_mult_x_diff $end
$var wire 32 [ a_in [31:0] $end
$var wire 32 \ b_in [31:0] $end
$var wire 64 ] product_full [63:0] $end
$var wire 32 ^ p_out [31:0] $end
$var wire 1 # overflow $end
$var parameter 32 _ FRACT_BITS $end
$upscope $end
$scope module inst_mult_y $end
$var wire 64 ` product_full [63:0] $end
$var wire 56 a p_out [55:0] $end
$var wire 1 " overflow $end
$var wire 32 b b_in [31:0] $end
$var wire 32 c a_in [31:0] $end
$var parameter 32 d FRACT_BITS $end
$upscope $end
$scope module inst_sub_x $end
$var wire 32 e a_in [31:0] $end
$var wire 32 f b_in [31:0] $end
$var wire 1 g overflow $end
$var wire 1 h sub_n_add $end
$var wire 33 i temp_result_wide [32:0] $end
$var wire 32 j sum_diff_out [31:0] $end
$upscope $end
$scope module inst_x_minus_offset $end
$var wire 32 k a_in [31:0] $end
$var wire 32 l b_in [31:0] $end
$var wire 1 m overflow $end
$var wire 1 n sub_n_add $end
$var wire 33 o temp_result_wide [32:0] $end
$var wire 32 p sum_diff_out [31:0] $end
$upscope $end
$upscope $end
$scope begin $unm_blk_15 $end
$var integer 32 q i [31:0] $end
$upscope $end
$upscope $end
$enddefinitions $end
$comment Show the parameter values. $end
$dumpall
b1000 d
b1000 _
b1000 Z
b10 B
b1 A
b0 @
b11 ?
b10000000000 >
b101 =
b10000000 <
b10000000000 -
b101 ,
b1010 +
b10000000 *
b1 )
$end
#0
$dumpvars
bx q
b11111111111111111111110000000000 p
b111111111111111111111110000000000 o
1n
0m
b10000000000 l
b0 k
b10000000000 j
b10000000000 i
1h
0g
b11111111111111111111110000000000 f
b0 e
b11111111111111111111110000000000 c
b11111111111111111111110000000000 b
b1000000000000 a
b100000000000000000000 `
b11111111111111111111110000000000 ^
b1111111111111111111111111111111111111111111111000000000000000000 ]
b11111111111111111111100000000000 \
b10000000 [
b1000000000000 Y
b100000000000000000000 X
b11111111111111111111110000000000 W
b11111111111111111111110000000000 V
b11111111111111111111110000000000 U
b111111111111111111111110000000000 T
1S
0R
b10000000000 Q
b0 P
b11111111111111111111110000000000 O
b11111111111111111111100000000000 N
b0 M
b10000000000 L
b1000000000000 K
b0 J
b0 I
b0 H
b0 G
b0 F
b10000000 E
b0 D
b0 C
0;
b11111111111111111111100000000000 :
b11111111111111111111110000000000 9
b1000000000000 8
b11111111111111111111110000000000 7
b11111111111111111111110000000000 6
b10000000000 5
b1000000000000 4
b0 3
b1000000000000000000001111111000 2
01
00
b0 /
0.
0(
0'
x&
b10000000 %
b0 $
0#
x"
b0 !
$end
#5000
1.
#10000
0.
#15000
1.
#20000
b1111111111111111111111111100000000000000000000000000 8
b1111111111111111111111111100000000000000000000000000 Y
0R
b111111111111111111111111110000000000000000000000000001000000 X
b111111111111111111111111111000 9
b111111111111111111111111111000 U
b111111111111111111111111111000 V
b111111111111111111111111111000 W
b1 F
b111111111111111111111111111000 T
0.
11
b1000000000000000000001111111000 /
b1000000000000000000001111111000 3
b1000000000000000000001111111000 P
b0 q
10
#25000
b10 F
b1 C
1.
#30000
0.
#35000
0g
b1111111111111111111111111100000000000000000000000000 4
b1111111111111111111111111100000000000000000000000000 K
b1111111111111111111111111100000000000000000000000000 a
b111111111111111111111111111000 7
b111111111111111111111111111000 ^
b111111111111111111111111111000 f
0m
1#
b10000000000 5
b10000000000 j
b111111111111111111111111110000000000000000000000000001000000 `
b111111111111111111111111111000 6
b111111111111111111111111111000 b
b111111111111111111111111111000 c
b111111111111111111111111111000 p
b11111111111111111111111111100000000000 ]
b1111111111111111111111111110000 :
b1111111111111111111111111110000 N
b1111111111111111111111111110000 \
b10000000000 i
b111111111111111111111111111000 o
b1000000000000000000001111111000 $
b1000000000000000000001111111000 H
0;
b1111111111111111111111111100000000000000000000000000 !
b1111111111111111111111111100000000000000000000000000 I
b1111111111111111111111111100000000000000000000000000 J
b111111111111111111111111111000 O
b1000000000000000000001111111000 G
b1000000000000000000001111111000 M
b1000000000000000000001111111000 e
b1000000000000000000001111111000 k
b10 C
1.
#40000
0.
#45000
1;
b0 4
b0 K
b0 a
b0 7
b0 ^
b0 f
0g
0#
b10000000000 5
b10000000000 j
b0 `
b0 6
b0 b
b0 c
b0 p
b0 ]
b0 :
b0 N
b0 \
b10000000000 i
b0 o
b0 O
b10000000000 G
b10000000000 M
b10000000000 e
b10000000000 k
b1 D
1.
#50000
0.
#55000
b10000000000 $
b10000000000 H
0;
b0 !
b0 I
b0 J
b10 D
1.
#60000
0.
#65000
b11 D
1.
#70000
0.
#75000
b100 D
1.
#80000
0.
#85000
b11 F
b101 D
1.
#90000
0.
#95000
b110 D
b11 C
1.
#100000
0.
#105000
b0 F
b1000000000000000000001111111001 2
01
1(
1.
#110000
0.
#115000
b0 C
1.
#120000
0.
#125000
0(
b1 C
b1111111111111111111111111100100000000000000000000000 8
b1111111111111111111111111100100000000000000000000000 Y
b111111111111111111111111110010000000000000000000000000110001 X
b111111111111111111111111111001 9
b111111111111111111111111111001 U
b111111111111111111111111111001 V
b111111111111111111111111111001 W
b10 F
b111111111111111111111111111001 T
1.
11
b1000000000000000000001111111001 /
b1000000000000000000001111111001 3
b1000000000000000000001111111001 P
b1 q
#130000
0.
#135000
b1111111111111111111111111100100000000000000000000000 4
b1111111111111111111111111100100000000000000000000000 K
b1111111111111111111111111100100000000000000000000000 a
b111111111111111111111111111001 7
b111111111111111111111111111001 ^
b111111111111111111111111111001 f
1#
b10000000000 5
b10000000000 j
b111111111111111111111111110010000000000000000000000000110001 `
b111111111111111111111111111001 6
b111111111111111111111111111001 b
b111111111111111111111111111001 c
b111111111111111111111111111001 p
b11111111111111111111111111100100000000 ]
b1111111111111111111111111110010 :
b1111111111111111111111111110010 N
b1111111111111111111111111110010 \
b10000000000 i
b111111111111111111111111111001 o
b0 D
b1000000000000000000001111111001 $
b1000000000000000000001111111001 H
0;
b1111111111111111111111111100100000000000000000000000 !
b1111111111111111111111111100100000000000000000000000 I
b1111111111111111111111111100100000000000000000000000 J
b111111111111111111111111111001 O
b1000000000000000000001111111001 G
b1000000000000000000001111111001 M
b1000000000000000000001111111001 e
b1000000000000000000001111111001 k
b10 C
1.
#140000
0.
#145000
1;
b0 4
b0 K
b0 a
b0 7
b0 ^
b0 f
0g
0#
b10000000000 5
b10000000000 j
b0 `
b0 6
b0 b
b0 c
b0 p
b0 ]
b0 :
b0 N
b0 \
b10000000000 i
b0 o
b0 O
b10000000000 G
b10000000000 M
b10000000000 e
b10000000000 k
b1 D
1.
#150000
0.
#155000
b10000000000 $
b10000000000 H
0;
b0 !
b0 I
b0 J
b10 D
1.
#160000
0.
#165000
b11 D
1.
#170000
0.
#175000
b100 D
1.
#180000
0.
#185000
b11 F
b101 D
1.
#190000
0.
#195000
b110 D
b11 C
1.
#200000
0.
#205000
b0 F
b1000000000000000000001111111010 2
01
1(
1.
#210000
0.
#215000
b0 C
1.
#220000
0.
#225000
0(
b1 C
b1111111111111111111111111101000000000000000000000000 8
b1111111111111111111111111101000000000000000000000000 Y
b111111111111111111111111110100000000000000000000000000100100 X
b111111111111111111111111111010 9
b111111111111111111111111111010 U
b111111111111111111111111111010 V
b111111111111111111111111111010 W
b10 F
b111111111111111111111111111010 T
1.
11
b1000000000000000000001111111010 /
b1000000000000000000001111111010 3
b1000000000000000000001111111010 P
b10 q
#230000
0.
#235000
b1111111111111111111111111101000000000000000000000000 4
b1111111111111111111111111101000000000000000000000000 K
b1111111111111111111111111101000000000000000000000000 a
b111111111111111111111111111010 7
b111111111111111111111111111010 ^
b111111111111111111111111111010 f
1#
b10000000000 5
b10000000000 j
b111111111111111111111111110100000000000000000000000000100100 `
b111111111111111111111111111010 6
b111111111111111111111111111010 b
b111111111111111111111111111010 c
b111111111111111111111111111010 p
b11111111111111111111111111101000000000 ]
b1111111111111111111111111110100 :
b1111111111111111111111111110100 N
b1111111111111111111111111110100 \
b10000000000 i
b111111111111111111111111111010 o
b0 D
b1000000000000000000001111111010 $
b1000000000000000000001111111010 H
0;
b1111111111111111111111111101000000000000000000000000 !
b1111111111111111111111111101000000000000000000000000 I
b1111111111111111111111111101000000000000000000000000 J
b111111111111111111111111111010 O
b1000000000000000000001111111010 G
b1000000000000000000001111111010 M
b1000000000000000000001111111010 e
b1000000000000000000001111111010 k
b10 C
1.
#240000
0.
#245000
1;
b0 4
b0 K
b0 a
b0 7
b0 ^
b0 f
0g
0#
b10000000000 5
b10000000000 j
b0 `
b0 6
b0 b
b0 c
b0 p
b0 ]
b0 :
b0 N
b0 \
b10000000000 i
b0 o
b0 O
b10000000000 G
b10000000000 M
b10000000000 e
b10000000000 k
b1 D
1.
#250000
0.
#255000
b10000000000 $
b10000000000 H
0;
b0 !
b0 I
b0 J
b10 D
1.
#260000
0.
#265000
b11 D
1.
#270000
0.
#275000
b100 D
1.
#280000
0.
#285000
b11 F
b101 D
1.
#290000
0.
#295000
b110 D
b11 C
1.
#300000
0.
#305000
b0 F
b1000000000000000000001111111011 2
01
1(
1.
#310000
0.
#315000
b0 C
1.
#320000
0.
#325000
0(
b1 C
b1111111111111111111111111101100000000000000000000000 8
b1111111111111111111111111101100000000000000000000000 Y
b111111111111111111111111110110000000000000000000000000011001 X
b111111111111111111111111111011 9
b111111111111111111111111111011 U
b111111111111111111111111111011 V
b111111111111111111111111111011 W
b10 F
b111111111111111111111111111011 T
1.
11
b1000000000000000000001111111011 /
b1000000000000000000001111111011 3
b1000000000000000000001111111011 P
b11 q
#330000
0.
#335000
b1111111111111111111111111101100000000000000000000000 4
b1111111111111111111111111101100000000000000000000000 K
b1111111111111111111111111101100000000000000000000000 a
b111111111111111111111111111011 7
b111111111111111111111111111011 ^
b111111111111111111111111111011 f
1#
b10000000000 5
b10000000000 j
b111111111111111111111111110110000000000000000000000000011001 `
b111111111111111111111111111011 6
b111111111111111111111111111011 b
b111111111111111111111111111011 c
b111111111111111111111111111011 p
b11111111111111111111111111101100000000 ]
b1111111111111111111111111110110 :
b1111111111111111111111111110110 N
b1111111111111111111111111110110 \
b10000000000 i
b111111111111111111111111111011 o
b0 D
b1000000000000000000001111111011 $
b1000000000000000000001111111011 H
0;
b1111111111111111111111111101100000000000000000000000 !
b1111111111111111111111111101100000000000000000000000 I
b1111111111111111111111111101100000000000000000000000 J
b111111111111111111111111111011 O
b1000000000000000000001111111011 G
b1000000000000000000001111111011 M
b1000000000000000000001111111011 e
b1000000000000000000001111111011 k
b10 C
1.
#340000
0.
#345000
1;
b0 4
b0 K
b0 a
b0 7
b0 ^
b0 f
0g
0#
b10000000000 5
b10000000000 j
b0 `
b0 6
b0 b
b0 c
b0 p
b0 ]
b0 :
b0 N
b0 \
b10000000000 i
b0 o
b0 O
b10000000000 G
b10000000000 M
b10000000000 e
b10000000000 k
b1 D
1.
#350000
0.
#355000
b10000000000 $
b10000000000 H
0;
b0 !
b0 I
b0 J
b10 D
1.
#360000
0.
#365000
b11 D
1.
#370000
0.
#375000
b100 D
1.
#380000
0.
#385000
b11 F
b101 D
1.
#390000
0.
#395000
b110 D
b11 C
1.
#400000
0.
#405000
b0 F
b1000000000000000000001111111100 2
01
1(
1.
#410000
0.
#415000
b0 C
1.
#420000
0.
#425000
0(
b1 C
b1111111111111111111111111110000000000000000000000000 8
b1111111111111111111111111110000000000000000000000000 Y
b111111111111111111111111111000000000000000000000000000010000 X
b111111111111111111111111111100 9
b111111111111111111111111111100 U
b111111111111111111111111111100 V
b111111111111111111111111111100 W
b10 F
b111111111111111111111111111100 T
1.
11
b1000000000000000000001111111100 /
b1000000000000000000001111111100 3
b1000000000000000000001111111100 P
b100 q
#430000
0.
#435000
b1111111111111111111111111110000000000000000000000000 4
b1111111111111111111111111110000000000000000000000000 K
b1111111111111111111111111110000000000000000000000000 a
b111111111111111111111111111100 7
b111111111111111111111111111100 ^
b111111111111111111111111111100 f
1#
b10000000000 5
b10000000000 j
b111111111111111111111111111000000000000000000000000000010000 `
b111111111111111111111111111100 6
b111111111111111111111111111100 b
b111111111111111111111111111100 c
b111111111111111111111111111100 p
b11111111111111111111111111110000000000 ]
b1111111111111111111111111111000 :
b1111111111111111111111111111000 N
b1111111111111111111111111111000 \
b10000000000 i
b111111111111111111111111111100 o
b0 D
b1000000000000000000001111111100 $
b1000000000000000000001111111100 H
0;
b1111111111111111111111111110000000000000000000000000 !
b1111111111111111111111111110000000000000000000000000 I
b1111111111111111111111111110000000000000000000000000 J
b111111111111111111111111111100 O
b1000000000000000000001111111100 G
b1000000000000000000001111111100 M
b1000000000000000000001111111100 e
b1000000000000000000001111111100 k
b10 C
1.
#440000
0.
#445000
1;
b0 4
b0 K
b0 a
b0 7
b0 ^
b0 f
0g
0#
b10000000000 5
b10000000000 j
b0 `
b0 6
b0 b
b0 c
b0 p
b0 ]
b0 :
b0 N
b0 \
b10000000000 i
b0 o
b0 O
b10000000000 G
b10000000000 M
b10000000000 e
b10000000000 k
b1 D
1.
#450000
0.
#455000
b10000000000 $
b10000000000 H
0;
b0 !
b0 I
b0 J
b10 D
1.
#460000
0.
#465000
b11 D
1.
#470000
0.
#475000
b100 D
1.
#480000
0.
#485000
b11 F
b101 D
1.
#490000
0.
#495000
b110 D
b11 C
1.
#500000
0.
#505000
b0 F
b1000000000000000000001111111101 2
01
1(
1.
#510000
0.
#515000
b0 C
1.
#520000
0.
#525000
0(
b1 C
b1111111111111111111111111110100000000000000000000000 8
b1111111111111111111111111110100000000000000000000000 Y
b111111111111111111111111111010000000000000000000000000001001 X
b111111111111111111111111111101 9
b111111111111111111111111111101 U
b111111111111111111111111111101 V
b111111111111111111111111111101 W
b10 F
b111111111111111111111111111101 T
1.
11
b1000000000000000000001111111101 /
b1000000000000000000001111111101 3
b1000000000000000000001111111101 P
b101 q
#530000
0.
#535000
b1111111111111111111111111110100000000000000000000000 4
b1111111111111111111111111110100000000000000000000000 K
b1111111111111111111111111110100000000000000000000000 a
b111111111111111111111111111101 7
b111111111111111111111111111101 ^
b111111111111111111111111111101 f
1#
b10000000000 5
b10000000000 j
b111111111111111111111111111010000000000000000000000000001001 `
b111111111111111111111111111101 6
b111111111111111111111111111101 b
b111111111111111111111111111101 c
b111111111111111111111111111101 p
b11111111111111111111111111110100000000 ]
b1111111111111111111111111111010 :
b1111111111111111111111111111010 N
b1111111111111111111111111111010 \
b10000000000 i
b111111111111111111111111111101 o
b0 D
b1000000000000000000001111111101 $
b1000000000000000000001111111101 H
0;
b1111111111111111111111111110100000000000000000000000 !
b1111111111111111111111111110100000000000000000000000 I
b1111111111111111111111111110100000000000000000000000 J
b111111111111111111111111111101 O
b1000000000000000000001111111101 G
b1000000000000000000001111111101 M
b1000000000000000000001111111101 e
b1000000000000000000001111111101 k
b10 C
1.
#540000
0.
#545000
1;
b0 4
b0 K
b0 a
b0 7
b0 ^
b0 f
0g
0#
b10000000000 5
b10000000000 j
b0 `
b0 6
b0 b
b0 c
b0 p
b0 ]
b0 :
b0 N
b0 \
b10000000000 i
b0 o
b0 O
b10000000000 G
b10000000000 M
b10000000000 e
b10000000000 k
b1 D
1.
#550000
0.
#555000
b10000000000 $
b10000000000 H
0;
b0 !
b0 I
b0 J
b10 D
1.
#560000
0.
#565000
b11 D
1.
#570000
0.
#575000
b100 D
1.
#580000
0.
#585000
b11 F
b101 D
1.
#590000
0.
#595000
b110 D
b11 C
1.
#600000
0.
#605000
b0 F
b1000000000000000000001111111110 2
01
1(
1.
#610000
0.
#615000
b0 C
1.
#620000
0.
#625000
0(
b1 C
b1111111111111111111111111111000000000000000000000000 8
b1111111111111111111111111111000000000000000000000000 Y
b111111111111111111111111111100000000000000000000000000000100 X
b111111111111111111111111111110 9
b111111111111111111111111111110 U
b111111111111111111111111111110 V
b111111111111111111111111111110 W
b10 F
b111111111111111111111111111110 T
1.
11
b1000000000000000000001111111110 /
b1000000000000000000001111111110 3
b1000000000000000000001111111110 P
b110 q
#630000
0.
